<?xml version="1.0" encoding="utf-8"?><worksheet xmlns:r="http://schemas.openxmlformats.org/officeDocument/2006/relationships" xmlns="http://schemas.openxmlformats.org/spreadsheetml/2006/main"><dimension ref="A1:H170" /><sheetViews><sheetView workbookViewId="0"><pane ySplit="1" topLeftCell="A2" state="frozen" activePane="bottomLeft" /><selection pane="bottomLeft" activeCell="A1" sqref="A1" /></sheetView></sheetViews><sheetFormatPr defaultRowHeight="15" /><cols><col min="1" max="1" width="10.91883373260498" customWidth="1"/><col min="2" max="2" width="9.140625" customWidth="1"/><col min="3" max="3" width="9.140625" customWidth="1"/><col min="4" max="4" width="14.9159517288208" customWidth="1"/><col min="5" max="5" width="14.367587089538574" customWidth="1"/><col min="6" max="6" width="12.295881271362305" customWidth="1"/><col min="7" max="7" width="12.7286376953125" customWidth="1"/><col min="8" max="8" width="79.09896087646484" customWidth="1"/></cols><sheetData><row r="1"><c r="A1" s="0" t="s"><v>693</v></c><c r="B1" s="0" t="s"><v>692</v></c><c r="C1" s="0" t="s"><v>35</v></c><c r="D1" s="0" t="s"><v>708</v></c><c r="E1" s="0" t="s"><v>709</v></c><c r="F1" s="0" t="s"><v>710</v></c><c r="G1" s="0" t="s"><v>711</v></c><c r="H1" s="0" t="s"><v>33</v></c></row><row r="2"><c r="A2" s="0"><v>60606</v></c><c r="B2" s="0" t="s"><v>39</v></c><c r="C2" s="13"><v>1586</v></c><c r="D2" s="13"><v>701212809469</v></c><c r="E2" s="13"><v>442126613.789</v></c><c r="F2" s="13"><v>0</v></c><c r="G2" s="13"><v>59640569000</v></c><c r="H2" s="0" t="s"><v>41</v></c></row><row r="3"><c r="A3" s="0"><v>65121</v></c><c r="B3" s="0" t="s"><v>42</v></c><c r="C3" s="13"><v>1586</v></c><c r="D3" s="13"><v>289640033694</v></c><c r="E3" s="13"><v>182622972.064</v></c><c r="F3" s="13"><v>0</v></c><c r="G3" s="13"><v>9463058000</v></c><c r="H3" s="0" t="s"><v>44</v></c></row><row r="4"><c r="A4" s="0"><v>65126</v></c><c r="B4" s="0" t="s"><v>45</v></c><c r="C4" s="13"><v>1586</v></c><c r="D4" s="13"><v>2326038741</v></c><c r="E4" s="13"><v>1466607.025</v></c><c r="F4" s="13"><v>0</v></c><c r="G4" s="13"><v>311708786</v></c><c r="H4" s="0" t="s"><v>47</v></c></row><row r="5"><c r="A5" s="0"><v>60611</v></c><c r="B5" s="0" t="s"><v>48</v></c><c r="C5" s="13"><v>1586</v></c><c r="D5" s="13"><v>1161248222906</v></c><c r="E5" s="13"><v>732186773.585</v></c><c r="F5" s="13"><v>32937</v></c><c r="G5" s="13"><v>73009567000</v></c><c r="H5" s="0" t="s"><v>50</v></c></row><row r="6"><c r="A6" s="0"><v>60616</v></c><c r="B6" s="0" t="s"><v>51</v></c><c r="C6" s="13"><v>1586</v></c><c r="D6" s="13"><v>288659261210</v></c><c r="E6" s="13"><v>182004578.317</v></c><c r="F6" s="13"><v>0</v></c><c r="G6" s="13"><v>11940978000</v></c><c r="H6" s="0" t="s"><v>53</v></c></row><row r="7"><c r="A7" s="0"><v>65091</v></c><c r="B7" s="0" t="s"><v>54</v></c><c r="C7" s="13"><v>1586</v></c><c r="D7" s="13"><v>154964604194</v></c><c r="E7" s="13"><v>97707821.055</v></c><c r="F7" s="13"><v>0</v></c><c r="G7" s="13"><v>6409159000</v></c><c r="H7" s="0" t="s"><v>56</v></c></row><row r="8"><c r="A8" s="0"><v>60621</v></c><c r="B8" s="0" t="s"><v>57</v></c><c r="C8" s="13"><v>1586</v></c><c r="D8" s="13"><v>402300723823</v></c><c r="E8" s="13"><v>253657455.122</v></c><c r="F8" s="13"><v>-115948000</v></c><c r="G8" s="13"><v>27193858000</v></c><c r="H8" s="0" t="s"><v>59</v></c></row><row r="9"><c r="A9" s="0"><v>60626</v></c><c r="B9" s="0" t="s"><v>60</v></c><c r="C9" s="13"><v>1586</v></c><c r="D9" s="13"><v>470288237873</v></c><c r="E9" s="13"><v>296524740.147</v></c><c r="F9" s="13"><v>0</v></c><c r="G9" s="13"><v>45649674000</v></c><c r="H9" s="0" t="s"><v>62</v></c></row><row r="10"><c r="A10" s="0"><v>64825</v></c><c r="B10" s="0" t="s"><v>63</v></c><c r="C10" s="13"><v>1586</v></c><c r="D10" s="13"><v>197639499840</v></c><c r="E10" s="13"><v>124615069.256</v></c><c r="F10" s="13"><v>0</v></c><c r="G10" s="13"><v>11972883000</v></c><c r="H10" s="0" t="s"><v>65</v></c></row><row r="11"><c r="A11" s="0"><v>65096</v></c><c r="B11" s="0" t="s"><v>66</v></c><c r="C11" s="13"><v>1586</v></c><c r="D11" s="13"><v>272648738033</v></c><c r="E11" s="13"><v>171909670.891</v></c><c r="F11" s="13"><v>-2182481</v></c><c r="G11" s="13"><v>33676791000</v></c><c r="H11" s="0" t="s"><v>68</v></c></row><row r="12"><c r="A12" s="0"><v>60631</v></c><c r="B12" s="0" t="s"><v>69</v></c><c r="C12" s="13"><v>1586</v></c><c r="D12" s="13"><v>872588961696</v></c><c r="E12" s="13"><v>550182195.269</v></c><c r="F12" s="13"><v>-46967677</v></c><c r="G12" s="13"><v>61519519000</v></c><c r="H12" s="0" t="s"><v>71</v></c></row><row r="13"><c r="A13" s="0"><v>60636</v></c><c r="B13" s="0" t="s"><v>72</v></c><c r="C13" s="13"><v>1586</v></c><c r="D13" s="13"><v>27858782148</v></c><c r="E13" s="13"><v>17565436.411</v></c><c r="F13" s="13"><v>0</v></c><c r="G13" s="13"><v>1024986000</v></c><c r="H13" s="0" t="s"><v>74</v></c></row><row r="14"><c r="A14" s="0"><v>60641</v></c><c r="B14" s="0" t="s"><v>75</v></c><c r="C14" s="13"><v>1586</v></c><c r="D14" s="13"><v>390025525939</v></c><c r="E14" s="13"><v>245917733.883</v></c><c r="F14" s="13"><v>0</v></c><c r="G14" s="13"><v>13526265000</v></c><c r="H14" s="0" t="s"><v>77</v></c></row><row r="15"><c r="A15" s="0"><v>60646</v></c><c r="B15" s="0" t="s"><v>78</v></c><c r="C15" s="13"><v>1586</v></c><c r="D15" s="13"><v>87628009080</v></c><c r="E15" s="13"><v>55250951.501</v></c><c r="F15" s="13"><v>0</v></c><c r="G15" s="13"><v>4065841000</v></c><c r="H15" s="0" t="s"><v>80</v></c></row><row r="16"><c r="A16" s="0"><v>65101</v></c><c r="B16" s="0" t="s"><v>81</v></c><c r="C16" s="13"><v>1586</v></c><c r="D16" s="13"><v>24044345207</v></c><c r="E16" s="13"><v>15160368.983</v></c><c r="F16" s="13"><v>0</v></c><c r="G16" s="13"><v>1040062000</v></c><c r="H16" s="0" t="s"><v>83</v></c></row><row r="17"><c r="A17" s="0"><v>65106</v></c><c r="B17" s="0" t="s"><v>84</v></c><c r="C17" s="13"><v>1586</v></c><c r="D17" s="13"><v>4302670988</v></c><c r="E17" s="13"><v>2712907.306</v></c><c r="F17" s="13"><v>0</v></c><c r="G17" s="13"><v>1239986000</v></c><c r="H17" s="0" t="s"><v>86</v></c></row><row r="18"><c r="A18" s="0"><v>65111</v></c><c r="B18" s="0" t="s"><v>87</v></c><c r="C18" s="13"><v>1586</v></c><c r="D18" s="13"><v>533859333362</v></c><c r="E18" s="13"><v>336607398.084</v></c><c r="F18" s="13"><v>0</v></c><c r="G18" s="13"><v>17218186000</v></c><c r="H18" s="0" t="s"><v>89</v></c></row><row r="19"><c r="A19" s="0"><v>65116</v></c><c r="B19" s="0" t="s"><v>90</v></c><c r="C19" s="13"><v>1586</v></c><c r="D19" s="13"><v>244219273349</v></c><c r="E19" s="13"><v>153984409.426</v></c><c r="F19" s="13"><v>0</v></c><c r="G19" s="13"><v>7755128000</v></c><c r="H19" s="0" t="s"><v>92</v></c></row><row r="20"><c r="A20" s="0"><v>60656</v></c><c r="B20" s="0" t="s"><v>93</v></c><c r="C20" s="13"><v>1586</v></c><c r="D20" s="13"><v>293559494494</v></c><c r="E20" s="13"><v>185094258.823</v></c><c r="F20" s="13"><v>-18804498</v></c><c r="G20" s="13"><v>14531169000</v></c><c r="H20" s="0" t="s"><v>95</v></c></row><row r="21"><c r="A21" s="0"><v>60661</v></c><c r="B21" s="0" t="s"><v>96</v></c><c r="C21" s="13"><v>1586</v></c><c r="D21" s="13"><v>282350916084</v></c><c r="E21" s="13"><v>178027059.322</v></c><c r="F21" s="13"><v>259507</v></c><c r="G21" s="13"><v>13857148000</v></c><c r="H21" s="0" t="s"><v>98</v></c></row><row r="22"><c r="A22" s="0"><v>60666</v></c><c r="B22" s="0" t="s"><v>99</v></c><c r="C22" s="13"><v>1586</v></c><c r="D22" s="13"><v>2567478927</v></c><c r="E22" s="13"><v>1618839.172</v></c><c r="F22" s="13"><v>-81940000</v></c><c r="G22" s="13"><v>315464776</v></c><c r="H22" s="0" t="s"><v>101</v></c></row><row r="23"><c r="A23" s="0"><v>60671</v></c><c r="B23" s="0" t="s"><v>102</v></c><c r="C23" s="13"><v>1586</v></c><c r="D23" s="13"><v>13776057337</v></c><c r="E23" s="13"><v>8686038.674</v></c><c r="F23" s="13"><v>-1768051000</v></c><c r="G23" s="13"><v>2337704000</v></c><c r="H23" s="0" t="s"><v>104</v></c></row><row r="24"><c r="A24" s="0"><v>60676</v></c><c r="B24" s="0" t="s"><v>105</v></c><c r="C24" s="13"><v>1586</v></c><c r="D24" s="13"><v>858739297840</v></c><c r="E24" s="13"><v>541449746.431</v></c><c r="F24" s="13"><v>-57934626</v></c><c r="G24" s="13"><v>61246694000</v></c><c r="H24" s="0" t="s"><v>107</v></c></row><row r="25"><c r="A25" s="0"><v>60681</v></c><c r="B25" s="0" t="s"><v>108</v></c><c r="C25" s="13"><v>1586</v></c><c r="D25" s="13"><v>73606519</v></c><c r="E25" s="13"><v>46410.163</v></c><c r="F25" s="13"><v>-27631298</v></c><c r="G25" s="13"><v>59231000</v></c><c r="H25" s="0" t="s"><v>110</v></c></row><row r="26"><c r="A26" s="0"><v>60686</v></c><c r="B26" s="0" t="s"><v>111</v></c><c r="C26" s="13"><v>1586</v></c><c r="D26" s="13"><v>872588961696</v></c><c r="E26" s="13"><v>550182195.269</v></c><c r="F26" s="13"><v>-46967677</v></c><c r="G26" s="13"><v>61519519000</v></c><c r="H26" s="0" t="s"><v>113</v></c></row><row r="27"><c r="A27" s="0"><v>60691</v></c><c r="B27" s="0" t="s"><v>114</v></c><c r="C27" s="13"><v>1764</v></c><c r="D27" s="13"><v>4922953278</v></c><c r="E27" s="13"><v>2790789.84</v></c><c r="F27" s="13"><v>0</v></c><c r="G27" s="13"><v>247841316</v></c><c r="H27" s="0" t="s"><v>116</v></c></row><row r="28"><c r="A28" s="0"><v>60696</v></c><c r="B28" s="0" t="s"><v>117</v></c><c r="C28" s="13"><v>1764</v></c><c r="D28" s="13"><v>1493412625</v></c><c r="E28" s="13"><v>846605.796</v></c><c r="F28" s="13"><v>0</v></c><c r="G28" s="13"><v>48565597</v></c><c r="H28" s="0" t="s"><v>119</v></c></row><row r="29"><c r="A29" s="0"><v>60701</v></c><c r="B29" s="0" t="s"><v>120</v></c><c r="C29" s="13"><v>1764</v></c><c r="D29" s="13"><v>2104343360</v></c><c r="E29" s="13"><v>1192938.413</v></c><c r="F29" s="13"><v>0</v></c><c r="G29" s="13"><v>27376000</v></c><c r="H29" s="0" t="s"><v>122</v></c></row><row r="30"><c r="A30" s="0"><v>60706</v></c><c r="B30" s="0" t="s"><v>123</v></c><c r="C30" s="13"><v>1764</v></c><c r="D30" s="13"><v>72797127</v></c><c r="E30" s="13"><v>41268.213</v></c><c r="F30" s="13"><v>0</v></c><c r="G30" s="13"><v>11609075</v></c><c r="H30" s="0" t="s"><v>125</v></c></row><row r="31"><c r="A31" s="0"><v>60711</v></c><c r="B31" s="0" t="s"><v>126</v></c><c r="C31" s="13"><v>1764</v></c><c r="D31" s="13"><v>8181757691</v></c><c r="E31" s="13"><v>4638184.632</v></c><c r="F31" s="13"><v>0</v></c><c r="G31" s="13"><v>433355044</v></c><c r="H31" s="0" t="s"><v>128</v></c></row><row r="32"><c r="A32" s="0"><v>60716</v></c><c r="B32" s="0" t="s"><v>129</v></c><c r="C32" s="13"><v>1764</v></c><c r="D32" s="13"><v>43051342204</v></c><c r="E32" s="13"><v>24405522.791</v></c><c r="F32" s="13"><v>0</v></c><c r="G32" s="13"><v>855558000</v></c><c r="H32" s="0" t="s"><v>131</v></c></row><row r="33"><c r="A33" s="0"><v>60721</v></c><c r="B33" s="0" t="s"><v>132</v></c><c r="C33" s="13"><v>1764</v></c><c r="D33" s="13"><v>59826606285</v></c><c r="E33" s="13"><v>33915309.685</v></c><c r="F33" s="13"><v>0</v></c><c r="G33" s="13"><v>1031962925</v></c><c r="H33" s="0" t="s"><v>134</v></c></row><row r="34"><c r="A34" s="0"><v>60726</v></c><c r="B34" s="0" t="s"><v>135</v></c><c r="C34" s="13"><v>1764</v></c><c r="D34" s="13"><v>49482623581</v></c><c r="E34" s="13"><v>28051373.912</v></c><c r="F34" s="13"><v>0</v></c><c r="G34" s="13"><v>897928000</v></c><c r="H34" s="0" t="s"><v>137</v></c></row><row r="35"><c r="A35" s="0"><v>60731</v></c><c r="B35" s="0" t="s"><v>138</v></c><c r="C35" s="13"><v>1764</v></c><c r="D35" s="13"><v>952462097</v></c><c r="E35" s="13"><v>539944.499</v></c><c r="F35" s="13"><v>0</v></c><c r="G35" s="13"><v>91060000</v></c><c r="H35" s="0" t="s"><v>140</v></c></row><row r="36"><c r="A36" s="0"><v>60733</v></c><c r="B36" s="0" t="s"><v>141</v></c><c r="C36" s="13"><v>1764</v></c><c r="D36" s="13"><v>50435085678</v></c><c r="E36" s="13"><v>28591318.412</v></c><c r="F36" s="13"><v>0</v></c><c r="G36" s="13"><v>988988000</v></c><c r="H36" s="0" t="s"><v>143</v></c></row><row r="37"><c r="A37" s="0"><v>61283</v></c><c r="B37" s="0" t="s"><v>144</v></c><c r="C37" s="13"><v>1764</v></c><c r="D37" s="13"><v>1209696087</v></c><c r="E37" s="13"><v>685768.757</v></c><c r="F37" s="13"><v>0</v></c><c r="G37" s="13"><v>39101000</v></c><c r="H37" s="0" t="s"><v>146</v></c></row><row r="38"><c r="A38" s="0"><v>61285</v></c><c r="B38" s="0" t="s"><v>147</v></c><c r="C38" s="13"><v>1764</v></c><c r="D38" s="13"><v>1195507910</v></c><c r="E38" s="13"><v>677725.573</v></c><c r="F38" s="13"><v>0</v></c><c r="G38" s="13"><v>39101000</v></c><c r="H38" s="0" t="s"><v>149</v></c></row><row r="39"><c r="A39" s="0"><v>61287</v></c><c r="B39" s="0" t="s"><v>150</v></c><c r="C39" s="13"><v>1764</v></c><c r="D39" s="13"><v>14188177</v></c><c r="E39" s="13"><v>8043.184</v></c><c r="F39" s="13"><v>0</v></c><c r="G39" s="13"><v>7852000</v></c><c r="H39" s="0" t="s"><v>152</v></c></row><row r="40"><c r="A40" s="0"><v>61289</v></c><c r="B40" s="0" t="s"><v>153</v></c><c r="C40" s="13"><v>1764</v></c><c r="D40" s="13"><v>821922853</v></c><c r="E40" s="13"><v>465942.66</v></c><c r="F40" s="13"><v>0</v></c><c r="G40" s="13"><v>111281170</v></c><c r="H40" s="0" t="s"><v>155</v></c></row><row r="41"><c r="A41" s="0"><v>61291</v></c><c r="B41" s="0" t="s"><v>156</v></c><c r="C41" s="13"><v>1764</v></c><c r="D41" s="13"><v>807264434</v></c><c r="E41" s="13"><v>457632.899</v></c><c r="F41" s="13"><v>0</v></c><c r="G41" s="13"><v>111281170</v></c><c r="H41" s="0" t="s"><v>158</v></c></row><row r="42"><c r="A42" s="0"><v>61293</v></c><c r="B42" s="0" t="s"><v>159</v></c><c r="C42" s="13"><v>1764</v></c><c r="D42" s="13"><v>14658419</v></c><c r="E42" s="13"><v>8309.761</v></c><c r="F42" s="13"><v>0</v></c><c r="G42" s="13"><v>5547073</v></c><c r="H42" s="0" t="s"><v>161</v></c></row><row r="43"><c r="A43" s="0"><v>61295</v></c><c r="B43" s="0" t="s"><v>162</v></c><c r="C43" s="13"><v>1764</v></c><c r="D43" s="13"><v>826777759</v></c><c r="E43" s="13"><v>468694.875</v></c><c r="F43" s="13"><v>0</v></c><c r="G43" s="13"><v>27376000</v></c><c r="H43" s="0" t="s"><v>164</v></c></row><row r="44"><c r="A44" s="0"><v>61297</v></c><c r="B44" s="0" t="s"><v>165</v></c><c r="C44" s="13"><v>1764</v></c><c r="D44" s="13"><v>823065061</v></c><c r="E44" s="13"><v>466590.171</v></c><c r="F44" s="13"><v>0</v></c><c r="G44" s="13"><v>27376000</v></c><c r="H44" s="0" t="s"><v>167</v></c></row><row r="45"><c r="A45" s="0"><v>61299</v></c><c r="B45" s="0" t="s"><v>168</v></c><c r="C45" s="13"><v>1764</v></c><c r="D45" s="13"><v>3712698</v></c><c r="E45" s="13"><v>2104.704</v></c><c r="F45" s="13"><v>0</v></c><c r="G45" s="13"><v>952892</v></c><c r="H45" s="0" t="s"><v>170</v></c></row><row r="46"><c r="A46" s="0"><v>61301</v></c><c r="B46" s="0" t="s"><v>171</v></c><c r="C46" s="13"><v>1764</v></c><c r="D46" s="13"><v>22534278</v></c><c r="E46" s="13"><v>12774.534</v></c><c r="F46" s="13"><v>0</v></c><c r="G46" s="13"><v>4958368</v></c><c r="H46" s="0" t="s"><v>173</v></c></row><row r="47"><c r="A47" s="0"><v>61303</v></c><c r="B47" s="0" t="s"><v>174</v></c><c r="C47" s="13"><v>1764</v></c><c r="D47" s="13"><v>22256921</v></c><c r="E47" s="13"><v>12617.302</v></c><c r="F47" s="13"><v>0</v></c><c r="G47" s="13"><v>4958368</v></c><c r="H47" s="0" t="s"><v>176</v></c></row><row r="48"><c r="A48" s="0"><v>61305</v></c><c r="B48" s="0" t="s"><v>177</v></c><c r="C48" s="13"><v>1764</v></c><c r="D48" s="13"><v>277357</v></c><c r="E48" s="13"><v>157.232</v></c><c r="F48" s="13"><v>0</v></c><c r="G48" s="13"><v>265357</v></c><c r="H48" s="0" t="s"><v>179</v></c></row><row r="49"><c r="A49" s="0"><v>61307</v></c><c r="B49" s="0" t="s"><v>180</v></c><c r="C49" s="13"><v>1764</v></c><c r="D49" s="13"><v>8736898436</v></c><c r="E49" s="13"><v>4952890.27</v></c><c r="F49" s="13"><v>0</v></c><c r="G49" s="13"><v>512884000</v></c><c r="H49" s="0" t="s"><v>182</v></c></row><row r="50"><c r="A50" s="0"><v>61309</v></c><c r="B50" s="0" t="s"><v>183</v></c><c r="C50" s="13"><v>1764</v></c><c r="D50" s="13"><v>8557925911</v></c><c r="E50" s="13"><v>4851431.922</v></c><c r="F50" s="13"><v>0</v></c><c r="G50" s="13"><v>512884000</v></c><c r="H50" s="0" t="s"><v>185</v></c></row><row r="51"><c r="A51" s="0"><v>61311</v></c><c r="B51" s="0" t="s"><v>186</v></c><c r="C51" s="13"><v>1764</v></c><c r="D51" s="13"><v>178972525</v></c><c r="E51" s="13"><v>101458.348</v></c><c r="F51" s="13"><v>0</v></c><c r="G51" s="13"><v>47082000</v></c><c r="H51" s="0" t="s"><v>188</v></c></row><row r="52"><c r="A52" s="0"><v>61313</v></c><c r="B52" s="0" t="s"><v>189</v></c><c r="C52" s="13"><v>1764</v></c><c r="D52" s="13"><v>38817256265</v></c><c r="E52" s="13"><v>22005247.316</v></c><c r="F52" s="13"><v>0</v></c><c r="G52" s="13"><v>845328026</v></c><c r="H52" s="0" t="s"><v>191</v></c></row><row r="53"><c r="A53" s="0"><v>61315</v></c><c r="B53" s="0" t="s"><v>192</v></c><c r="C53" s="13"><v>1764</v></c><c r="D53" s="13"><v>38076603344</v></c><c r="E53" s="13"><v>21585376.045</v></c><c r="F53" s="13"><v>0</v></c><c r="G53" s="13"><v>768570885</v></c><c r="H53" s="0" t="s"><v>194</v></c></row><row r="54"><c r="A54" s="0"><v>61317</v></c><c r="B54" s="0" t="s"><v>195</v></c><c r="C54" s="13"><v>1764</v></c><c r="D54" s="13"><v>740652921</v></c><c r="E54" s="13"><v>419871.27</v></c><c r="F54" s="13"><v>0</v></c><c r="G54" s="13"><v>76757141</v></c><c r="H54" s="0" t="s"><v>197</v></c></row><row r="55"><c r="A55" s="0"><v>60736</v></c><c r="B55" s="0" t="s"><v>198</v></c><c r="C55" s="13"><v>1766</v></c><c r="D55" s="13"><v>87779327069</v></c><c r="E55" s="13"><v>49705168.216</v></c><c r="F55" s="13"><v>0</v></c><c r="G55" s="13"><v>2511047000</v></c><c r="H55" s="0" t="s"><v>200</v></c></row><row r="56"><c r="A56" s="0"><v>65131</v></c><c r="B56" s="0" t="s"><v>201</v></c><c r="C56" s="13"><v>1766</v></c><c r="D56" s="13"><v>87779327069</v></c><c r="E56" s="13"><v>49705168.216</v></c><c r="F56" s="13"><v>0</v></c><c r="G56" s="13"><v>2511047000</v></c><c r="H56" s="0" t="s"><v>203</v></c></row><row r="57"><c r="A57" s="0"><v>65136</v></c><c r="B57" s="0" t="s"><v>204</v></c><c r="C57" s="13"><v>1766</v></c><c r="D57" s="13"><v>0</v></c><c r="E57" s="13"><v>0</v></c><c r="F57" s="13"><v>0</v></c><c r="G57" s="13"><v>0</v></c><c r="H57" s="0" t="s"><v>206</v></c></row><row r="58"><c r="A58" s="0"><v>65141</v></c><c r="B58" s="0" t="s"><v>207</v></c><c r="C58" s="13"><v>1766</v></c><c r="D58" s="13"><v>0</v></c><c r="E58" s="13"><v>0</v></c><c r="F58" s="13"><v>0</v></c><c r="G58" s="13"><v>0</v></c><c r="H58" s="0" t="s"><v>209</v></c></row><row r="59"><c r="A59" s="0"><v>60741</v></c><c r="B59" s="0" t="s"><v>210</v></c><c r="C59" s="13"><v>1766</v></c><c r="D59" s="13"><v>633121187</v></c><c r="E59" s="13"><v>358505.768</v></c><c r="F59" s="13"><v>0</v></c><c r="G59" s="13"><v>251604000</v></c><c r="H59" s="0" t="s"><v>212</v></c></row><row r="60"><c r="A60" s="0"><v>65146</v></c><c r="B60" s="0" t="s"><v>213</v></c><c r="C60" s="13"><v>1766</v></c><c r="D60" s="13"><v>626510011</v></c><c r="E60" s="13"><v>354762.181</v></c><c r="F60" s="13"><v>0</v></c><c r="G60" s="13"><v>248199000</v></c><c r="H60" s="0" t="s"><v>215</v></c></row><row r="61"><c r="A61" s="0"><v>65151</v></c><c r="B61" s="0" t="s"><v>216</v></c><c r="C61" s="13"><v>1766</v></c><c r="D61" s="13"><v>6611176</v></c><c r="E61" s="13"><v>3743.588</v></c><c r="F61" s="13"><v>0</v></c><c r="G61" s="13"><v>3405000</v></c><c r="H61" s="0" t="s"><v>218</v></c></row><row r="62"><c r="A62" s="0"><v>65156</v></c><c r="B62" s="0" t="s"><v>219</v></c><c r="C62" s="13"><v>1766</v></c><c r="D62" s="13"><v>0</v></c><c r="E62" s="13"><v>0</v></c><c r="F62" s="13"><v>0</v></c><c r="G62" s="13"><v>0</v></c><c r="H62" s="0" t="s"><v>221</v></c></row><row r="63"><c r="A63" s="0"><v>60746</v></c><c r="B63" s="0" t="s"><v>222</v></c><c r="C63" s="13"><v>1766</v></c><c r="D63" s="13"><v>1549572208</v></c><c r="E63" s="13"><v>877447.456</v></c><c r="F63" s="13"><v>0</v></c><c r="G63" s="13"><v>395006828</v></c><c r="H63" s="0" t="s"><v>224</v></c></row><row r="64"><c r="A64" s="0"><v>65161</v></c><c r="B64" s="0" t="s"><v>225</v></c><c r="C64" s="13"><v>1766</v></c><c r="D64" s="13"><v>1524199705</v></c><c r="E64" s="13"><v>863080.241</v></c><c r="F64" s="13"><v>0</v></c><c r="G64" s="13"><v>395006828</v></c><c r="H64" s="0" t="s"><v>227</v></c></row><row r="65"><c r="A65" s="0"><v>65166</v></c><c r="B65" s="0" t="s"><v>228</v></c><c r="C65" s="13"><v>1766</v></c><c r="D65" s="13"><v>25372503</v></c><c r="E65" s="13"><v>14367.216</v></c><c r="F65" s="13"><v>0</v></c><c r="G65" s="13"><v>12341270</v></c><c r="H65" s="0" t="s"><v>230</v></c></row><row r="66"><c r="A66" s="0"><v>65171</v></c><c r="B66" s="0" t="s"><v>231</v></c><c r="C66" s="13"><v>1766</v></c><c r="D66" s="13"><v>0</v></c><c r="E66" s="13"><v>0</v></c><c r="F66" s="13"><v>0</v></c><c r="G66" s="13"><v>0</v></c><c r="H66" s="0" t="s"><v>233</v></c></row><row r="67"><c r="A67" s="0"><v>60751</v></c><c r="B67" s="0" t="s"><v>234</v></c><c r="C67" s="13"><v>1766</v></c><c r="D67" s="13"><v>4356246</v></c><c r="E67" s="13"><v>2466.73</v></c><c r="F67" s="13"><v>0</v></c><c r="G67" s="13"><v>1546437</v></c><c r="H67" s="0" t="s"><v>236</v></c></row><row r="68"><c r="A68" s="0"><v>65176</v></c><c r="B68" s="0" t="s"><v>237</v></c><c r="C68" s="13"><v>1766</v></c><c r="D68" s="13"><v>4102734</v></c><c r="E68" s="13"><v>2323.179</v></c><c r="F68" s="13"><v>0</v></c><c r="G68" s="13"><v>1546437</v></c><c r="H68" s="0" t="s"><v>239</v></c></row><row r="69"><c r="A69" s="0"><v>65181</v></c><c r="B69" s="0" t="s"><v>240</v></c><c r="C69" s="13"><v>1766</v></c><c r="D69" s="13"><v>253512</v></c><c r="E69" s="13"><v>143.552</v></c><c r="F69" s="13"><v>0</v></c><c r="G69" s="13"><v>253512</v></c><c r="H69" s="0" t="s"><v>242</v></c></row><row r="70"><c r="A70" s="0"><v>65186</v></c><c r="B70" s="0" t="s"><v>243</v></c><c r="C70" s="13"><v>1766</v></c><c r="D70" s="13"><v>0</v></c><c r="E70" s="13"><v>0</v></c><c r="F70" s="13"><v>0</v></c><c r="G70" s="13"><v>0</v></c><c r="H70" s="0" t="s"><v>245</v></c></row><row r="71"><c r="A71" s="0"><v>60756</v></c><c r="B71" s="0" t="s"><v>246</v></c><c r="C71" s="13"><v>1766</v></c><c r="D71" s="13"><v>29267184597</v></c><c r="E71" s="13"><v>16572584.71</v></c><c r="F71" s="13"><v>0</v></c><c r="G71" s="13"><v>4011839000</v></c><c r="H71" s="0" t="s"><v>248</v></c></row><row r="72"><c r="A72" s="0"><v>65191</v></c><c r="B72" s="0" t="s"><v>249</v></c><c r="C72" s="13"><v>1766</v></c><c r="D72" s="13"><v>28713724360</v></c><c r="E72" s="13"><v>16259187.067</v></c><c r="F72" s="13"><v>0</v></c><c r="G72" s="13"><v>4011839000</v></c><c r="H72" s="0" t="s"><v>251</v></c></row><row r="73"><c r="A73" s="0"><v>65196</v></c><c r="B73" s="0" t="s"><v>252</v></c><c r="C73" s="13"><v>1766</v></c><c r="D73" s="13"><v>529951001</v></c><c r="E73" s="13"><v>300085.505</v></c><c r="F73" s="13"><v>0</v></c><c r="G73" s="13"><v>39847381</v></c><c r="H73" s="0" t="s"><v>254</v></c></row><row r="74"><c r="A74" s="0"><v>65201</v></c><c r="B74" s="0" t="s"><v>255</v></c><c r="C74" s="13"><v>1766</v></c><c r="D74" s="13"><v>23509236</v></c><c r="E74" s="13"><v>13312.138</v></c><c r="F74" s="13"><v>0</v></c><c r="G74" s="13"><v>20824936</v></c><c r="H74" s="0" t="s"><v>257</v></c></row><row r="75"><c r="A75" s="0"><v>60761</v></c><c r="B75" s="0" t="s"><v>258</v></c><c r="C75" s="13"><v>1766</v></c><c r="D75" s="13"><v>1780637630</v></c><c r="E75" s="13"><v>1008288.579</v></c><c r="F75" s="13"><v>0</v></c><c r="G75" s="13"><v>174837000</v></c><c r="H75" s="0" t="s"><v>260</v></c></row><row r="76"><c r="A76" s="0"><v>65206</v></c><c r="B76" s="0" t="s"><v>261</v></c><c r="C76" s="13"><v>1766</v></c><c r="D76" s="13"><v>1624226662</v></c><c r="E76" s="13"><v>919720.647</v></c><c r="F76" s="13"><v>0</v></c><c r="G76" s="13"><v>174837000</v></c><c r="H76" s="0" t="s"><v>263</v></c></row><row r="77"><c r="A77" s="0"><v>65211</v></c><c r="B77" s="0" t="s"><v>264</v></c><c r="C77" s="13"><v>1766</v></c><c r="D77" s="13"><v>153918555</v></c><c r="E77" s="13"><v>87156.6</v></c><c r="F77" s="13"><v>0</v></c><c r="G77" s="13"><v>17292221</v></c><c r="H77" s="0" t="s"><v>266</v></c></row><row r="78"><c r="A78" s="0"><v>65216</v></c><c r="B78" s="0" t="s"><v>267</v></c><c r="C78" s="13"><v>1766</v></c><c r="D78" s="13"><v>2492413</v></c><c r="E78" s="13"><v>1411.332</v></c><c r="F78" s="13"><v>0</v></c><c r="G78" s="13"><v>1782825</v></c><c r="H78" s="0" t="s"><v>269</v></c></row><row r="79"><c r="A79" s="0"><v>60766</v></c><c r="B79" s="0" t="s"><v>270</v></c><c r="C79" s="13"><v>1766</v></c><c r="D79" s="13"><v>666970544</v></c><c r="E79" s="13"><v>377673.015</v></c><c r="F79" s="13"><v>0</v></c><c r="G79" s="13"><v>227619032</v></c><c r="H79" s="0" t="s"><v>272</v></c></row><row r="80"><c r="A80" s="0"><v>65221</v></c><c r="B80" s="0" t="s"><v>273</v></c><c r="C80" s="13"><v>1766</v></c><c r="D80" s="13"><v>650612270</v></c><c r="E80" s="13"><v>368410.119</v></c><c r="F80" s="13"><v>0</v></c><c r="G80" s="13"><v>227619032</v></c><c r="H80" s="0" t="s"><v>275</v></c></row><row r="81"><c r="A81" s="0"><v>65226</v></c><c r="B81" s="0" t="s"><v>276</v></c><c r="C81" s="13"><v>1766</v></c><c r="D81" s="13"><v>14783274</v></c><c r="E81" s="13"><v>8371.05</v></c><c r="F81" s="13"><v>0</v></c><c r="G81" s="13"><v>3931295</v></c><c r="H81" s="0" t="s"><v>278</v></c></row><row r="82"><c r="A82" s="0"><v>65231</v></c><c r="B82" s="0" t="s"><v>279</v></c><c r="C82" s="13"><v>1766</v></c><c r="D82" s="13"><v>1575000</v></c><c r="E82" s="13"><v>891.846</v></c><c r="F82" s="13"><v>0</v></c><c r="G82" s="13"><v>1570000</v></c><c r="H82" s="0" t="s"><v>281</v></c></row><row r="83"><c r="A83" s="0"><v>60771</v></c><c r="B83" s="0" t="s"><v>282</v></c><c r="C83" s="13"><v>1766</v></c><c r="D83" s="13"><v>36896349088</v></c><c r="E83" s="13"><v>20892609.903</v></c><c r="F83" s="13"><v>0</v></c><c r="G83" s="13"><v>2843444000</v></c><c r="H83" s="0" t="s"><v>284</v></c></row><row r="84"><c r="A84" s="0"><v>65236</v></c><c r="B84" s="0" t="s"><v>285</v></c><c r="C84" s="13"><v>1766</v></c><c r="D84" s="13"><v>16258861560</v></c><c r="E84" s="13"><v>9206603.375</v></c><c r="F84" s="13"><v>-3265910</v></c><c r="G84" s="13"><v>1180304786</v></c><c r="H84" s="0" t="s"><v>287</v></c></row><row r="85"><c r="A85" s="0"><v>65251</v></c><c r="B85" s="0" t="s"><v>288</v></c><c r="C85" s="13"><v>1766</v></c><c r="D85" s="13"><v>12065404310</v></c><c r="E85" s="13"><v>6832052.271</v></c><c r="F85" s="13"><v>-9784132</v></c><c r="G85" s="13"><v>940330000</v></c><c r="H85" s="0" t="s"><v>290</v></c></row><row r="86"><c r="A86" s="0"><v>65266</v></c><c r="B86" s="0" t="s"><v>291</v></c><c r="C86" s="13"><v>1766</v></c><c r="D86" s="13"><v>8572083218</v></c><c r="E86" s="13"><v>4853954.257</v></c><c r="F86" s="13"><v>-739000</v></c><c r="G86" s="13"><v>1710717000</v></c><c r="H86" s="0" t="s"><v>293</v></c></row><row r="87"><c r="A87" s="0"><v>65281</v></c><c r="B87" s="0" t="s"><v>294</v></c><c r="C87" s="13"><v>1766</v></c><c r="D87" s="13"><v>27801778739</v></c><c r="E87" s="13"><v>15742796.568</v></c><c r="F87" s="13"><v>0</v></c><c r="G87" s="13"><v>2326344000</v></c><c r="H87" s="0" t="s"><v>296</v></c></row><row r="88"><c r="A88" s="0"><v>65241</v></c><c r="B88" s="0" t="s"><v>297</v></c><c r="C88" s="13"><v>1766</v></c><c r="D88" s="13"><v>8331967113</v></c><c r="E88" s="13"><v>4717988.173</v></c><c r="F88" s="13"><v>-3265910</v></c><c r="G88" s="13"><v>831543000</v></c><c r="H88" s="0" t="s"><v>299</v></c></row><row r="89"><c r="A89" s="0"><v>65256</v></c><c r="B89" s="0" t="s"><v>300</v></c><c r="C89" s="13"><v>1766</v></c><c r="D89" s="13"><v>10950724065</v></c><c r="E89" s="13"><v>6200863.004</v></c><c r="F89" s="13"><v>-9903633</v></c><c r="G89" s="13"><v>710886000</v></c><c r="H89" s="0" t="s"><v>302</v></c></row><row r="90"><c r="A90" s="0"><v>65271</v></c><c r="B90" s="0" t="s"><v>303</v></c><c r="C90" s="13"><v>1766</v></c><c r="D90" s="13"><v>8519087561</v></c><c r="E90" s="13"><v>4823945.391</v></c><c r="F90" s="13"><v>-739000</v></c><c r="G90" s="13"><v>1710717000</v></c><c r="H90" s="0" t="s"><v>305</v></c></row><row r="91"><c r="A91" s="0"><v>65286</v></c><c r="B91" s="0" t="s"><v>306</v></c><c r="C91" s="13"><v>1766</v></c><c r="D91" s="13"><v>9094570349</v></c><c r="E91" s="13"><v>5149813.335</v></c><c r="F91" s="13"><v>0</v></c><c r="G91" s="13"><v>1177325229</v></c><c r="H91" s="0" t="s"><v>308</v></c></row><row r="92"><c r="A92" s="0"><v>65246</v></c><c r="B92" s="0" t="s"><v>309</v></c><c r="C92" s="13"><v>1766</v></c><c r="D92" s="13"><v>7926894447</v></c><c r="E92" s="13"><v>4488615.202</v></c><c r="F92" s="13"><v>-407307</v></c><c r="G92" s="13"><v>1177325229</v></c><c r="H92" s="0" t="s"><v>311</v></c></row><row r="93"><c r="A93" s="0"><v>65261</v></c><c r="B93" s="0" t="s"><v>312</v></c><c r="C93" s="13"><v>1766</v></c><c r="D93" s="13"><v>1114680245</v></c><c r="E93" s="13"><v>631189.267</v></c><c r="F93" s="13"><v>-25000</v></c><c r="G93" s="13"><v>229444000</v></c><c r="H93" s="0" t="s"><v>314</v></c></row><row r="94"><c r="A94" s="0"><v>65276</v></c><c r="B94" s="0" t="s"><v>315</v></c><c r="C94" s="13"><v>1766</v></c><c r="D94" s="13"><v>52995657</v></c><c r="E94" s="13"><v>30008.866</v></c><c r="F94" s="13"><v>-124860</v></c><c r="G94" s="13"><v>14997484</v></c><c r="H94" s="0" t="s"><v>317</v></c></row><row r="95"><c r="A95" s="0"><v>60776</v></c><c r="B95" s="0" t="s"><v>318</v></c><c r="C95" s="13"><v>1766</v></c><c r="D95" s="13"><v>3030445101</v></c><c r="E95" s="13"><v>1715993.828</v></c><c r="F95" s="13"><v>0</v></c><c r="G95" s="13"><v>784706444</v></c><c r="H95" s="0" t="s"><v>320</v></c></row><row r="96"><c r="A96" s="0"><v>65291</v></c><c r="B96" s="0" t="s"><v>321</v></c><c r="C96" s="13"><v>1766</v></c><c r="D96" s="13"><v>2894010252</v></c><c r="E96" s="13"><v>1638737.402</v></c><c r="F96" s="13"><v>0</v></c><c r="G96" s="13"><v>784706444</v></c><c r="H96" s="0" t="s"><v>323</v></c></row><row r="97"><c r="A97" s="0"><v>65296</v></c><c r="B97" s="0" t="s"><v>324</v></c><c r="C97" s="13"><v>1766</v></c><c r="D97" s="13"><v>119938853</v></c><c r="E97" s="13"><v>67915.545</v></c><c r="F97" s="13"><v>0</v></c><c r="G97" s="13"><v>49049000</v></c><c r="H97" s="0" t="s"><v>326</v></c></row><row r="98"><c r="A98" s="0"><v>65301</v></c><c r="B98" s="0" t="s"><v>327</v></c><c r="C98" s="13"><v>1766</v></c><c r="D98" s="13"><v>16495996</v></c><c r="E98" s="13"><v>9340.881</v></c><c r="F98" s="13"><v>0</v></c><c r="G98" s="13"><v>5001850</v></c><c r="H98" s="0" t="s"><v>329</v></c></row><row r="99"><c r="A99" s="0"><v>60781</v></c><c r="B99" s="0" t="s"><v>330</v></c><c r="C99" s="13"><v>1766</v></c><c r="D99" s="13"><v>21341675724</v></c><c r="E99" s="13"><v>12084754.091</v></c><c r="F99" s="13"><v>-598921827</v></c><c r="G99" s="13"><v>1627243000</v></c><c r="H99" s="0" t="s"><v>332</v></c></row><row r="100"><c r="A100" s="0"><v>65306</v></c><c r="B100" s="0" t="s"><v>333</v></c><c r="C100" s="13"><v>1766</v></c><c r="D100" s="13"><v>16990918323</v></c><c r="E100" s="13"><v>9621131.553</v></c><c r="F100" s="13"><v>-509709000</v></c><c r="G100" s="13"><v>1782329000</v></c><c r="H100" s="0" t="s"><v>335</v></c></row><row r="101"><c r="A101" s="0"><v>65311</v></c><c r="B101" s="0" t="s"><v>336</v></c><c r="C101" s="13"><v>1766</v></c><c r="D101" s="13"><v>4114760088</v></c><c r="E101" s="13"><v>2329988.725</v></c><c r="F101" s="13"><v>-1445799000</v></c><c r="G101" s="13"><v>1105194000</v></c><c r="H101" s="0" t="s"><v>338</v></c></row><row r="102"><c r="A102" s="0"><v>65316</v></c><c r="B102" s="0" t="s"><v>339</v></c><c r="C102" s="13"><v>1766</v></c><c r="D102" s="13"><v>235997313</v></c><c r="E102" s="13"><v>133633.813</v></c><c r="F102" s="13"><v>-221299917</v></c><c r="G102" s="13"><v>47498000</v></c><c r="H102" s="0" t="s"><v>341</v></c></row><row r="103"><c r="A103" s="0"><v>60786</v></c><c r="B103" s="0" t="s"><v>342</v></c><c r="C103" s="13"><v>1766</v></c><c r="D103" s="13"><v>11590363993</v></c><c r="E103" s="13"><v>6563060.019</v></c><c r="F103" s="13"><v>0</v></c><c r="G103" s="13"><v>2074865000</v></c><c r="H103" s="0" t="s"><v>344</v></c></row><row r="104"><c r="A104" s="0"><v>65321</v></c><c r="B104" s="0" t="s"><v>345</v></c><c r="C104" s="13"><v>1766</v></c><c r="D104" s="13"><v>11590363993</v></c><c r="E104" s="13"><v>6563060.019</v></c><c r="F104" s="13"><v>0</v></c><c r="G104" s="13"><v>2074865000</v></c><c r="H104" s="0" t="s"><v>347</v></c></row><row r="105"><c r="A105" s="0"><v>60791</v></c><c r="B105" s="0" t="s"><v>348</v></c><c r="C105" s="13"><v>1658</v></c><c r="D105" s="13"><v>20387198122</v></c><c r="E105" s="13"><v>12296259.422</v></c><c r="F105" s="13"><v>0</v></c><c r="G105" s="13"><v>515975000</v></c><c r="H105" s="0" t="s"><v>350</v></c></row><row r="106"><c r="A106" s="0"><v>65326</v></c><c r="B106" s="0" t="s"><v>351</v></c><c r="C106" s="13"><v>1658</v></c><c r="D106" s="13"><v>20387198122</v></c><c r="E106" s="13"><v>12296259.422</v></c><c r="F106" s="13"><v>0</v></c><c r="G106" s="13"><v>515975000</v></c><c r="H106" s="0" t="s"><v>353</v></c></row><row r="107"><c r="A107" s="0"><v>60796</v></c><c r="B107" s="0" t="s"><v>354</v></c><c r="C107" s="13"><v>1573</v></c><c r="D107" s="13"><v>49227072052</v></c><c r="E107" s="13"><v>31295023.555</v></c><c r="F107" s="13"><v>0</v></c><c r="G107" s="13"><v>8718133000</v></c><c r="H107" s="0" t="s"><v>356</v></c></row><row r="108"><c r="A108" s="0"><v>65331</v></c><c r="B108" s="0" t="s"><v>357</v></c><c r="C108" s="13"><v>1573</v></c><c r="D108" s="13"><v>49227072052</v></c><c r="E108" s="13"><v>31295023.555</v></c><c r="F108" s="13"><v>0</v></c><c r="G108" s="13"><v>8718133000</v></c><c r="H108" s="0" t="s"><v>359</v></c></row><row r="109"><c r="A109" s="0"><v>60801</v></c><c r="B109" s="0" t="s"><v>360</v></c><c r="C109" s="13"><v>1573</v></c><c r="D109" s="13"><v>10710841667</v></c><c r="E109" s="13"><v>6809180.971</v></c><c r="F109" s="13"><v>0</v></c><c r="G109" s="13"><v>2673772000</v></c><c r="H109" s="0" t="s"><v>362</v></c></row><row r="110"><c r="A110" s="0"><v>65336</v></c><c r="B110" s="0" t="s"><v>363</v></c><c r="C110" s="13"><v>1573</v></c><c r="D110" s="13"><v>10687505677</v></c><c r="E110" s="13"><v>6794345.631</v></c><c r="F110" s="13"><v>0</v></c><c r="G110" s="13"><v>2673772000</v></c><c r="H110" s="0" t="s"><v>365</v></c></row><row r="111"><c r="A111" s="0"><v>65341</v></c><c r="B111" s="0" t="s"><v>366</v></c><c r="C111" s="13"><v>1573</v></c><c r="D111" s="13"><v>17259440</v></c><c r="E111" s="13"><v>10972.308</v></c><c r="F111" s="13"><v>0</v></c><c r="G111" s="13"><v>2934920</v></c><c r="H111" s="0" t="s"><v>368</v></c></row><row r="112"><c r="A112" s="0"><v>65346</v></c><c r="B112" s="0" t="s"><v>369</v></c><c r="C112" s="13"><v>1573</v></c><c r="D112" s="13"><v>6076550</v></c><c r="E112" s="13"><v>3863.032</v></c><c r="F112" s="13"><v>0</v></c><c r="G112" s="13"><v>4629969</v></c><c r="H112" s="0" t="s"><v>371</v></c></row><row r="113"><c r="A113" s="0"><v>60806</v></c><c r="B113" s="0" t="s"><v>372</v></c><c r="C113" s="13"><v>1766</v></c><c r="D113" s="13"><v>19337139366</v></c><c r="E113" s="13"><v>10949682.54</v></c><c r="F113" s="13"><v>-405791</v></c><c r="G113" s="13"><v>4895407378</v></c><c r="H113" s="0" t="s"><v>374</v></c></row><row r="114"><c r="A114" s="0"><v>65351</v></c><c r="B114" s="0" t="s"><v>375</v></c><c r="C114" s="13"><v>1766</v></c><c r="D114" s="13"><v>19327833088</v></c><c r="E114" s="13"><v>10944412.847</v></c><c r="F114" s="13"><v>-5263603</v></c><c r="G114" s="13"><v>4895407378</v></c><c r="H114" s="0" t="s"><v>377</v></c></row><row r="115"><c r="A115" s="0"><v>65356</v></c><c r="B115" s="0" t="s"><v>378</v></c><c r="C115" s="13"><v>1766</v></c><c r="D115" s="13"><v>-248203439</v></c><c r="E115" s="13"><v>-140545.549</v></c><c r="F115" s="13"><v>-56677000</v></c><c r="G115" s="13"><v>65196000</v></c><c r="H115" s="0" t="s"><v>380</v></c></row><row r="116"><c r="A116" s="0"><v>65361</v></c><c r="B116" s="0" t="s"><v>381</v></c><c r="C116" s="13"><v>1766</v></c><c r="D116" s="13"><v>257509717</v></c><c r="E116" s="13"><v>145815.242</v></c><c r="F116" s="13"><v>-7373000</v></c><c r="G116" s="13"><v>136925000</v></c><c r="H116" s="0" t="s"><v>383</v></c></row><row r="117"><c r="A117" s="0"><v>60811</v></c><c r="B117" s="0" t="s"><v>384</v></c><c r="C117" s="13"><v>1766</v></c><c r="D117" s="13"><v>294202254594</v></c><c r="E117" s="13"><v>166592443.145</v></c><c r="F117" s="13"><v>-18804498</v></c><c r="G117" s="13"><v>14531169000</v></c><c r="H117" s="0" t="s"><v>386</v></c></row><row r="118"><c r="A118" s="0"><v>65366</v></c><c r="B118" s="0" t="s"><v>387</v></c><c r="C118" s="13"><v>1766</v></c><c r="D118" s="13"><v>268286465878</v></c><c r="E118" s="13"><v>151917591.097</v></c><c r="F118" s="13"><v>-18804498</v></c><c r="G118" s="13"><v>13904707000</v></c><c r="H118" s="0" t="s"><v>389</v></c></row><row r="119"><c r="A119" s="0"><v>65371</v></c><c r="B119" s="0" t="s"><v>390</v></c><c r="C119" s="13"><v>1766</v></c><c r="D119" s="13"><v>16800049273</v></c><c r="E119" s="13"><v>9513051.683</v></c><c r="F119" s="13"><v>-1349355000</v></c><c r="G119" s="13"><v>2045524000</v></c><c r="H119" s="0" t="s"><v>392</v></c></row><row r="120"><c r="A120" s="0"><v>65376</v></c><c r="B120" s="0" t="s"><v>393</v></c><c r="C120" s="13"><v>1766</v></c><c r="D120" s="13"><v>9115739443</v></c><c r="E120" s="13"><v>5161800.364</v></c><c r="F120" s="13"><v>-37267441</v></c><c r="G120" s="13"><v>1710580000</v></c><c r="H120" s="0" t="s"><v>395</v></c></row><row r="121"><c r="A121" s="0"><v>65380</v></c><c r="B121" s="0" t="s"><v>396</v></c><c r="C121" s="13"><v>1766</v></c><c r="D121" s="13"><v>0</v></c><c r="E121" s="13"><v>0</v></c><c r="F121" s="13"><v>0</v></c><c r="G121" s="13"><v>0</v></c><c r="H121" s="0" t="s"><v>398</v></c></row><row r="122"><c r="A122" s="0"><v>65381</v></c><c r="B122" s="0" t="s"><v>399</v></c><c r="C122" s="13"><v>1766</v></c><c r="D122" s="13"><v>17251655331</v></c><c r="E122" s="13"><v>9768774.253</v></c><c r="F122" s="13"><v>-348175000</v></c><c r="G122" s="13"><v>2498564000</v></c><c r="H122" s="0" t="s"><v>401</v></c></row><row r="123"><c r="A123" s="0"><v>65386</v></c><c r="B123" s="0" t="s"><v>402</v></c><c r="C123" s="13"><v>1766</v></c><c r="D123" s="13"><v>-17013749461</v></c><c r="E123" s="13"><v>-9634059.717</v></c><c r="F123" s="13"><v>-2498564000</v></c><c r="G123" s="13"><v>348175000</v></c><c r="H123" s="0" t="s"><v>404</v></c></row><row r="124"><c r="A124" s="0"><v>65387</v></c><c r="B124" s="0" t="s"><v>405</v></c><c r="C124" s="13"><v>1766</v></c><c r="D124" s="13"><v>-237905870</v></c><c r="E124" s="13"><v>-134714.536</v></c><c r="F124" s="13"><v>-106213000</v></c><c r="G124" s="13"><v>5995000</v></c><c r="H124" s="0" t="s"><v>407</v></c></row><row r="125"><c r="A125" s="0"><v>65390</v></c><c r="B125" s="0" t="s"><v>408</v></c><c r="C125" s="13"><v>1766</v></c><c r="D125" s="13"><v>294202254594</v></c><c r="E125" s="13"><v>166592443.145</v></c><c r="F125" s="13"><v>-18804498</v></c><c r="G125" s="13"><v>14531169000</v></c><c r="H125" s="0" t="s"><v>410</v></c></row><row r="126"><c r="A126" s="0"><v>65391</v></c><c r="B126" s="0" t="s"><v>411</v></c><c r="C126" s="13"><v>1766</v></c><c r="D126" s="13"><v>285538121209</v></c><c r="E126" s="13"><v>161686365.351</v></c><c r="F126" s="13"><v>-18804498</v></c><c r="G126" s="13"><v>14658996000</v></c><c r="H126" s="0" t="s"><v>413</v></c></row><row r="127"><c r="A127" s="0"><v>65396</v></c><c r="B127" s="0" t="s"><v>414</v></c><c r="C127" s="13"><v>1766</v></c><c r="D127" s="13"><v>-213700188</v></c><c r="E127" s="13"><v>-121008.034</v></c><c r="F127" s="13"><v>-2388639000</v></c><c r="G127" s="13"><v>646284730</v></c><c r="H127" s="0" t="s"><v>416</v></c></row><row r="128"><c r="A128" s="0"><v>65401</v></c><c r="B128" s="0" t="s"><v>417</v></c><c r="C128" s="13"><v>1766</v></c><c r="D128" s="13"><v>8877833573</v></c><c r="E128" s="13"><v>5027085.828</v></c><c r="F128" s="13"><v>-44375000</v></c><c r="G128" s="13"><v>1604367000</v></c><c r="H128" s="0" t="s"><v>419</v></c></row><row r="129"><c r="A129" s="0"><v>60816</v></c><c r="B129" s="0" t="s"><v>420</v></c><c r="C129" s="13"><v>1766</v></c><c r="D129" s="13"><v>76015618059</v></c><c r="E129" s="13"><v>43043951.336</v></c><c r="F129" s="13"><v>0</v></c><c r="G129" s="13"><v>3504073000</v></c><c r="H129" s="0" t="s"><v>422</v></c></row><row r="130"><c r="A130" s="0"><v>60821</v></c><c r="B130" s="0" t="s"><v>423</v></c><c r="C130" s="13"><v>1766</v></c><c r="D130" s="13"><v>42606026245</v></c><c r="E130" s="13"><v>24125722.676</v></c><c r="F130" s="13"><v>0</v></c><c r="G130" s="13"><v>1937001000</v></c><c r="H130" s="0" t="s"><v>425</v></c></row><row r="131"><c r="A131" s="0"><v>60851</v></c><c r="B131" s="0" t="s"><v>426</v></c><c r="C131" s="13"><v>1766</v></c><c r="D131" s="13"><v>31768549364</v></c><c r="E131" s="13"><v>17988986.05</v></c><c r="F131" s="13"><v>0</v></c><c r="G131" s="13"><v>3949502000</v></c><c r="H131" s="0" t="s"><v>428</v></c></row><row r="132"><c r="A132" s="0"><v>60856</v></c><c r="B132" s="0" t="s"><v>429</v></c><c r="C132" s="13"><v>1766</v></c><c r="D132" s="13"><v>13352699598</v></c><c r="E132" s="13"><v>7560985.05</v></c><c r="F132" s="13"><v>0</v></c><c r="G132" s="13"><v>1926202000</v></c><c r="H132" s="0" t="s"><v>431</v></c></row><row r="133"><c r="A133" s="0"><v>60886</v></c><c r="B133" s="0" t="s"><v>432</v></c><c r="C133" s="13"><v>1766</v></c><c r="D133" s="13"><v>4030964026</v></c><c r="E133" s="13"><v>2282539.086</v></c><c r="F133" s="13"><v>0</v></c><c r="G133" s="13"><v>1045652420</v></c><c r="H133" s="0" t="s"><v>434</v></c></row><row r="134"><c r="A134" s="0"><v>60891</v></c><c r="B134" s="0" t="s"><v>435</v></c><c r="C134" s="13"><v>1766</v></c><c r="D134" s="13"><v>1953329127</v></c><c r="E134" s="13"><v>1106075.383</v></c><c r="F134" s="13"><v>0</v></c><c r="G134" s="13"><v>845984899</v></c><c r="H134" s="0" t="s"><v>437</v></c></row><row r="135"><c r="A135" s="0"><v>60921</v></c><c r="B135" s="0" t="s"><v>438</v></c><c r="C135" s="13"><v>1766</v></c><c r="D135" s="13"><v>24185380535</v></c><c r="E135" s="13"><v>13695005.965</v></c><c r="F135" s="13"><v>0</v></c><c r="G135" s="13"><v>1790657501</v></c><c r="H135" s="0" t="s"><v>440</v></c></row><row r="136"><c r="A136" s="0"><v>60926</v></c><c r="B136" s="0" t="s"><v>441</v></c><c r="C136" s="13"><v>1766</v></c><c r="D136" s="13"><v>11656003111</v></c><c r="E136" s="13"><v>6600228.262</v></c><c r="F136" s="13"><v>0</v></c><c r="G136" s="13"><v>1021106443</v></c><c r="H136" s="0" t="s"><v>443</v></c></row><row r="137"><c r="A137" s="0"><v>60956</v></c><c r="B137" s="0" t="s"><v>444</v></c><c r="C137" s="13"><v>1766</v></c><c r="D137" s="13"><v>22837061367</v></c><c r="E137" s="13"><v>12931518.328</v></c><c r="F137" s="13"><v>0</v></c><c r="G137" s="13"><v>435109321</v></c><c r="H137" s="0" t="s"><v>446</v></c></row><row r="138"><c r="A138" s="0"><v>60961</v></c><c r="B138" s="0" t="s"><v>447</v></c><c r="C138" s="13"><v>1766</v></c><c r="D138" s="13"><v>8995924026</v></c><c r="E138" s="13"><v>5093954.715</v></c><c r="F138" s="13"><v>0</v></c><c r="G138" s="13"><v>144951324</v></c><c r="H138" s="0" t="s"><v>449</v></c></row><row r="139"><c r="A139" s="0"><v>60991</v></c><c r="B139" s="0" t="s"><v>450</v></c><c r="C139" s="13"><v>1766</v></c><c r="D139" s="13"><v>35069778214</v></c><c r="E139" s="13"><v>19858311.559</v></c><c r="F139" s="13"><v>0</v></c><c r="G139" s="13"><v>1213343000</v></c><c r="H139" s="0" t="s"><v>452</v></c></row><row r="140"><c r="A140" s="0"><v>60996</v></c><c r="B140" s="0" t="s"><v>453</v></c><c r="C140" s="13"><v>1766</v></c><c r="D140" s="13"><v>14379288176</v></c><c r="E140" s="13"><v>8142292.285</v></c><c r="F140" s="13"><v>0</v></c><c r="G140" s="13"><v>470958000</v></c><c r="H140" s="0" t="s"><v>455</v></c></row><row r="141"><c r="A141" s="0"><v>61026</v></c><c r="B141" s="0" t="s"><v>456</v></c><c r="C141" s="13"><v>1658</v></c><c r="D141" s="13"><v>20451845338</v></c><c r="E141" s="13"><v>12335250.505</v></c><c r="F141" s="13"><v>0</v></c><c r="G141" s="13"><v>723539000</v></c><c r="H141" s="0" t="s"><v>458</v></c></row><row r="142"><c r="A142" s="0"><v>61031</v></c><c r="B142" s="0" t="s"><v>459</v></c><c r="C142" s="13"><v>1658</v></c><c r="D142" s="13"><v>3187178573</v></c><c r="E142" s="13"><v>1922303.12</v></c><c r="F142" s="13"><v>0</v></c><c r="G142" s="13"><v>220805000</v></c><c r="H142" s="0" t="s"><v>461</v></c></row><row r="143"><c r="A143" s="0"><v>61061</v></c><c r="B143" s="0" t="s"><v>462</v></c><c r="C143" s="13"><v>1766</v></c><c r="D143" s="13"><v>1274746691</v></c><c r="E143" s="13"><v>721827.118</v></c><c r="F143" s="13"><v>0</v></c><c r="G143" s="13"><v>181295000</v></c><c r="H143" s="0" t="s"><v>464</v></c></row><row r="144"><c r="A144" s="0"><v>61096</v></c><c r="B144" s="0" t="s"><v>465</v></c><c r="C144" s="13"><v>1573</v></c><c r="D144" s="13"><v>49993167468</v></c><c r="E144" s="13"><v>31782051.791</v></c><c r="F144" s="13"><v>0</v></c><c r="G144" s="13"><v>8946990000</v></c><c r="H144" s="0" t="s"><v>467</v></c></row><row r="145"><c r="A145" s="0"><v>61101</v></c><c r="B145" s="0" t="s"><v>468</v></c><c r="C145" s="13"><v>1573</v></c><c r="D145" s="13"><v>22266236229</v></c><c r="E145" s="13"><v>14155267.787</v></c><c r="F145" s="13"><v>0</v></c><c r="G145" s="13"><v>3449762000</v></c><c r="H145" s="0" t="s"><v>470</v></c></row><row r="146"><c r="A146" s="0"><v>61131</v></c><c r="B146" s="0" t="s"><v>471</v></c><c r="C146" s="13"><v>1573</v></c><c r="D146" s="13"><v>10085330349</v></c><c r="E146" s="13"><v>6411525.969</v></c><c r="F146" s="13"><v>0</v></c><c r="G146" s="13"><v>2673771733</v></c><c r="H146" s="0" t="s"><v>473</v></c></row><row r="147"><c r="A147" s="0"><v>61136</v></c><c r="B147" s="0" t="s"><v>474</v></c><c r="C147" s="13"><v>1573</v></c><c r="D147" s="13"><v>2241025639</v></c><c r="E147" s="13"><v>1424682.542</v></c><c r="F147" s="13"><v>0</v></c><c r="G147" s="13"><v>972293442</v></c><c r="H147" s="0" t="s"><v>476</v></c></row><row r="148"><c r="A148" s="0"><v>61201</v></c><c r="B148" s="0" t="s"><v>477</v></c><c r="C148" s="13"><v>1766</v></c><c r="D148" s="13"><v>7398303678</v></c><c r="E148" s="13"><v>4189299.931</v></c><c r="F148" s="13"><v>-850477</v></c><c r="G148" s="13"><v>3860552000</v></c><c r="H148" s="0" t="s"><v>479</v></c></row><row r="149"><c r="A149" s="0"><v>61206</v></c><c r="B149" s="0" t="s"><v>480</v></c><c r="C149" s="13"><v>1766</v></c><c r="D149" s="13"><v>4026536935</v></c><c r="E149" s="13"><v>2280032.24</v></c><c r="F149" s="13"><v>0</v></c><c r="G149" s="13"><v>2624541000</v></c><c r="H149" s="0" t="s"><v>482</v></c></row><row r="150"><c r="A150" s="0"><v>61236</v></c><c r="B150" s="0" t="s"><v>483</v></c><c r="C150" s="13"><v>1766</v></c><c r="D150" s="13"><v>283110745089</v></c><c r="E150" s="13"><v>160311860.186</v></c><c r="F150" s="13"><v>0</v></c><c r="G150" s="13"><v>13857148000</v></c><c r="H150" s="0" t="s"><v>485</v></c></row><row r="151"><c r="A151" s="0"><v>61241</v></c><c r="B151" s="0" t="s"><v>486</v></c><c r="C151" s="13"><v>1766</v></c><c r="D151" s="13"><v>124664247659</v></c><c r="E151" s="13"><v>70591306.715</v></c><c r="F151" s="13"><v>0</v></c><c r="G151" s="13"><v>6045218000</v></c><c r="H151" s="0" t="s"><v>488</v></c></row><row r="152"><c r="A152" s="0"><v>61246</v></c><c r="B152" s="0" t="s"><v>489</v></c><c r="C152" s="13"><v>1766</v></c><c r="D152" s="13"><v>32923588115</v></c><c r="E152" s="13"><v>18643028.378</v></c><c r="F152" s="13"><v>0</v></c><c r="G152" s="13"><v>1581494000</v></c><c r="H152" s="0" t="s"><v>491</v></c></row><row r="153"><c r="A153" s="0"><v>61251</v></c><c r="B153" s="0" t="s"><v>492</v></c><c r="C153" s="13"><v>1766</v></c><c r="D153" s="13"><v>17308945788</v></c><c r="E153" s="13"><v>9801215.055</v></c><c r="F153" s="13"><v>0</v></c><c r="G153" s="13"><v>694072000</v></c><c r="H153" s="0" t="s"><v>494</v></c></row><row r="154"><c r="A154" s="0"><v>61256</v></c><c r="B154" s="0" t="s"><v>495</v></c><c r="C154" s="13"><v>1766</v></c><c r="D154" s="13"><v>16598582693</v></c><c r="E154" s="13"><v>9398970.947</v></c><c r="F154" s="13"><v>0</v></c><c r="G154" s="13"><v>650251000</v></c><c r="H154" s="0" t="s"><v>497</v></c></row><row r="155"><c r="A155" s="0"><v>61261</v></c><c r="B155" s="0" t="s"><v>498</v></c><c r="C155" s="13"><v>1766</v></c><c r="D155" s="13"><v>5901890719</v></c><c r="E155" s="13"><v>3341953.975</v></c><c r="F155" s="13"><v>0</v></c><c r="G155" s="13"><v>246850000</v></c><c r="H155" s="0" t="s"><v>500</v></c></row><row r="156"><c r="A156" s="0"><v>61266</v></c><c r="B156" s="0" t="s"><v>501</v></c><c r="C156" s="13"><v>1766</v></c><c r="D156" s="13"><v>85713490115</v></c><c r="E156" s="13"><v>48535385.116</v></c><c r="F156" s="13"><v>0</v></c><c r="G156" s="13"><v>5243187000</v></c><c r="H156" s="0" t="s"><v>503</v></c></row><row r="157"><c r="A157" s="0"><v>61271</v></c><c r="B157" s="0" t="s"><v>507</v></c><c r="C157" s="13"><v>1319</v></c><c r="D157" s="13"><v>611208618662</v></c><c r="E157" s="13"><v>463387883.747</v></c><c r="F157" s="13"><v>147</v></c><c r="G157" s="13"><v>50877680000</v></c><c r="H157" s="0" t="s"><v>509</v></c></row><row r="158"><c r="A158" s="0"><v>61276</v></c><c r="B158" s="0" t="s"><v>510</v></c><c r="C158" s="13"><v>1319</v></c><c r="D158" s="13"><v>615702007717</v></c><c r="E158" s="13"><v>466794547.17</v></c><c r="F158" s="13"><v>148</v></c><c r="G158" s="13"><v>50748594000</v></c><c r="H158" s="0" t="s"><v>512</v></c></row><row r="159"><c r="A159" s="0"><v>61319</v></c><c r="B159" s="0" t="s"><v>513</v></c><c r="C159" s="13"><v>1319</v></c><c r="D159" s="13"><v>4493442218</v></c><c r="E159" s="13"><v>3406703.729</v></c><c r="F159" s="13"><v>-1745354000</v></c><c r="G159" s="13"><v>2294393000</v></c><c r="H159" s="0" t="s"><v>515</v></c></row><row r="160"><c r="A160" s="0"><v>61321</v></c><c r="B160" s="0" t="s"><v>516</v></c><c r="C160" s="13"><v>1319</v></c><c r="D160" s="13"><v>12974395937</v></c><c r="E160" s="13"><v>9836539.755</v></c><c r="F160" s="13"><v>0</v></c><c r="G160" s="13"><v>2491863000</v></c><c r="H160" s="0" t="s"><v>518</v></c></row><row r="161"><c r="A161" s="0"><v>61323</v></c><c r="B161" s="0" t="s"><v>519</v></c><c r="C161" s="13"><v>1319</v></c><c r="D161" s="13"><v>16480714000</v></c><c r="E161" s="13"><v>12494855.193</v></c><c r="F161" s="13"><v>-689719000</v></c><c r="G161" s="13"><v>1337648000</v></c><c r="H161" s="0" t="s"><v>521</v></c></row><row r="162"><c r="A162" s="0"><v>61325</v></c><c r="B162" s="0" t="s"><v>522</v></c><c r="C162" s="13"><v>1319</v></c><c r="D162" s="13"><v>-27692313073</v></c><c r="E162" s="13"><v>-20994930.306</v></c><c r="F162" s="13"><v>-2244699000</v></c><c r="G162" s="13"><v>0</v></c><c r="H162" s="0" t="s"><v>524</v></c></row><row r="163"><c r="A163" s="0"><v>61327</v></c><c r="B163" s="0" t="s"><v>525</v></c><c r="C163" s="13"><v>1319</v></c><c r="D163" s="13"><v>2730645354</v></c><c r="E163" s="13"><v>2070239.086</v></c><c r="F163" s="13"><v>-201326268</v></c><c r="G163" s="13"><v>743757000</v></c><c r="H163" s="0" t="s"><v>527</v></c></row><row r="164"><c r="A164" s="0"><v>61329</v></c><c r="B164" s="0" t="s"><v>528</v></c><c r="C164" s="13"><v>1586</v></c><c r="D164" s="13"><v>8300871291</v></c><c r="E164" s="13"><v>5233840.663</v></c><c r="F164" s="13"><v>-601753000</v></c><c r="G164" s="13"><v>1006510000</v></c><c r="H164" s="0" t="s"><v>530</v></c></row><row r="165"><c r="A165" s="0"><v>61331</v></c><c r="B165" s="0" t="s"><v>531</v></c><c r="C165" s="13"><v>1586</v></c><c r="D165" s="13"><v>283251984311</v></c><c r="E165" s="13"><v>178595198.178</v></c><c r="F165" s="13"><v>-18804498</v></c><c r="G165" s="13"><v>14992873000</v></c><c r="H165" s="0" t="s"><v>533</v></c></row><row r="166"><c r="A166" s="0"><v>61333</v></c><c r="B166" s="0" t="s"><v>534</v></c><c r="C166" s="13"><v>1586</v></c><c r="D166" s="13"><v>13776057337</v></c><c r="E166" s="13"><v>8686038.674</v></c><c r="F166" s="13"><v>-1768051000</v></c><c r="G166" s="13"><v>2337704000</v></c><c r="H166" s="0" t="s"><v>536</v></c></row><row r="167"><c r="A167" s="0"><v>61335</v></c><c r="B167" s="0" t="s"><v>537</v></c><c r="C167" s="13"><v>1586</v></c><c r="D167" s="13"><v>858739297840</v></c><c r="E167" s="13"><v>541449746.431</v></c><c r="F167" s="13"><v>-57934626</v></c><c r="G167" s="13"><v>61246694000</v></c><c r="H167" s="0" t="s"><v>71</v></c></row><row r="168"><c r="A168" s="0"><v>61337</v></c><c r="B168" s="0" t="s"><v>539</v></c><c r="C168" s="13"><v>1586</v></c><c r="D168" s="13"><v>504340605488</v></c><c r="E168" s="13"><v>317995337.634</v></c><c r="F168" s="13"><v>-47017677</v></c><c r="G168" s="13"><v>43771399000</v></c><c r="H168" s="0" t="s"><v>541</v></c></row><row r="169"><c r="A169" s="0"><v>61339</v></c><c r="B169" s="0" t="s"><v>542</v></c><c r="C169" s="13"><v>1586</v></c><c r="D169" s="13"><v>154615723452</v></c><c r="E169" s="13"><v>97487845.808</v></c><c r="F169" s="13"><v>0</v></c><c r="G169" s="13"><v>6409159000</v></c><c r="H169" s="0" t="s"><v>544</v></c></row><row r="170"><c r="A170" s="0"><v>61341</v></c><c r="B170" s="0" t="s"><v>545</v></c><c r="C170" s="13"><v>1586</v></c><c r="D170" s="13"><v>282350916084</v></c><c r="E170" s="13"><v>178027059.322</v></c><c r="F170" s="13"><v>259507</v></c><c r="G170" s="13"><v>13857148000</v></c><c r="H170" s="0" t="s"><v>547</v></c></row></sheetData><headerFooter /></worksheet>