{"id":268148636,"generated_unique_award_id":"ASST_NON_K23NS117736_075","fain":"K23NS117736","uri":"K23NS117736-3328274178","category":"grant","type":"04","type_description":"PROJECT GRANT (B)","description":"INVESTIGATING AUTONOMIC DYSFUNCTION AS AN EARLY PATHOLOGIC FEATURE OF HUNTINGTON?S DISEASE - PROJECT SUMMARY/ABSTRACT THE PURPOSE OF THIS MENTORED PATIENT-ORIENTED CAREER DEVELOPMENT AWARD (K23) IS TO SUPPORT MY SHORT-TERM CAREER OBJECTIVE OF DETERMINING IF DYSFUNCTION OF THE AUTONOMIC NERVOUS SYSTEM (ANS) IS AN EARLY PATHOLOGICAL FEATURE OF HD BY QUANTITATIVELY CHARACTERIZING FUNCTIONAL CONNECTIONS BETWEEN BRAIN REGIONS THAT REGULATE THE ANS IN CHILDREN WITH THE GENE EXPANSION THAT CAUSES HD USING MAGNETIC RESONANCE IMAGING (MRI). I WILL ALSO INVESTIGATE UNIQUE PHYSIOLOGIC MEASURES OF ANS FUNCTION AND EARLY EFFECTS ON THE VASCULAR SYSTEM IN THESE PARTICIPANTS. ANS DYSFUNCTION HAS BEEN DESCRIBED IN ADULT PATIENTS WITH HD, BUT IT HAS BEEN THOUGHT THAT THIS IS A SECONDARY COMPLICATION OF NEURODEGENERATION. HOWEVER, I RECENTLY DISCOVERED THAT CHILDREN CARRYING THE HD GENE EXPANSION THAT CAUSES HD (GE CHILDREN) EXHIBIT SYMPTOMS CONSISTENT WITH ENHANCED SYMPATHETIC TONE DECADES PRIOR TO THEIR PREDICTED MOTOR ONSET. THESE FINDINGS INDICATE THAT ANS DYSFUNCTION MAY BE ONE OF THE EARLIEST MANIFESTATIONS OF NEURODEGENERATION IN HD. AS A RESULT, THE ANS MAY BE A THERAPEUTIC TARGET FOR DISEASE MODIFICATION OF HD, BUT MORE INFORMATION IS REQUIRED. THE ANS IS HIGHLY REGULATED BY CORTICAL BRAIN REGIONS THAT COMPRISE THE CENTRAL AUTONOMIC NETWORK (CAN), AND CORTICAL THINNING AND ATROPHY HAVE BEEN WELL-DESCRIBED IN HD. HOWEVER, THERE ARE NO PUBLISHED REPORTS THAT HAVE OBJECTIVELY CHARACTERIZED THE INTEGRITY OF THE FUNCTIONAL CONNECTIONS IN THE CAN IN HD. I WILL PERFORM RESTING-STATE AND TASKED FUNCTIONAL MRI ON GE CHILDREN TO CHARACTERIZE THE FUNCTION OF THE CAN AT DIFFERENT STAGES OF THE DISEASE. THIS EXPERIMENT WILL TEST THE SPECIFIC HYPOTHESIS THAT QUANTITATIVE CHANGES IN FUNCTIONAL INTEGRITY OF THE CAN ARE APPARENT DECADES PRIOR TO THE PREDICTED MOTOR ONSET OF HD. ADDITIONALLY, I WILL EXPLORE PHYSIOLOGIC MEASURE OF ANS DYSFUNCTION INCLUDING BAROREFLEX SENSITIVITY (BRS) AND HOW THIS RELATES TO THE FUNCTION OF THE VASCULAR SYSTEM EARLY IN THE DISEASE COURSE OF HD. SPECIFICALLY, I WILL MEASURE AORTIC STIFFNESS AND CAROTID ARTERY COMPLIANCE WHILE ALSO MEASURING CEREBRAL BLOOD FLOW USING ARTERIAL SPIN LABELING TO TEST THE HYPOTHESES THAT RELATIVE TO HEALTHY CONTROL CHILDREN, GE CHILDREN WILL DEMONSTRATE INCREASED AORTIC STIFFNESS, DECREASED BRS, AND DECREASED CEREBRAL BLOOD FLOW. THESE EXPERIMENTS WILL PROVIDE VITAL INFORMATION REGARDING WHEN ANS DYSFUNCTION OCCURS IN HD, THE UNDERLYING MECHANISMS CAUSING THE DYSFUNCTION, AND IF THESE CHANGES HAVE NEGATIVE EFFECTS ON THE CARDIOVASCULAR SYSTEM EARLY IN THE DISEASE COURSE. I HAVE A UNIQUE BACKGROUND THAT POSITIONS ME WELL TO BE A SUCCESSFUL TRANSLATIONAL SCIENTIST. FURTHER TRAINING IS REQUIRED IN SOPHISTICATED NEUROIMAGING METHODS, NEURODEVELOPMENT AND NEUROBIOLOGY, AS WELL AS BIOSTATISTICS. THE PROPOSED INTEGRATED RESEARCH, WORLD-CLASS MENTORSHIP TEAM, AND DIDACTIC TRAINING PROGRAMS WILL ENSURE MY SHORT-TERM AND LONG-TERM SUCCESS. ADDITIONALLY, THE PROPOSED RESEARCH AND TRAINING PLANS SUPPORT MY LONG-TERM CAREER GOAL TO BE AN INDEPENDENT TRANSLATIONAL PHARMACIST STUDYING THE STRUCTURE AND FUNCTION OF THE BRAIN IN PATIENTS WITH HD TO ADVANCE THERAPEUTIC STRATEGIES.","subaward_count":0,"total_subaward_amount":null,"total_subsidy_cost":0.0,"total_loan_value":0.0,"total_obligation":713702.07,"date_signed":"2021-02-26","base_and_all_options":null,"base_exercised_options":null,"non_federal_funding":0.0,"total_funding":713702.07,"total_account_outlay":639070.32,"total_account_obligation":713702.07,"account_outlays_by_defc":[{"code":"Q","amount":639070.32}],"account_obligations_by_defc":[{"code":"Q","amount":713702.07}],"record_type":2,"cfda_info":[{"applicant_eligibility":"Research Grants: Any public, private, nonprofit, or for-profit institution is eligible to apply. For-profit institutions are not eligible for Institutional National Research Service Awards but are eligible for Individual NRSAs. All proposals are reviewed for scientific merit, for evaluation of the qualifications of the investigators, for adequacy of the research environment, and for significance of the problem. Approved proposals compete for available funds. All Career Development Program awardees, with the exception of awardees of the Pathway to Independence Award (K99/R00), must be citizens or have been admitted to the United States for permanent residence. Candidates must be nominated for the program by a nonfederal public or private nonprofit institution located in the United States, its possessions or territories. To be eligible, postdoctoral NRSA trainees or fellows must have a professional or scientific degree (M.D., Ph.D., D.D.S., D.O., D.V.M., Sc.D., D. Eng., or equivalent domestic or foreign degree). SBIR grants can be awarded only to domestic small businesses (entities that are independently owned and operated for profit, are not dominant in the field in which research is proposed, and have no more than 500 employees). Primary employment (more than one-half time) of the principal investigator must be with the small business at the time of award and during the conduct of the proposed project. In both Phase I and Phase II, the entire research must be performed in the United States. To be eligible for funding, a grant application must be approved for scientific merit and program relevance by a scientific review group and a national advisory council. STTR grants can be awarded only to domestic small business concerns (entities that are independently owned and operated for profit, are not dominant in the field in which research is proposed and have no more than 500 employees) which \"partner\" with a research institution in cooperative research and development. At least 40 percent of the project is to be performed by the small business concern and at least 30 percent by the research institution. In both Phase I and Phase II, the research must be performed in the U.S. and its possessions. To be eligible for funding, a grant application must be approved for scientific merit and program relevance by a scientific review group and a national advisory council.","beneficiary_eligibility":"Health professionals, graduate students, health professional students, scientists, and researchers.","cfda_federal_agency":"NATIONAL INSTITUTES OF HEALTH, HEALTH AND HUMAN SERVICES, DEPARTMENT OF","cfda_number":"93.853","cfda_objectives":"(1) To support extramural research funded by the National Institute of Neurological Disorders and Stroke (NINDS) including: basic research that explores the fundamental structure and function of the brain and the nervous system; research to understand the causes and origins of pathological conditions of the nervous system with the goal of preventing these disorders; research on the natural course of neurological disorders; improved methods of disease prevention; new methods of diagnosis and treatment; drug development; development of neural devices; clinical trials; and research training in basic, translational and clinical neuroscience. The Institute is the largest funder of basic neuroscience in the US and supports research on topics including but not limited to: development of the nervous system, including neurogenesis and progenitor cell biology, signal transduction in development and plasticity, and programmed cell death; synapse formation, function, and plasticity;  learning and memory; channels, transporters, and pumps; circuit formation and modulation;  behavioral and cognitive neuroscience; sensorimotor learning, integration and executive function; neuroendocrine systems; sleep and circadian rhythms; and sensory and motor systems.  In addition, the Institute supports basic, translational and clinical studies on a number of disorders of the nervous system including (but not limited to): stroke; traumatic injury to the brain, spinal cord and peripheral nervous system; neurodegenerative disorders; movement disorders; brain tumors; convulsive disorders; infectious disorders of the brain and nervous system; immune disorders of the brain and nervous system, including multiple sclerosis; disorders related to sleep; and pain. Programmatic areas, which are primarily supported by the Division of Neuroscience, are also supported by the Division of Extramural Activities, the Division of Translational Research, the Division of Clinical Research, the Office of Training and Workforce Development, the Office of Programs to Enhance the Neuroscience Workforce, and the Office of International Activities. (2) To expand and improve the Small Business Innovation Research (SBIR) program; to increase private sector commercialization of innovations derived from Federal research and development; to increase small business participation in Federal research and development; and to foster and encourage participation of socially and economically disadvantaged small business concerns and women-owned small business concerns in technological innovation. To utilize the Small Business Technology Transfer (STTR) program; to stimulate and foster scientific and technological innovation through cooperative research and development carried out between small business concerns and research institutions; to foster technology transfer between small business concerns and research institutions; to increase private sector commercialization of innovations derived from Federal research and development; and to foster and encourage participation of socially and economically disadvantaged small business concerns and women-owned small business concerns in technological innovation.","cfda_obligations":"(Project Grants (Contracts)) FY 23$161,797,318.00; FY 24 est $157,671,519.00; FY 25 est $175,019,736.00; FY 22$118,801,942.00; FY 21$148,891,276.00; FY 20$148,901,463.00; FY 19$116,500,719.00; FY 18$95,906,371.00; - (Project Grants) FY 23$1,815,798,407.00; FY 24 est $1,834,858,709.00; FY 25 est $2,035,714,200.00; FY 22$1,662,351,993.00; FY 21$1,697,329,900.00; FY 20$1,703,587,636.00; FY 19$1,583,831,299.00; FY 18$1,392,406,713.00; - ","cfda_popular_name":"","cfda_title":"Extramural Research Programs in the Neurosciences and Neurological Disorders","cfda_website":"http://www.ninds.nih.gov/","federal_action_obligation_amount":713702.07,"non_federal_funding_amount":0.0,"sam_website":"https://sam.gov/fal/02c72ff133e748cba386a1af55dcc35b/view","total_funding_amount":713702.07}],"transaction_obligated_amount":713702.07,"funding_agency":{"id":830,"has_agency_page":true,"toptier_agency":{"name":"Department of Health and Human Services","code":"075","abbreviation":"HHS","slug":"department-of-health-and-human-services"},"subtier_agency":{"name":"National Institutes of Health","code":"7529","abbreviation":"NIH"},"office_agency_name":"NIH National Institute of Neurological Disorders and Stroke"},"awarding_agency":{"id":830,"has_agency_page":true,"toptier_agency":{"name":"Department of Health and Human Services","code":"075","abbreviation":"HHS","slug":"department-of-health-and-human-services"},"subtier_agency":{"name":"National Institutes of Health","code":"7529","abbreviation":"NIH"},"office_agency_name":"NIH National Institute of Neurological Disorders and Stroke"},"period_of_performance":{"start_date":"2021-04-01","end_date":"2025-05-08","last_modified_date":"2026-02-06"},"recipient":{"recipient_hash":"0b441d38-e3c0-de89-ee08-69fc9e6ee58a-R","recipient_name":"THE UNIVERSITY OF IOWA","recipient_uei":"Z1H9VJS8NG16","recipient_unique_id":null,"parent_recipient_hash":null,"parent_recipient_name":null,"parent_recipient_uei":null,"parent_recipient_unique_id":null,"business_categories":["Higher Education","Higher Education (Public)"],"location":{"location_country_code":"USA","country_name":"UNITED STATES","state_code":"IA","state_name":"IOWA","city_name":"IOWA CITY","county_code":"103","county_name":"JOHNSON","address_line1":"105 JESSUP HALL","address_line2":null,"address_line3":null,"congressional_code":"01","zip4":"1316","zip5":"52242","foreign_postal_code":null,"foreign_province":null}},"executive_details":{"officers":[{"name":null,"amount":null},{"name":null,"amount":null},{"name":null,"amount":null},{"name":null,"amount":null},{"name":null,"amount":null}]},"place_of_performance":{"location_country_code":"USA","country_name":"UNITED STATES","county_code":"103","county_name":"JOHNSON","city_name":"IOWA CITY","state_code":"IA","state_name":"IOWA","congressional_code":"01","zip4":null,"zip5":"52242","address_line1":null,"address_line2":null,"address_line3":null,"foreign_province":null,"foreign_postal_code":null},"total_outlay":639070.32,"funding_opportunity":{"number":"PA-20-205","goals":"(1) TO SUPPORT EXTRAMURAL RESEARCH FUNDED BY THE NATIONAL INSTITUTE OF NEUROLOGICAL DISORDERS AND STROKE (NINDS) INCLUDING: BASIC RESEARCH THAT EXPLORES THE FUNDAMENTAL STRUCTURE AND FUNCTION OF THE BRAIN AND THE NERVOUS SYSTEM, RESEARCH TO UNDERSTAND THE CAUSES AND ORIGINS OF PATHOLOGICAL CONDITIONS OF THE NERVOUS SYSTEM WITH THE GOAL OF PREVENTING THESE DISORDERS, RESEARCH ON THE NATURAL COURSE OF NEUROLOGICAL DISORDERS, IMPROVED METHODS OF DISEASE PREVENTION, NEW METHODS OF DIAGNOSIS AND TREATMENT, DRUG DEVELOPMENT, DEVELOPMENT OF NEURAL DEVICES, CLINICAL TRIALS, AND RESEARCH TRAINING IN BASIC, TRANSLATIONAL AND CLINICAL NEUROSCIENCE. THE INSTITUTE IS THE LARGEST FUNDER OF BASIC NEUROSCIENCE IN THE US AND SUPPORTS RESEARCH ON TOPICS INCLUDING BUT NOT LIMITED TO: DEVELOPMENT OF THE NERVOUS SYSTEM, INCLUDING NEUROGENESIS AND PROGENITOR CELL BIOLOGY, SIGNAL TRANSDUCTION IN DEVELOPMENT AND PLASTICITY, AND PROGRAMMED CELL DEATH, SYNAPSE FORMATION, FUNCTION, AND PLASTICITY,  LEARNING AND MEMORY, CHANNELS, TRANSPORTERS, AND PUMPS, CIRCUIT FORMATION AND MODULATION,  BEHAVIORAL AND COGNITIVE NEUROSCIENCE, SENSORIMOTOR LEARNING, INTEGRATION AND EXECUTIVE FUNCTION, NEUROENDOCRINE SYSTEMS, SLEEP AND CIRCADIAN RHYTHMS, AND SENSORY AND MOTOR SYSTEMS.  IN ADDITION, THE INSTITUTE SUPPORTS BASIC, TRANSLATIONAL AND CLINICAL STUDIES ON A NUMBER OF DISORDERS OF THE NERVOUS SYSTEM INCLUDING (BUT NOT LIMITED TO): STROKE, TRAUMATIC INJURY TO THE BRAIN, SPINAL CORD AND PERIPHERAL NERVOUS SYSTEM, NEURODEGENERATIVE DISORDERS, MOVEMENT DISORDERS, BRAIN TUMORS, CONVULSIVE DISORDERS, INFECTIOUS DISORDERS OF THE BRAIN AND NERVOUS SYSTEM, IMMUNE DISORDERS OF THE BRAIN AND NERVOUS SYSTEM, INCLUDING MULTIPLE SCLEROSIS, DISORDERS RELATED TO SLEEP, AND PAIN. PROGRAMMATIC AREAS, WHICH ARE PRIMARILY SUPPORTED BY THE DIVISION OF NEUROSCIENCE, ARE ALSO SUPPORTED BY THE DIVISION OF EXTRAMURAL ACTIVITIES, THE DIVISION OF TRANSLATIONAL RESEARCH, THE DIVISION OF CLINICAL RESEARCH, THE OFFICE OF TRAINING AND WORKFORCE DEVELOPMENT, THE OFFICE OF PROGRAMS TO ENHANCE NEUROSCIENCE WORKFORCE DEVELOPMENT, AND THE OFFICE OF INTERNATIONAL ACTIVITIES. (2) TO EXPAND AND IMPROVE THE SMALL BUSINESS INNOVATION RESEARCH (SBIR) PROGRAM, TO INCREASE PRIVATE SECTOR COMMERCIALIZATION OF INNOVATIONS DERIVED FROM FEDERAL RESEARCH AND DEVELOPMENT, TO INCREASE SMALL BUSINESS PARTICIPATION IN FEDERAL RESEARCH AND DEVELOPMENT, AND TO FOSTER AND ENCOURAGE PARTICIPATION OF SOCIALLY AND ECONOMICALLY DISADVANTAGED SMALL BUSINESS CONCERNS AND WOMEN-OWNED SMALL BUSINESS CONCERNS IN TECHNOLOGICAL INNOVATION. TO UTILIZE THE SMALL BUSINESS TECHNOLOGY TRANSFER (STTR) PROGRAM, TO STIMULATE AND FOSTER SCIENTIFIC AND TECHNOLOGICAL INNOVATION THROUGH COOPERATIVE RESEARCH AND DEVELOPMENT CARRIED OUT BETWEEN SMALL BUSINESS CONCERNS AND RESEARCH INSTITUTIONS, TO FOSTER TECHNOLOGY TRANSFER BETWEEN SMALL BUSINESS CONCERNS AND RESEARCH INSTITUTIONS, TO INCREASE PRIVATE SECTOR COMMERCIALIZATION OF INNOVATIONS DERIVED FROM FEDERAL RESEARCH AND DEVELOPMENT, AND TO FOSTER AND ENCOURAGE PARTICIPATION OF SOCIALLY AND ECONOMICALLY DISADVANTAGED SMALL BUSINESS CONCERNS AND WOMEN-OWNED SMALL BUSINESS CONCERNS IN TECHNOLOGICAL INNOVATION."}}
