<?xml version="1.0" encoding="UTF-8" standalone="yes"?>
<worksheet xmlns="http://schemas.openxmlformats.org/spreadsheetml/2006/main" xmlns:r="http://schemas.openxmlformats.org/officeDocument/2006/relationships" xmlns:mc="http://schemas.openxmlformats.org/markup-compatibility/2006" mc:Ignorable="x14ac" xmlns:x14ac="http://schemas.microsoft.com/office/spreadsheetml/2009/9/ac"><dimension ref="A1:H324"/><sheetViews><sheetView workbookViewId="0"><pane ySplit="1" topLeftCell="A2" activePane="bottomLeft" state="frozen"/><selection pane="bottomLeft"/></sheetView></sheetViews><sheetFormatPr defaultColWidth="9.1796875" defaultRowHeight="12.5" x14ac:dyDescent="0.25"/><cols><col min="1" max="1" width="12.81640625" style="1" customWidth="1"/><col min="2" max="2" width="15.54296875" style="1" customWidth="1"/><col min="3" max="3" width="6.7265625" style="30" bestFit="1" customWidth="1"/><col min="4" max="4" width="17.26953125" style="10" customWidth="1"/><col min="5" max="5" width="18.26953125" style="35" customWidth="1"/><col min="6" max="6" width="16.7265625" style="10" customWidth="1"/><col min="7" max="7" width="17.26953125" style="30" customWidth="1"/><col min="8" max="8" width="120.54296875" style="1" bestFit="1" customWidth="1"/><col min="9" max="16384" width="9.1796875" style="1"/></cols><sheetData><row r="1" spans="1:8" s="21" customFormat="1" x14ac:dyDescent="0.25"><c r="A1" s="21" t="s"><v>10</v></c><c r="B1" s="21" t="s"><v>11</v></c><c r="C1" s="32" t="s"><v>339</v></c><c r="D1" s="33" t="s"><v>340</v></c><c r="E1" s="34" t="s"><v>341</v></c><c r="F1" s="10" t="s"><v>342</v></c><c r="G1" s="32" t="s"><v>343</v></c><c r="H1" s="21" t="s"><v>16</v></c></row><row r="2" spans="1:8" x14ac:dyDescent="0.25"><c r="A2" s="1"><v>61386</v></c><c r="B2" s="1" t="s"><v>21</v></c><c r="C2" s="30"><v>1500</v></c><c r="D2" s="10"><v>177241021494</v></c><c r="E2" s="11"><v>118160680.99600001</v></c><c r="F2" s="10"><v>0</v></c><c r="G2" s="30"><v>16044282000</v></c><c r="H2" s="1" t="s"><v>23</v></c></row><row r="3" spans="1:8" x14ac:dyDescent="0.25"><c r="A3" s="1"><v>65001</v></c><c r="B3" s="1" t="s"><v>24</v></c><c r="C3" s="30"><v>1500</v></c><c r="D3" s="10"><v>412594160993</v></c><c r="E3" s="11"><v>275062773.99533331</v></c><c r="F3" s="10"><v>0</v></c><c r="G3" s="30"><v>36543173000</v></c><c r="H3" s="1" t="s"><v>26</v></c></row><row r="4" spans="1:8" x14ac:dyDescent="0.25"><c r="A4" s="1"><v>61401</v></c><c r="B4" s="1" t="s"><v>27</v></c><c r="C4" s="30"><v>1500</v></c><c r="D4" s="10"><v>273815796449</v></c><c r="E4" s="11"><v>182543864.29933333</v></c><c r="F4" s="10"><v>-6076974</v></c><c r="G4" s="30"><v>53529403611</v></c><c r="H4" s="1" t="s"><v>29</v></c></row><row r="5" spans="1:8" x14ac:dyDescent="0.25"><c r="A5" s="1"><v>61406</v></c><c r="B5" s="1" t="s"><v>30</v></c><c r="C5" s="30"><v>1500</v></c><c r="D5" s="10"><v>686409957442</v></c><c r="E5" s="11"><v>457606638.29466665</v></c><c r="F5" s="10"><v>0</v></c><c r="G5" s="30"><v>64907723995</v></c><c r="H5" s="1" t="s"><v>32</v></c></row><row r="6" spans="1:8" x14ac:dyDescent="0.25"><c r="A6" s="1"><v>61411</v></c><c r="B6" s="1" t="s"><v>33</v></c><c r="C6" s="30"><v>1500</v></c><c r="D6" s="10"><v>863650978936</v></c><c r="E6" s="11"><v>575767319.2906667</v></c><c r="F6" s="10"><v>0</v></c><c r="G6" s="30"><v>77606971000</v></c><c r="H6" s="1" t="s"><v>35</v></c></row><row r="7" spans="1:8" x14ac:dyDescent="0.25"><c r="A7" s="1"><v>61473</v></c><c r="B7" s="1" t="s"><v>391</v></c><c r="C7" s="30"><v>1500</v></c><c r="D7" s="10"><v>62476248041</v></c><c r="E7" s="11"><v>41650832.027333334</v></c><c r="F7" s="10"><v>0</v></c><c r="G7" s="30"><v>14622134000</v></c><c r="H7" s="1" t="s"><v>393</v></c></row><row r="8" spans="1:8" x14ac:dyDescent="0.25"><c r="A8" s="1"><v>61416</v></c><c r="B8" s="1" t="s"><v>36</v></c><c r="C8" s="30"><v>1500</v></c><c r="D8" s="10"><v>14339176866</v></c><c r="E8" s="11"><v>9559451.2440000009</v></c><c r="F8" s="10"><v>0</v></c><c r="G8" s="30"><v>1996183000</v></c><c r="H8" s="1" t="s"><v>38</v></c></row><row r="9" spans="1:8" x14ac:dyDescent="0.25"><c r="A9" s="1"><v>61421</v></c><c r="B9" s="1" t="s"><v>39</v></c><c r="C9" s="30"><v>1500</v></c><c r="D9" s="10"><v>83759930118</v></c><c r="E9" s="11"><v>55839953.412</v></c><c r="F9" s="10"><v>0</v></c><c r="G9" s="30"><v>12055183000</v></c><c r="H9" s="1" t="s"><v>41</v></c></row><row r="10" spans="1:8" x14ac:dyDescent="0.25"><c r="A10" s="1"><v>61426</v></c><c r="B10" s="1" t="s"><v>42</v></c><c r="C10" s="30"><v>1500</v></c><c r="D10" s="10"><v>98099106984</v></c><c r="E10" s="11"><v>65399404.656000003</v></c><c r="F10" s="10"><v>0</v></c><c r="G10" s="30"><v>14051366000</v></c><c r="H10" s="1" t="s"><v>44</v></c></row><row r="11" spans="1:8" x14ac:dyDescent="0.25"><c r="A11" s="1"><v>61431</v></c><c r="B11" s="1" t="s"><v>45</v></c><c r="C11" s="30"><v>1500</v></c><c r="D11" s="10"><v>213967896950</v></c><c r="E11" s="11"><v>142645264.63333333</v></c><c r="F11" s="10"><v>0</v></c><c r="G11" s="30"><v>23329565000</v></c><c r="H11" s="1" t="s"><v>47</v></c></row><row r="12" spans="1:8" x14ac:dyDescent="0.25"><c r="A12" s="1"><v>61436</v></c><c r="B12" s="1" t="s"><v>48</v></c><c r="C12" s="30"><v>1500</v></c><c r="D12" s="10"><v>273912852855</v></c><c r="E12" s="11"><v>182608568.56999999</v></c><c r="F12" s="10"><v>0</v></c><c r="G12" s="30"><v>47713294000</v></c><c r="H12" s="1" t="s"><v>50</v></c></row><row r="13" spans="1:8" x14ac:dyDescent="0.25"><c r="A13" s="1"><v>61441</v></c><c r="B13" s="1" t="s"><v>51</v></c><c r="C13" s="30"><v>1500</v></c><c r="D13" s="10"><v>487880749805</v></c><c r="E13" s="11"><v>325253833.20333332</v></c><c r="F13" s="10"><v>0</v></c><c r="G13" s="30"><v>71042859000</v></c><c r="H13" s="1" t="s"><v>53</v></c></row><row r="14" spans="1:8" x14ac:dyDescent="0.25"><c r="A14" s="1"><v>61446</v></c><c r="B14" s="1" t="s"><v>54</v></c><c r="C14" s="30"><v>1500</v></c><c r="D14" s="10"><v>585979856789</v></c><c r="E14" s="11"><v>390653237.85933334</v></c><c r="F14" s="10"><v>0</v></c><c r="G14" s="30"><v>85094225000</v></c><c r="H14" s="1" t="s"><v>56</v></c></row><row r="15" spans="1:8" x14ac:dyDescent="0.25"><c r="A15" s="1"><v>61474</v></c><c r="B15" s="1" t="s"><v>394</v></c><c r="C15" s="30"><v>1500</v></c><c r="D15" s="10"><v>49686880901</v></c><c r="E15" s="11"><v>33124587.267333332</v></c><c r="F15" s="10"><v>0</v></c><c r="G15" s="30"><v>7251375000</v></c><c r="H15" s="1" t="s"><v>396</v></c></row><row r="16" spans="1:8" x14ac:dyDescent="0.25"><c r="A16" s="1"><v>61451</v></c><c r="B16" s="1" t="s"><v>57</v></c><c r="C16" s="30"><v>1500</v></c><c r="D16" s="10"><v>247980766188</v></c><c r="E16" s="11"><v>165320510.792</v></c><c r="F16" s="10"><v>-3830909591</v></c><c r="G16" s="30"><v>14425511000</v></c><c r="H16" s="1" t="s"><v>59</v></c></row><row r="17" spans="1:8" x14ac:dyDescent="0.25"><c r="A17" s="1"><v>61456</v></c><c r="B17" s="1" t="s"><v>60</v></c><c r="C17" s="30"><v>1500</v></c><c r="D17" s="10"><v>77010926687</v></c><c r="E17" s="11"><v>51340617.791333333</v></c><c r="F17" s="10"><v>-246713510</v></c><c r="G17" s="30"><v>13199063758</v></c><c r="H17" s="1" t="s"><v>62</v></c></row><row r="18" spans="1:8" x14ac:dyDescent="0.25"><c r="A18" s="1"><v>61461</v></c><c r="B18" s="1" t="s"><v>63</v></c><c r="C18" s="30"><v>1500</v></c><c r="D18" s="10"><v>59000806231</v></c><c r="E18" s="11"><v>39333870.820666663</v></c><c r="F18" s="10"><v>0</v></c><c r="G18" s="30"><v>27203144075</v></c><c r="H18" s="1" t="s"><v>65</v></c></row><row r="19" spans="1:8" x14ac:dyDescent="0.25"><c r="A19" s="1"><v>61466</v></c><c r="B19" s="1" t="s"><v>66</v></c><c r="C19" s="30"><v>1500</v></c><c r="D19" s="10"><v>-93532009819</v></c><c r="E19" s="11"><v>-62354673.212666668</v></c><c r="F19" s="10"><v>-24675509000</v></c><c r="G19" s="30"><v>3045345000</v></c><c r="H19" s="1" t="s"><v>68</v></c></row><row r="20" spans="1:8" x14ac:dyDescent="0.25"><c r="A20" s="1"><v>61471</v></c><c r="B20" s="1" t="s"><v>69</v></c><c r="C20" s="30"><v>1500</v></c><c r="D20" s="10"><v>290460489287</v></c><c r="E20" s="11"><v>193640326.19133332</v></c><c r="F20" s="10"><v>-16479432511</v></c><c r="G20" s="30"><v>35626487260</v></c><c r="H20" s="1" t="s"><v>397</v></c></row><row r="21" spans="1:8" x14ac:dyDescent="0.25"><c r="A21" s="1"><v>61491</v></c><c r="B21" s="1" t="s"><v>71</v></c><c r="C21" s="30"><v>1500</v></c><c r="D21" s="10"><v>30674172687</v></c><c r="E21" s="11"><v>20449448.458000001</v></c><c r="F21" s="10"><v>0</v></c><c r="G21" s="30"><v>1370982000</v></c><c r="H21" s="1" t="s"><v>73</v></c></row><row r="22" spans="1:8" x14ac:dyDescent="0.25"><c r="A22" s="1"><v>61511</v></c><c r="B22" s="1" t="s"><v>74</v></c><c r="C22" s="30"><v>1500</v></c><c r="D22" s="10"><v>32452907594</v></c><c r="E22" s="11"><v>21635271.729333334</v></c><c r="F22" s="10"><v>0</v></c><c r="G22" s="30"><v>991883027</v></c><c r="H22" s="1" t="s"><v>76</v></c></row><row r="23" spans="1:8" x14ac:dyDescent="0.25"><c r="A23" s="1"><v>61531</v></c><c r="B23" s="1" t="s"><v>77</v></c><c r="C23" s="30"><v>1500</v></c><c r="D23" s="10"><v>542367634277</v></c><c r="E23" s="11"><v>361578422.85133332</v></c><c r="F23" s="10"><v>0</v></c><c r="G23" s="30"><v>45070160000</v></c><c r="H23" s="1" t="s"><v>79</v></c></row><row r="24" spans="1:8" x14ac:dyDescent="0.25"><c r="A24" s="1"><v>65006</v></c><c r="B24" s="1" t="s"><v>80</v></c><c r="C24" s="30"><v>1500</v></c><c r="D24" s="10"><v>110545821171</v></c><c r="E24" s="11"><v>73697214.113999993</v></c><c r="F24" s="10"><v>0</v></c><c r="G24" s="30"><v>12602694000</v></c><c r="H24" s="1" t="s"><v>82</v></c></row><row r="25" spans="1:8" x14ac:dyDescent="0.25"><c r="A25" s="1"><v>61611</v></c><c r="B25" s="1" t="s"><v>83</v></c><c r="C25" s="30"><v>1500</v></c><c r="D25" s="10"><v>38240320693</v></c><c r="E25" s="11"><v>25493547.128666665</v></c><c r="F25" s="10"><v>0</v></c><c r="G25" s="30"><v>3935420000</v></c><c r="H25" s="1" t="s"><v>85</v></c></row><row r="26" spans="1:8" x14ac:dyDescent="0.25"><c r="A26" s="1"><v>61615</v></c><c r="B26" s="1" t="s"><v>86</v></c><c r="C26" s="30"><v>1500</v></c><c r="D26" s="10"><v>754280856422</v></c><c r="E26" s="11"><v>502853904.28133333</v></c><c r="F26" s="10"><v>0</v></c><c r="G26" s="30"><v>63900953000</v></c><c r="H26" s="1" t="s"><v>88</v></c></row><row r="27" spans="1:8" x14ac:dyDescent="0.25"><c r="A27" s="1"><v>61631</v></c><c r="B27" s="1" t="s"><v>89</v></c><c r="C27" s="30"><v>1500</v></c><c r="D27" s="10"><v>326419364730</v></c><c r="E27" s="11"><v>217612909.81999999</v></c><c r="F27" s="10"><v>0</v></c><c r="G27" s="10"><v>29199769000</v></c><c r="H27" s="1" t="s"><v>91</v></c></row><row r="28" spans="1:8" x14ac:dyDescent="0.25"><c r="A28" s="1"><v>65011</v></c><c r="B28" s="1" t="s"><v>92</v></c><c r="C28" s="30"><v>1500</v></c><c r="D28" s="10"><v>1655571803</v></c><c r="E28" s="11"><v>1103714.5353333333</v></c><c r="F28" s="10"><v>0</v></c><c r="G28" s="10"><v>245761194</v></c><c r="H28" s="1" t="s"><v>94</v></c></row><row r="29" spans="1:8" x14ac:dyDescent="0.25"><c r="A29" s="1"><v>65016</v></c><c r="B29" s="1" t="s"><v>95</v></c><c r="C29" s="30"><v>1500</v></c><c r="D29" s="10"><v>3079317837</v></c><c r="E29" s="11"><v>2052878.558</v></c><c r="F29" s="10"><v>0</v></c><c r="G29" s="10"><v>256110440</v></c><c r="H29" s="1" t="s"><v>97</v></c></row><row r="30" spans="1:8" x14ac:dyDescent="0.25"><c r="A30" s="1"><v>62281</v></c><c r="B30" s="1" t="s"><v>255</v></c><c r="C30" s="30"><v>1501</v></c><c r="D30" s="10"><v>412870169837</v></c><c r="E30" s="11"><v>275063404.28847432</v></c><c r="F30" s="10"><v>2791352</v></c><c r="G30" s="10"><v>42143213000</v></c><c r="H30" s="1" t="s"><v>257</v></c></row><row r="31" spans="1:8" x14ac:dyDescent="0.25"><c r="A31" s="1"><v>62286</v></c><c r="B31" s="1" t="s"><v>258</v></c><c r="C31" s="30"><v>1501</v></c><c r="D31" s="10"><v>404691657701</v></c><c r="E31" s="11"><v>269614695.33710861</v></c><c r="F31" s="10"><v>2705351</v></c><c r="G31" s="10"><v>45587053000</v></c><c r="H31" s="1" t="s"><v>260</v></c></row><row r="32" spans="1:8" x14ac:dyDescent="0.25"><c r="A32" s="1"><v>62291</v></c><c r="B32" s="1" t="s"><v>261</v></c><c r="C32" s="30"><v>1501</v></c><c r="D32" s="10"><v>8178512136</v></c><c r="E32" s="11"><v>5448708.9513657559</v></c><c r="F32" s="10"><v>-3443840000</v></c><c r="G32" s="10"><v>1196578828</v></c><c r="H32" s="1" t="s"><v>263</v></c></row><row r="33" spans="1:8" x14ac:dyDescent="0.25"><c r="A33" s="1"><v>62296</v></c><c r="B33" s="1" t="s"><v>264</v></c><c r="C33" s="30"><v>1500</v></c><c r="D33" s="10"><v>273674834447</v></c><c r="E33" s="11"><v>182449889.63133332</v></c><c r="F33" s="10"><v>-15995837492</v></c><c r="G33" s="10"><v>25758242499</v></c><c r="H33" s="1" t="s"><v>266</v></c></row><row r="34" spans="1:8" x14ac:dyDescent="0.25"><c r="A34" s="1"><v>62301</v></c><c r="B34" s="1" t="s"><v>267</v></c><c r="C34" s="30"><v>1501</v></c><c r="D34" s="10"><v>8607142704</v></c><c r="E34" s="11"><v>5734272.2878081277</v></c><c r="F34" s="10"><v>-771512593</v></c><c r="G34" s="10"><v>8671665933</v></c><c r="H34" s="1" t="s"><v>269</v></c></row><row r="35" spans="1:8" x14ac:dyDescent="0.25"><c r="A35" s="1"><v>62306</v></c><c r="B35" s="1" t="s"><v>270</v></c><c r="C35" s="30"><v>1500</v></c><c r="D35" s="10"><v>290460489287</v></c><c r="E35" s="11"><v>193640326.19133332</v></c><c r="F35" s="10"><v>-16479432511</v></c><c r="G35" s="10"><v>35626487260</v></c><c r="H35" s="1" t="s"><v>272</v></c></row><row r="36" spans="1:8" x14ac:dyDescent="0.25"><c r="A36" s="1"><v>61636</v></c><c r="B36" s="1" t="s"><v>98</v></c><c r="C36" s="30"><v>1949</v></c><c r="D36" s="10"><v>80162643516</v></c><c r="E36" s="11"><v>41130140.336582862</v></c><c r="F36" s="10"><v>0</v></c><c r="G36" s="10"><v>1550581000</v></c><c r="H36" s="1" t="s"><v>100</v></c></row><row r="37" spans="1:8" x14ac:dyDescent="0.25"><c r="A37" s="1"><v>61641</v></c><c r="B37" s="1" t="s"><v>101</v></c><c r="C37" s="30"><v>1949</v></c><c r="D37" s="10"><v>31777530673</v></c><c r="E37" s="11"><v>16304530.873781426</v></c><c r="F37" s="10"><v>0</v></c><c r="G37" s="10"><v>1081879558</v></c><c r="H37" s="1" t="s"><v>103</v></c></row><row r="38" spans="1:8" x14ac:dyDescent="0.25"><c r="A38" s="1"><v>61646</v></c><c r="B38" s="1" t="s"><v>104</v></c><c r="C38" s="30"><v>1949</v></c><c r="D38" s="10"><v>9675496256</v></c><c r="E38" s="11"><v>4964338.766546947</v></c><c r="F38" s="10"><v>0</v></c><c r="G38" s="10"><v>443902268</v></c><c r="H38" s="1" t="s"><v>106</v></c></row><row r="39" spans="1:8" x14ac:dyDescent="0.25"><c r="A39" s="1"><v>61651</v></c><c r="B39" s="1" t="s"><v>107</v></c><c r="C39" s="30"><v>1949</v></c><c r="D39" s="10"><v>15126728346</v></c><c r="E39" s="11"><v>7761276.729604926</v></c><c r="F39" s="10"><v>0</v></c><c r="G39" s="10"><v>921111000</v></c><c r="H39" s="1" t="s"><v>109</v></c></row><row r="40" spans="1:8" x14ac:dyDescent="0.25"><c r="A40" s="1"><v>65021</v></c><c r="B40" s="1" t="s"><v>110</v></c><c r="C40" s="30"><v>1949</v></c><c r="D40" s="10"><v>2580376567</v></c><c r="E40" s="11"><v>1323948.9825551566</v></c><c r="F40" s="10"><v>0</v></c><c r="G40" s="10"><v>500654829</v></c><c r="H40" s="1" t="s"><v>112</v></c></row><row r="41" spans="1:8" x14ac:dyDescent="0.25"><c r="A41" s="1"><v>65026</v></c><c r="B41" s="1" t="s"><v>113</v></c><c r="C41" s="30"><v>1949</v></c><c r="D41" s="10"><v>12546351779</v></c><c r="E41" s="11"><v>6437327.7470497694</v></c><c r="F41" s="10"><v>0</v></c><c r="G41" s="10"><v>913953000</v></c><c r="H41" s="1" t="s"><v>115</v></c></row><row r="42" spans="1:8" x14ac:dyDescent="0.25"><c r="A42" s="1"><v>61656</v></c><c r="B42" s="1" t="s"><v>116</v></c><c r="C42" s="30"><v>1645</v></c><c r="D42" s="10"><v>24962782615</v></c><c r="E42" s="11"><v>15174943.838905776</v></c><c r="F42" s="10"><v>0</v></c><c r="G42" s="10"><v>880751894</v></c><c r="H42" s="1" t="s"><v>118</v></c></row><row r="43" spans="1:8" x14ac:dyDescent="0.25"><c r="A43" s="1"><v>61661</v></c><c r="B43" s="1" t="s"><v>119</v></c><c r="C43" s="30"><v>746</v></c><c r="D43" s="10"><v>54926511433</v></c><c r="E43" s="11"><v>73628031.411528155</v></c><c r="F43" s="10"><v>0</v></c><c r="G43" s="10"><v>5014765000</v></c><c r="H43" s="1" t="s"><v>121</v></c></row><row r="44" spans="1:8" x14ac:dyDescent="0.25"><c r="A44" s="1"><v>65031</v></c><c r="B44" s="1" t="s"><v>122</v></c><c r="C44" s="30"><v>1949</v></c><c r="D44" s="10"><v>11425370069</v></c><c r="E44" s="11"><v>5862170.3791688047</v></c><c r="F44" s="10"><v>0</v></c><c r="G44" s="10"><v>2145629000</v></c><c r="H44" s="1" t="s"><v>124</v></c></row><row r="45" spans="1:8" x14ac:dyDescent="0.25"><c r="A45" s="1"><v>61666</v></c><c r="B45" s="1" t="s"><v>125</v></c><c r="C45" s="30"><v>746</v></c><c r="D45" s="10"><v>1911140486</v></c><c r="E45" s="11"><v>2561850.5174262733</v></c><c r="F45" s="10"><v>0</v></c><c r="G45" s="10"><v>958793000</v></c><c r="H45" s="1" t="s"><v>127</v></c></row><row r="46" spans="1:8" x14ac:dyDescent="0.25"><c r="A46" s="1"><v>61671</v></c><c r="B46" s="1" t="s"><v>128</v></c><c r="C46" s="30"><v>1949</v></c><c r="D46" s="10"><v>12405623810</v></c><c r="E46" s="11"><v>6365122.5295023089</v></c><c r="F46" s="10"><v>-193690</v></c><c r="G46" s="10"><v>1423602000</v></c><c r="H46" s="1" t="s"><v>130</v></c></row><row r="47" spans="1:8" x14ac:dyDescent="0.25"><c r="A47" s="1"><v>61676</v></c><c r="B47" s="1" t="s"><v>131</v></c><c r="C47" s="30"><v>1949</v></c><c r="D47" s="10"><v>242373827204</v></c><c r="E47" s="11"><v>124358043.71677783</v></c><c r="F47" s="10"><v>0</v></c><c r="G47" s="10"><v>7767570000</v></c><c r="H47" s="1" t="s"><v>133</v></c></row><row r="48" spans="1:8" x14ac:dyDescent="0.25"><c r="A48" s="1"><v>61681</v></c><c r="B48" s="1" t="s"><v>134</v></c><c r="C48" s="30"><v>1949</v></c><c r="D48" s="10"><v>2131041539</v></c><c r="E48" s="11"><v>1093402.5341200617</v></c><c r="F48" s="10"><v>0</v></c><c r="G48" s="10"><v>612126947</v></c><c r="H48" s="1" t="s"><v>136</v></c></row><row r="49" spans="1:8" x14ac:dyDescent="0.25"><c r="A49" s="1"><v>61686</v></c><c r="B49" s="1" t="s"><v>137</v></c><c r="C49" s="30"><v>1949</v></c><c r="D49" s="10"><v>76879641366</v></c><c r="E49" s="11"><v>39445685.667521805</v></c><c r="F49" s="10"><v>0</v></c><c r="G49" s="10"><v>802559112</v></c><c r="H49" s="1" t="s"><v>139</v></c></row><row r="50" spans="1:8" x14ac:dyDescent="0.25"><c r="A50" s="1"><v>61691</v></c><c r="B50" s="1" t="s"><v>140</v></c><c r="C50" s="30"><v>1949</v></c><c r="D50" s="10"><v>15065496182</v></c><c r="E50" s="11"><v>7729859.5084658796</v></c><c r="F50" s="10"><v>0</v></c><c r="G50" s="10"><v>332488321</v></c><c r="H50" s="1" t="s"><v>142</v></c></row><row r="51" spans="1:8" x14ac:dyDescent="0.25"><c r="A51" s="1"><v>61696</v></c><c r="B51" s="1" t="s"><v>143</v></c><c r="C51" s="30"><v>1949</v></c><c r="D51" s="10"><v>26732919933</v></c><c r="E51" s="11"><v>13716223.670087224</v></c><c r="F51" s="10"><v>0</v></c><c r="G51" s="10"><v>234247000</v></c><c r="H51" s="1" t="s"><v>145</v></c></row><row r="52" spans="1:8" x14ac:dyDescent="0.25"><c r="A52" s="1"><v>61701</v></c><c r="B52" s="1" t="s"><v>146</v></c><c r="C52" s="30"><v>1949</v></c><c r="D52" s="10"><v>6467625203</v></c><c r="E52" s="11"><v>3318432.6336582862</v></c><c r="F52" s="10"><v>0</v></c><c r="G52" s="10"><v>181349000</v></c><c r="H52" s="1" t="s"><v>148</v></c></row><row r="53" spans="1:8" x14ac:dyDescent="0.25"><c r="A53" s="1"><v>61706</v></c><c r="B53" s="1" t="s"><v>149</v></c><c r="C53" s="30"><v>1949</v></c><c r="D53" s="10"><v>470633673</v></c><c r="E53" s="11"><v>241474.43458183683</v></c><c r="F53" s="10"><v>0</v></c><c r="G53" s="10"><v>99022510</v></c><c r="H53" s="1" t="s"><v>151</v></c></row><row r="54" spans="1:8" x14ac:dyDescent="0.25"><c r="A54" s="1"><v>61711</v></c><c r="B54" s="1" t="s"><v>152</v></c><c r="C54" s="30"><v>1949</v></c><c r="D54" s="10"><v>9307046884</v></c><c r="E54" s="11"><v>4775293.4243201641</v></c><c r="F54" s="10"><v>-114446</v></c><c r="G54" s="10"><v>394763000</v></c><c r="H54" s="1" t="s"><v>154</v></c></row><row r="55" spans="1:8" x14ac:dyDescent="0.25"><c r="A55" s="1"><v>61716</v></c><c r="B55" s="1" t="s"><v>155</v></c><c r="C55" s="30"><v>1949</v></c><c r="D55" s="10"><v>11037373171</v></c><c r="E55" s="11"><v>5663095.5212929705</v></c><c r="F55" s="10"><v>-371179000</v></c><c r="G55" s="10"><v>3415176188</v></c><c r="H55" s="1" t="s"><v>157</v></c></row><row r="56" spans="1:8" x14ac:dyDescent="0.25"><c r="A56" s="1"><v>61821</v></c><c r="B56" s="1" t="s"><v>158</v></c><c r="C56" s="30"><v>1949</v></c><c r="D56" s="10"><v>7233258755</v></c><c r="E56" s="11"><v>3711266.6777834785</v></c><c r="F56" s="10"><v>-4249990</v></c><c r="G56" s="10"><v>684136960</v></c><c r="H56" s="1" t="s"><v>160</v></c></row><row r="57" spans="1:8" x14ac:dyDescent="0.25"><c r="A57" s="1"><v>61826</v></c><c r="B57" s="1" t="s"><v>161</v></c><c r="C57" s="30"><v>1949</v></c><c r="D57" s="10"><v>155325036706</v></c><c r="E57" s="11"><v>79694734.071831703</v></c><c r="F57" s="10"><v>-273779</v></c><c r="G57" s="10"><v>3446859868</v></c><c r="H57" s="1" t="s"><v>163</v></c></row><row r="58" spans="1:8" x14ac:dyDescent="0.25"><c r="A58" s="1"><v>65033</v></c><c r="B58" s="1" t="s"><v>164</v></c><c r="C58" s="30"><v>1949</v></c><c r="D58" s="10"><v>397698863910</v></c><c r="E58" s="11"><v>204052777.78860953</v></c><c r="F58" s="10"><v>0</v></c><c r="G58" s="10"><v>9062360000</v></c><c r="H58" s="1" t="s"><v>166</v></c></row><row r="59" spans="1:8" x14ac:dyDescent="0.25"><c r="A59" s="1"><v>61831</v></c><c r="B59" s="1" t="s"><v>167</v></c><c r="C59" s="30"><v>1645</v></c><c r="D59" s="10"><v>5998672240</v></c><c r="E59" s="11"><v>3646609.2644376899</v></c><c r="F59" s="10"><v>-570014</v></c><c r="G59" s="10"><v>145027310</v></c><c r="H59" s="1" t="s"><v>169</v></c></row><row r="60" spans="1:8" x14ac:dyDescent="0.25"><c r="A60" s="1"><v>61836</v></c><c r="B60" s="1" t="s"><v>170</v></c><c r="C60" s="30"><v>1645</v></c><c r="D60" s="10"><v>4084798244</v></c><c r="E60" s="11"><v>2483160.0267477203</v></c><c r="F60" s="10"><v>-102578</v></c><c r="G60" s="10"><v>398019624</v></c><c r="H60" s="1" t="s"><v>172</v></c></row><row r="61" spans="1:8" x14ac:dyDescent="0.25"><c r="A61" s="1"><v>61841</v></c><c r="B61" s="1" t="s"><v>173</v></c><c r="C61" s="30"><v>1645</v></c><c r="D61" s="10"><v>1182700715</v></c><c r="E61" s="11"><v>718967</v></c><c r="F61" s="10"><v>0</v></c><c r="G61" s="10"><v>148800926</v></c><c r="H61" s="1" t="s"><v>175</v></c></row><row r="62" spans="1:8" x14ac:dyDescent="0.25"><c r="A62" s="1"><v>61846</v></c><c r="B62" s="1" t="s"><v>176</v></c><c r="C62" s="30"><v>1949</v></c><c r="D62" s="10"><v>7908402595</v></c><c r="E62" s="11"><v>4057671.9317598767</v></c><c r="F62" s="10"><v>-5632040</v></c><c r="G62" s="10"><v>1012949529</v></c><c r="H62" s="1" t="s"><v>178</v></c></row><row r="63" spans="1:8" x14ac:dyDescent="0.25"><c r="A63" s="1"><v>61851</v></c><c r="B63" s="1" t="s"><v>179</v></c><c r="C63" s="30"><v>1949</v></c><c r="D63" s="10"><v>19174573794</v></c><c r="E63" s="11"><v>9838159.9763981532</v></c><c r="F63" s="10"><v>-153572</v></c><c r="G63" s="10"><v>1161750455</v></c><c r="H63" s="1" t="s"><v>181</v></c></row><row r="64" spans="1:8" x14ac:dyDescent="0.25"><c r="A64" s="1"><v>61856</v></c><c r="B64" s="1" t="s"><v>182</v></c><c r="C64" s="30"><v>1949</v></c><c r="D64" s="10"><v>416873437704</v></c><c r="E64" s="11"><v>213890937.7650077</v></c><c r="F64" s="10"><v>0</v></c><c r="G64" s="10"><v>9111445000</v></c><c r="H64" s="1" t="s"><v>184</v></c></row><row r="65" spans="1:8" x14ac:dyDescent="0.25"><c r="A65" s="1"><v>61861</v></c><c r="B65" s="1" t="s"><v>185</v></c><c r="C65" s="30"><v>1949</v></c><c r="D65" s="10"><v>113474889377</v></c><c r="E65" s="11"><v>58222108.454079017</v></c><c r="F65" s="10"><v>0</v></c><c r="G65" s="10"><v>2710436200</v></c><c r="H65" s="1" t="s"><v>187</v></c></row><row r="66" spans="1:8" x14ac:dyDescent="0.25"><c r="A66" s="1"><v>61866</v></c><c r="B66" s="1" t="s"><v>188</v></c><c r="C66" s="30"><v>1949</v></c><c r="D66" s="10"><v>67777013497</v></c><c r="E66" s="11"><v>34775276.293996923</v></c><c r="F66" s="10"><v>0</v></c><c r="G66" s="10"><v>1654247785</v></c><c r="H66" s="1" t="s"><v>190</v></c></row><row r="67" spans="1:8" x14ac:dyDescent="0.25"><c r="A67" s="1"><v>61886</v></c><c r="B67" s="1" t="s"><v>191</v></c><c r="C67" s="30"><v>1949</v></c><c r="D67" s="10"><v>39312662206</v></c><c r="E67" s="11"><v>20170683.533093896</v></c><c r="F67" s="10"><v>0</v></c><c r="G67" s="10"><v>1162850481</v></c><c r="H67" s="1" t="s"><v>193</v></c></row><row r="68" spans="1:8" x14ac:dyDescent="0.25"><c r="A68" s="1"><v>61891</v></c><c r="B68" s="1" t="s"><v>194</v></c><c r="C68" s="30"><v>1949</v></c><c r="D68" s="10"><v>17726171487</v></c><c r="E68" s="11"><v>9095008.4592098519</v></c><c r="F68" s="10"><v>0</v></c><c r="G68" s="10"><v>705852493</v></c><c r="H68" s="1" t="s"><v>196</v></c></row><row r="69" spans="1:8" x14ac:dyDescent="0.25"><c r="A69" s="1"><v>61911</v></c><c r="B69" s="1" t="s"><v>197</v></c><c r="C69" s="30"><v>1949</v></c><c r="D69" s="10"><v>16500100724</v></c><c r="E69" s="11"><v>8465931.6182657778</v></c><c r="F69" s="10"><v>0</v></c><c r="G69" s="10"><v>817182000</v></c><c r="H69" s="1" t="s"><v>199</v></c></row><row r="70" spans="1:8" x14ac:dyDescent="0.25"><c r="A70" s="1"><v>61916</v></c><c r="B70" s="1" t="s"><v>200</v></c><c r="C70" s="30"><v>1949</v></c><c r="D70" s="10"><v>7717578107</v></c><c r="E70" s="11"><v>3959763.0102616725</v></c><c r="F70" s="10"><v>0</v></c><c r="G70" s="30"><v>536619000</v></c><c r="H70" s="1" t="s"><v>202</v></c></row><row r="71" spans="1:8" x14ac:dyDescent="0.25"><c r="A71" s="1"><v>61936</v></c><c r="B71" s="1" t="s"><v>203</v></c><c r="C71" s="30"><v>1949</v></c><c r="D71" s="10"><v>32768438519</v></c><c r="E71" s="11"><v>16812949.471010774</v></c><c r="F71" s="10"><v>0</v></c><c r="G71" s="30"><v>997040191</v></c><c r="H71" s="1" t="s"><v>205</v></c></row><row r="72" spans="1:8" x14ac:dyDescent="0.25"><c r="A72" s="1"><v>61941</v></c><c r="B72" s="1" t="s"><v>206</v></c><c r="C72" s="30"><v>1949</v></c><c r="D72" s="10"><v>15756568236</v></c><c r="E72" s="11"><v>8084437.2683427399</v></c><c r="F72" s="10"><v>0</v></c><c r="G72" s="30"><v>505280841</v></c><c r="H72" s="1" t="s"><v>208</v></c></row><row r="73" spans="1:8" x14ac:dyDescent="0.25"><c r="A73" s="1"><v>61961</v></c><c r="B73" s="1" t="s"><v>209</v></c><c r="C73" s="30"><v>1949</v></c><c r="D73" s="10"><v>22281557902</v></c><c r="E73" s="11"><v>11432302.669061057</v></c><c r="F73" s="10"><v>0</v></c><c r="G73" s="30"><v>275649828</v></c><c r="H73" s="1" t="s"><v>211</v></c></row><row r="74" spans="1:8" x14ac:dyDescent="0.25"><c r="A74" s="1"><v>61966</v></c><c r="B74" s="1" t="s"><v>212</v></c><c r="C74" s="30"><v>1949</v></c><c r="D74" s="10"><v>10764527726</v></c><c r="E74" s="11"><v>5523102.9892252441</v></c><c r="F74" s="10"><v>0</v></c><c r="G74" s="30"><v>109315321</v></c><c r="H74" s="1" t="s"><v>214</v></c></row><row r="75" spans="1:8" x14ac:dyDescent="0.25"><c r="A75" s="1"><v>61986</v></c><c r="B75" s="1" t="s"><v>215</v></c><c r="C75" s="30"><v>1949</v></c><c r="D75" s="10"><v>37443297734</v></c><c r="E75" s="11"><v>19211543.21908671</v></c><c r="F75" s="10"><v>0</v></c><c r="G75" s="30"><v>401747172</v></c><c r="H75" s="1" t="s"><v>217</v></c></row><row r="76" spans="1:8" x14ac:dyDescent="0.25"><c r="A76" s="1"><v>61991</v></c><c r="B76" s="1" t="s"><v>218</v></c><c r="C76" s="30"><v>1949</v></c><c r="D76" s="10"><v>17238163752</v></c><c r="E76" s="11"><v>8844619.6777834781</v></c><c r="F76" s="10"><v>0</v></c><c r="G76" s="30"><v>205678836</v></c><c r="H76" s="1" t="s"><v>220</v></c></row><row r="77" spans="1:8" x14ac:dyDescent="0.25"><c r="A77" s="1"><v>62046</v></c><c r="B77" s="1" t="s"><v>221</v></c><c r="C77" s="30"><v>1949</v></c><c r="D77" s="10"><v>19977380705</v></c><c r="E77" s="11"><v>10250067.062596204</v></c><c r="F77" s="10"><v>0</v></c><c r="G77" s="30"><v>292914000</v></c><c r="H77" s="1" t="s"><v>223</v></c></row><row r="78" spans="1:8" x14ac:dyDescent="0.25"><c r="A78" s="1"><v>62071</v></c><c r="B78" s="1" t="s"><v>224</v></c><c r="C78" s="30"><v>1645</v></c><c r="D78" s="10"><v>32049906836</v></c><c r="E78" s="11"><v>19483226.040121581</v></c><c r="F78" s="10"><v>0</v></c><c r="G78" s="30"><v>996990473</v></c><c r="H78" s="1" t="s"><v>226</v></c></row><row r="79" spans="1:8" x14ac:dyDescent="0.25"><c r="A79" s="1"><v>62076</v></c><c r="B79" s="1" t="s"><v>227</v></c><c r="C79" s="30"><v>1645</v></c><c r="D79" s="10"><v>9386115331</v></c><c r="E79" s="11"><v>5705845.1860182369</v></c><c r="F79" s="10"><v>0</v></c><c r="G79" s="30"><v>382231834</v></c><c r="H79" s="1" t="s"><v>229</v></c></row><row r="80" spans="1:8" x14ac:dyDescent="0.25"><c r="A80" s="1"><v>62096</v></c><c r="B80" s="1" t="s"><v>230</v></c><c r="C80" s="30"><v>746</v></c><c r="D80" s="10"><v>54822689445</v></c><c r="E80" s="11"><v>73488859.845844507</v></c><c r="F80" s="10"><v>0</v></c><c r="G80" s="30"><v>4958820000</v></c><c r="H80" s="1" t="s"><v>232</v></c></row><row r="81" spans="1:8" x14ac:dyDescent="0.25"><c r="A81" s="1"><v>62101</v></c><c r="B81" s="1" t="s"><v>233</v></c><c r="C81" s="30"><v>746</v></c><c r="D81" s="10"><v>22853615553</v></c><c r="E81" s="11"><v>30634873.395442359</v></c><c r="F81" s="10"><v>0</v></c><c r="G81" s="30"><v>2471482000</v></c><c r="H81" s="1" t="s"><v>235</v></c></row><row r="82" spans="1:8" x14ac:dyDescent="0.25"><c r="A82" s="1"><v>62121</v></c><c r="B82" s="1" t="s"><v>236</v></c><c r="C82" s="30"><v>746</v></c><c r="D82" s="10"><v>1762823432</v></c><c r="E82" s="11"><v>2363034.0911528151</v></c><c r="F82" s="10"><v>0</v></c><c r="G82" s="30"><v>762928000</v></c><c r="H82" s="1" t="s"><v>238</v></c></row><row r="83" spans="1:8" x14ac:dyDescent="0.25"><c r="A83" s="1"><v>62126</v></c><c r="B83" s="1" t="s"><v>239</v></c><c r="C83" s="30"><v>746</v></c><c r="D83" s="10"><v>508743263</v></c><c r="E83" s="11"><v>681961.47855227883</v></c><c r="F83" s="10"><v>0</v></c><c r="G83" s="30"><v>318440000</v></c><c r="H83" s="1" t="s"><v>241</v></c></row><row r="84" spans="1:8" x14ac:dyDescent="0.25"><c r="A84" s="1"><v>62146</v></c><c r="B84" s="1" t="s"><v>242</v></c><c r="C84" s="30"><v>1949</v></c><c r="D84" s="10"><v>37821584653</v></c><c r="E84" s="11"><v>19405636.045664445</v></c><c r="F84" s="10"><v>-329346356</v></c><c r="G84" s="30"><v>4888626638</v></c><c r="H84" s="1" t="s"><v>244</v></c></row><row r="85" spans="1:8" x14ac:dyDescent="0.25"><c r="A85" s="1"><v>62151</v></c><c r="B85" s="1" t="s"><v>245</v></c><c r="C85" s="30"><v>1949</v></c><c r="D85" s="10"><v>1449625118</v></c><c r="E85" s="11"><v>743778.92149820423</v></c><c r="F85" s="10"><v>0</v></c><c r="G85" s="30"><v>74055807</v></c><c r="H85" s="1" t="s"><v>247</v></c></row><row r="86" spans="1:8" x14ac:dyDescent="0.25"><c r="A86" s="1"><v>62256</v></c><c r="B86" s="1" t="s"><v>248</v></c><c r="C86" s="30"><v>1949</v></c><c r="D86" s="10"><v>408215331533</v></c><c r="E86" s="11"><v>209448605.19907644</v></c><c r="F86" s="10"><v>0</v></c><c r="G86" s="30"><v>9273968000</v></c><c r="H86" s="1" t="s"><v>398</v></c></row><row r="87" spans="1:8" x14ac:dyDescent="0.25"><c r="A87" s="1"><v>62261</v></c><c r="B87" s="1" t="s"><v>250</v></c><c r="C87" s="30"><v>1949</v></c><c r="D87" s="10"><v>171178122070</v></c><c r="E87" s="11"><v>87828692.698819906</v></c><c r="F87" s="10"><v>0</v></c><c r="G87" s="30"><v>4365460000</v></c><c r="H87" s="1" t="s"><v>399</v></c></row><row r="88" spans="1:8" x14ac:dyDescent="0.25"><c r="A88" s="1"><v>62266</v></c><c r="B88" s="1" t="s"><v>252</v></c><c r="C88" s="30"><v>1949</v></c><c r="D88" s="10"><v>70567360438</v></c><c r="E88" s="11"><v>36206957.638789125</v></c><c r="F88" s="10"><v>-145658534</v></c><c r="G88" s="30"><v>3118529356</v></c><c r="H88" s="1" t="s"><v>400</v></c></row><row r="89" spans="1:8" x14ac:dyDescent="0.25"><c r="A89" s="1"><v>62268</v></c><c r="B89" s="1" t="s"><v>401</v></c><c r="C89" s="30"><v>1949</v></c><c r="D89" s="10"><v>23171753941</v></c><c r="E89" s="11"><v>11889047.686505901</v></c><c r="F89" s="10"><v>-188000</v></c><c r="G89" s="30"><v>292603000</v></c><c r="H89" s="1" t="s"><v>402</v></c></row><row r="90" spans="1:8" x14ac:dyDescent="0.25"><c r="A90" s="1"><v>62271</v></c><c r="B90" s="1" t="s"><v>403</v></c><c r="C90" s="30"><v>1949</v></c><c r="D90" s="10"><v>23355194812</v></c><c r="E90" s="11"><v>11983168.194971781</v></c><c r="F90" s="10"><v>0</v></c><c r="G90" s="30"><v>548412000</v></c><c r="H90" s="1" t="s"><v>404</v></c></row><row r="91" spans="1:8" x14ac:dyDescent="0.25"><c r="A91" s="1"><v>65088</v></c><c r="B91" s="1" t="s"><v>405</v></c><c r="C91" s="30"><v>1949</v></c><c r="D91" s="10"><v>7841869276</v></c><c r="E91" s="11"><v>4023534.7747562854</v></c><c r="F91" s="10"><v>-10468019</v></c><c r="G91" s="30"><v>327445930</v></c><c r="H91" s="1" t="s"><v>254</v></c></row><row r="92" spans="1:8" x14ac:dyDescent="0.25"><c r="A92" s="1"><v>62276</v></c><c r="B92" s="1" t="s"><v>406</v></c><c r="C92" s="30"><v>1949</v></c><c r="D92" s="10"><v>112101030996</v></c><c r="E92" s="11"><v>57517204.205233455</v></c><c r="F92" s="10"><v>-8516000</v></c><c r="G92" s="30"><v>2742682442</v></c><c r="H92" s="1" t="s"><v>407</v></c></row><row r="93" spans="1:8" x14ac:dyDescent="0.25"><c r="A93" s="1"><v>67056</v></c><c r="B93" s="1" t="s"><v>378</v></c><c r="C93" s="30"><v>1401</v></c><c r="D93" s="10"><v>14336322176</v></c><c r="E93" s="11"><v>10232920.896502499</v></c><c r="F93" s="10"><v>-393622917</v></c><c r="G93" s="30"><v>1891611000</v></c><c r="H93" s="1" t="s"><v>408</v></c></row><row r="94" spans="1:8" x14ac:dyDescent="0.25"><c r="A94" s="1"><v>67061</v></c><c r="B94" s="1" t="s"><v>380</v></c><c r="C94" s="30"><v>1401</v></c><c r="D94" s="10"><v>118258939000</v></c><c r="E94" s="11"><v>84410377.58743754</v></c><c r="F94" s="10"><v>-257266899</v></c><c r="G94" s="30"><v>15147313000</v></c><c r="H94" s="1" t="s"><v>409</v></c></row><row r="95" spans="1:8" x14ac:dyDescent="0.25"><c r="A95" s="1"><v>67066</v></c><c r="B95" s="1" t="s"><v>382</v></c><c r="C95" s="30"><v>1401</v></c><c r="D95" s="10"><v>13964297505</v></c><c r="E95" s="11"><v>9967378.6616702359</v></c><c r="F95" s="10"><v>-12508371</v></c><c r="G95" s="30"><v>1056704429</v></c><c r="H95" s="1" t="s"><v>428</v></c></row><row r="96" spans="1:8" x14ac:dyDescent="0.25"><c r="A96" s="1"><v>67071</v></c><c r="B96" s="1" t="s"><v>384</v></c><c r="C96" s="30"><v>1401</v></c><c r="D96" s="10"><v>33593005148</v></c><c r="E96" s="11"><v>23977876.622412562</v></c><c r="F96" s="10"><v>-8286008</v></c><c r="G96" s="30"><v>4605158000</v></c><c r="H96" s="1" t="s"><v>429</v></c></row><row r="97" spans="1:8" x14ac:dyDescent="0.25"><c r="A97" s="1"><v>67076</v></c><c r="B97" s="1" t="s"><v>501</v></c><c r="C97" s="30"><v>1295</v></c><c r="D97" s="10"><v>6339917707</v></c><c r="E97" s="11"><v>4895689.349034749</v></c><c r="F97" s="10"><v>-67870000</v></c><c r="G97" s="30"><v>1048152000</v></c><c r="H97" s="1" t="s"><v>503</v></c></row><row r="98" spans="1:8" x14ac:dyDescent="0.25"><c r="A98" s="1"><v>67081</v></c><c r="B98" s="1" t="s"><v>504</v></c><c r="C98" s="30"><v>1295</v></c><c r="D98" s="10"><v>131826873815</v></c><c r="E98" s="11"><v>101796813.75675675</v></c><c r="F98" s="10"><v>-77589218</v></c><c r="G98" s="30"><v>16323618000</v></c><c r="H98" s="1" t="s"><v>506</v></c></row><row r="99" spans="1:8" x14ac:dyDescent="0.25"><c r="A99" s="1"><v>67086</v></c><c r="B99" s="1" t="s"><v>507</v></c><c r="C99" s="30"><v>1295</v></c><c r="D99" s="10"><v>29170168267</v></c><c r="E99" s="11"><v>22525226.461003862</v></c><c r="F99" s="10"><v>-8333092</v></c><c r="G99" s="30"><v>4146829000</v></c><c r="H99" s="1" t="s"><v>509</v></c></row><row r="100" spans="1:8" x14ac:dyDescent="0.25"><c r="A100" s="1"><v>67091</v></c><c r="B100" s="1" t="s"><v>510</v></c><c r="C100" s="30"><v>1295</v></c><c r="D100" s="10"><v>23895129865</v></c><c r="E100" s="11"><v>18451837.733590733</v></c><c r="F100" s="10"><v>-1365206</v></c><c r="G100" s="30"><v>4220566000</v></c><c r="H100" s="1" t="s"><v>512</v></c></row><row r="101" spans="1:8" x14ac:dyDescent="0.25"><c r="A101" s="1"><v>62321</v></c><c r="B101" s="1" t="s"><v>273</v></c><c r="C101" s="30"><v>1886</v></c><c r="D101" s="10"><v>19479812981</v></c><c r="E101" s="11"><v>10328638.908271475</v></c><c r="F101" s="10"><v>0</v></c><c r="G101" s="30"><v>173823000</v></c><c r="H101" s="1" t="s"><v>275</v></c></row><row r="102" spans="1:8" x14ac:dyDescent="0.25"><c r="A102" s="1"><v>62326</v></c><c r="B102" s="1" t="s"><v>276</v></c><c r="C102" s="30"><v>1886</v></c><c r="D102" s="10"><v>4317181032</v></c><c r="E102" s="11"><v>2289067.3552492047</v></c><c r="F102" s="10"><v>0</v></c><c r="G102" s="30"><v>92258732</v></c><c r="H102" s="1" t="s"><v>278</v></c></row><row r="103" spans="1:8" x14ac:dyDescent="0.25"><c r="A103" s="1"><v>62331</v></c><c r="B103" s="1" t="s"><v>279</v></c><c r="C103" s="30"><v>1886</v></c><c r="D103" s="10"><v>8365988243</v></c><c r="E103" s="11"><v>4435836.8202545065</v></c><c r="F103" s="10"><v>0</v></c><c r="G103" s="10"><v>180670000</v></c><c r="H103" s="1" t="s"><v>281</v></c></row><row r="104" spans="1:8" x14ac:dyDescent="0.25"><c r="A104" s="1"><v>62336</v></c><c r="B104" s="1" t="s"><v>282</v></c><c r="C104" s="30"><v>1886</v></c><c r="D104" s="10"><v>224905449</v></c><c r="E104" s="11"><v>119249.97295864263</v></c><c r="F104" s="10"><v>0</v></c><c r="G104" s="30"><v>29213875</v></c><c r="H104" s="1" t="s"><v>284</v></c></row><row r="105" spans="1:8" x14ac:dyDescent="0.25"><c r="A105" s="1"><v>62341</v></c><c r="B105" s="1" t="s"><v>285</v></c><c r="C105" s="30"><v>1886</v></c><c r="D105" s="10"><v>4189900375</v></c><c r="E105" s="11"><v>2221580.2624602332</v></c><c r="F105" s="10"><v>0</v></c><c r="G105" s="30"><v>202899021</v></c><c r="H105" s="1" t="s"><v>287</v></c></row><row r="106" spans="1:8" x14ac:dyDescent="0.25"><c r="A106" s="1"><v>62346</v></c><c r="B106" s="1" t="s"><v>288</v></c><c r="C106" s="30"><v>1886</v></c><c r="D106" s="10"><v>18026674189</v></c><c r="E106" s="11"><v>9558151.7439024393</v></c><c r="F106" s="10"><v>0</v></c><c r="G106" s="30"><v>526512000</v></c><c r="H106" s="1" t="s"><v>290</v></c></row><row r="107" spans="1:8" x14ac:dyDescent="0.25"><c r="A107" s="1"><v>62351</v></c><c r="B107" s="1" t="s"><v>291</v></c><c r="C107" s="30"><v>1886</v></c><c r="D107" s="10"><v>54604462269</v></c><c r="E107" s="11"><v>28952525.063096501</v></c><c r="F107" s="10"><v>0</v></c><c r="G107" s="30"><v>778535000</v></c><c r="H107" s="1" t="s"><v>293</v></c></row><row r="108" spans="1:8" x14ac:dyDescent="0.25"><c r="A108" s="1"><v>62356</v></c><c r="B108" s="1" t="s"><v>294</v></c><c r="C108" s="30"><v>1886</v></c><c r="D108" s="10"><v>32333083306</v></c><c r="E108" s="11"><v>17143734.520678684</v></c><c r="F108" s="10"><v>0</v></c><c r="G108" s="30"><v>462730000</v></c><c r="H108" s="1" t="s"><v>296</v></c></row><row r="109" spans="1:8" x14ac:dyDescent="0.25"><c r="A109" s="1"><v>62361</v></c><c r="B109" s="1" t="s"><v>297</v></c><c r="C109" s="30"><v>1886</v></c><c r="D109" s="10"><v>2364134921</v></c><c r="E109" s="11"><v>1253517.9856839874</v></c><c r="F109" s="10"><v>0</v></c><c r="G109" s="30"><v>42265422</v></c><c r="H109" s="1" t="s"><v>299</v></c></row><row r="110" spans="1:8" x14ac:dyDescent="0.25"><c r="A110" s="1"><v>62366</v></c><c r="B110" s="1" t="s"><v>300</v></c><c r="C110" s="30"><v>1886</v></c><c r="D110" s="10"><v>34697218227</v></c><c r="E110" s="11"><v>18397252.506362673</v></c><c r="F110" s="10"><v>0</v></c><c r="G110" s="30"><v>485621000</v></c><c r="H110" s="1" t="s"><v>302</v></c></row><row r="111" spans="1:8" x14ac:dyDescent="0.25"><c r="A111" s="1"><v>62371</v></c><c r="B111" s="1" t="s"><v>303</v></c><c r="C111" s="30"><v>1886</v></c><c r="D111" s="10"><v>19907244042</v></c><c r="E111" s="11"><v>10555272.556733828</v></c><c r="F111" s="10"><v>0</v></c><c r="G111" s="30"><v>292914000</v></c><c r="H111" s="1" t="s"><v>305</v></c></row><row r="112" spans="1:8" x14ac:dyDescent="0.25"><c r="A112" s="1"><v>62378</v></c><c r="B112" s="1" t="s"><v>522</v></c><c r="C112" s="30"><v>1886</v></c><c r="D112" s="10"><v>11199525623</v></c><c r="E112" s="11"><v>5938242.6420996822</v></c><c r="F112" s="10"><v>0</v></c><c r="G112" s="30"><v>100725000</v></c><c r="H112" s="1" t="s"><v>644</v></c></row><row r="113" spans="1:8" x14ac:dyDescent="0.25"><c r="A113" s="1"><v>62380</v></c><c r="B113" s="1" t="s"><v>524</v></c><c r="C113" s="30"><v>1886</v></c><c r="D113" s="10"><v>10571676974</v></c><c r="E113" s="11"><v>5605343.0402969243</v></c><c r="F113" s="10"><v>0</v></c><c r="G113" s="30"><v>95869000</v></c><c r="H113" s="1" t="s"><v>645</v></c></row><row r="114" spans="1:8" x14ac:dyDescent="0.25"><c r="A114" s="1"><v>62382</v></c><c r="B114" s="1" t="s"><v>526</v></c><c r="C114" s="30"><v>1886</v></c><c r="D114" s="10"><v>627848649</v></c><c r="E114" s="11"><v>332899.60180275718</v></c><c r="F114" s="10"><v>0</v></c><c r="G114" s="30"><v>27756125</v></c><c r="H114" s="1" t="s"><v>528</v></c></row><row r="115" spans="1:8" x14ac:dyDescent="0.25"><c r="A115" s="1"><v>62384</v></c><c r="B115" s="1" t="s"><v>529</v></c><c r="C115" s="30"><v>1886</v></c><c r="D115" s="10"><v>1754101897</v></c><c r="E115" s="11"><v>930064.63255567336</v></c><c r="F115" s="10"><v>0</v></c><c r="G115" s="30"><v>105306000</v></c><c r="H115" s="1" t="s"><v>531</v></c></row><row r="116" spans="1:8" x14ac:dyDescent="0.25"><c r="A116" s="1"><v>62386</v></c><c r="B116" s="1" t="s"><v>532</v></c><c r="C116" s="30"><v>1886</v></c><c r="D116" s="10"><v>1647164441</v></c><c r="E116" s="11"><v>873363.96659597033</v></c><c r="F116" s="10"><v>0</v></c><c r="G116" s="30"><v>98823995</v></c><c r="H116" s="1" t="s"><v>534</v></c></row><row r="117" spans="1:8" x14ac:dyDescent="0.25"><c r="A117" s="1"><v>62388</v></c><c r="B117" s="1" t="s"><v>535</v></c><c r="C117" s="30"><v>1886</v></c><c r="D117" s="10"><v>106937456</v></c><c r="E117" s="11"><v>56700.665959703074</v></c><c r="F117" s="10"><v>0</v></c><c r="G117" s="30"><v>9629000</v></c><c r="H117" s="1" t="s"><v>537</v></c></row><row r="118" spans="1:8" x14ac:dyDescent="0.25"><c r="A118" s="1"><v>62390</v></c><c r="B118" s="1" t="s"><v>538</v></c><c r="C118" s="30"><v>1886</v></c><c r="D118" s="10"><v>5558336247</v></c><c r="E118" s="11"><v>2947156.0164369033</v></c><c r="F118" s="10"><v>0</v></c><c r="G118" s="30"><v>127173941</v></c><c r="H118" s="1" t="s"><v>540</v></c></row><row r="119" spans="1:8" x14ac:dyDescent="0.25"><c r="A119" s="1"><v>62392</v></c><c r="B119" s="1" t="s"><v>541</v></c><c r="C119" s="30"><v>1886</v></c><c r="D119" s="10"><v>5321796612</v></c><c r="E119" s="11"><v>2821737.3340402967</v></c><c r="F119" s="10"><v>0</v></c><c r="G119" s="30"><v>127173941</v></c><c r="H119" s="1" t="s"><v>543</v></c></row><row r="120" spans="1:8" x14ac:dyDescent="0.25"><c r="A120" s="1"><v>62394</v></c><c r="B120" s="1" t="s"><v>544</v></c><c r="C120" s="30"><v>1886</v></c><c r="D120" s="10"><v>236539635</v></c><c r="E120" s="11"><v>125418.68239660657</v></c><c r="F120" s="10"><v>0</v></c><c r="G120" s="30"><v>15536375</v></c><c r="H120" s="1" t="s"><v>546</v></c></row><row r="121" spans="1:8" x14ac:dyDescent="0.25"><c r="A121" s="1"><v>62396</v></c><c r="B121" s="1" t="s"><v>547</v></c><c r="C121" s="30"><v>1886</v></c><c r="D121" s="10"><v>257874428</v></c><c r="E121" s="11"><v>136730.87380699895</v></c><c r="F121" s="10"><v>0</v></c><c r="G121" s="30"><v>27667028</v></c><c r="H121" s="1" t="s"><v>549</v></c></row><row r="122" spans="1:8" x14ac:dyDescent="0.25"><c r="A122" s="1"><v>62398</v></c><c r="B122" s="1" t="s"><v>550</v></c><c r="C122" s="30"><v>1886</v></c><c r="D122" s="10"><v>248587433</v></c><c r="E122" s="11"><v>131806.69830328738</v></c><c r="F122" s="10"><v>0</v></c><c r="G122" s="30"><v>27667028</v></c><c r="H122" s="1" t="s"><v>552</v></c></row><row r="123" spans="1:8" x14ac:dyDescent="0.25"><c r="A123" s="1"><v>62400</v></c><c r="B123" s="1" t="s"><v>553</v></c><c r="C123" s="30"><v>1886</v></c><c r="D123" s="10"><v>9286995</v></c><c r="E123" s="11"><v>4924.175503711559</v></c><c r="F123" s="10"><v>0</v></c><c r="G123" s="30"><v>2094506</v></c><c r="H123" s="1" t="s"><v>555</v></c></row><row r="124" spans="1:8" x14ac:dyDescent="0.25"><c r="A124" s="1"><v>62402</v></c><c r="B124" s="1" t="s"><v>556</v></c><c r="C124" s="30"><v>1886</v></c><c r="D124" s="10"><v>2374025777</v></c><c r="E124" s="11"><v>1258762.3419936374</v></c><c r="F124" s="10"><v>0</v></c><c r="G124" s="30"><v>107720000</v></c><c r="H124" s="1" t="s"><v>558</v></c></row><row r="125" spans="1:8" x14ac:dyDescent="0.25"><c r="A125" s="1"><v>62404</v></c><c r="B125" s="1" t="s"><v>559</v></c><c r="C125" s="30"><v>1886</v></c><c r="D125" s="10"><v>2164422632</v></c><c r="E125" s="11"><v>1147625.9978791091</v></c><c r="F125" s="10"><v>0</v></c><c r="G125" s="30"><v>94920000</v></c><c r="H125" s="1" t="s"><v>561</v></c></row><row r="126" spans="1:8" x14ac:dyDescent="0.25"><c r="A126" s="1"><v>62406</v></c><c r="B126" s="1" t="s"><v>562</v></c><c r="C126" s="30"><v>1886</v></c><c r="D126" s="10"><v>209603145</v></c><c r="E126" s="11"><v>111136.3441145281</v></c><c r="F126" s="10"><v>0</v></c><c r="G126" s="30"><v>15760493</v></c><c r="H126" s="1" t="s"><v>564</v></c></row><row r="127" spans="1:8" x14ac:dyDescent="0.25"><c r="A127" s="1"><v>62408</v></c><c r="B127" s="1" t="s"><v>565</v></c><c r="C127" s="30"><v>1886</v></c><c r="D127" s="10"><v>13553354255</v></c><c r="E127" s="11"><v>7186295.9994697776</v></c><c r="F127" s="10"><v>0</v></c><c r="G127" s="30"><v>366588000</v></c><c r="H127" s="1" t="s"><v>646</v></c></row><row r="128" spans="1:8" x14ac:dyDescent="0.25"><c r="A128" s="1"><v>62410</v></c><c r="B128" s="1" t="s"><v>567</v></c><c r="C128" s="30"><v>1886</v></c><c r="D128" s="10"><v>12379435214</v></c><c r="E128" s="11"><v>6563857.4835630963</v></c><c r="F128" s="10"><v>0</v></c><c r="G128" s="30"><v>349435000</v></c><c r="H128" s="1" t="s"><v>569</v></c></row><row r="129" spans="1:8" x14ac:dyDescent="0.25"><c r="A129" s="1"><v>62412</v></c><c r="B129" s="1" t="s"><v>570</v></c><c r="C129" s="30"><v>1886</v></c><c r="D129" s="10"><v>1173919041</v></c><c r="E129" s="11"><v>622438.51590668084</v></c><c r="F129" s="10"><v>0</v></c><c r="G129" s="30"><v>25973007</v></c><c r="H129" s="1" t="s"><v>572</v></c></row><row r="130" spans="1:8" x14ac:dyDescent="0.25"><c r="A130" s="1"><v>62311</v></c><c r="B130" s="1" t="s"><v>308</v></c><c r="C130" s="30"><v>1342</v></c><c r="D130" s="10"><v>210853183440</v></c><c r="E130" s="11"><v>157118616.57228017</v></c><c r="F130" s="10"><v>0</v></c><c r="G130" s="30"><v>29842396358</v></c><c r="H130" s="1" t="s"><v>310</v></c></row><row r="131" spans="1:8" x14ac:dyDescent="0.25"><c r="A131" s="1"><v>62316</v></c><c r="B131" s="1" t="s"><v>311</v></c><c r="C131" s="30"><v>1342</v></c><c r="D131" s="10"><v>216002774746</v></c><c r="E131" s="11"><v>160955867.9180328</v></c><c r="F131" s="10"><v>5</v></c><c r="G131" s="30"><v>30522119569</v></c><c r="H131" s="1" t="s"><v>313</v></c></row><row r="132" spans="1:8" x14ac:dyDescent="0.25"><c r="A132" s="1"><v>62414</v></c><c r="B132" s="1" t="s"><v>573</v></c><c r="C132" s="30"><v>1342</v></c><c r="D132" s="10"><v>5149591306</v></c><c r="E132" s="11"><v>3837251.345752608</v></c><c r="F132" s="10"><v>-300636144</v></c><c r="G132" s="30"><v>951939000</v></c><c r="H132" s="1" t="s"><v>575</v></c></row><row r="133" spans="1:8" x14ac:dyDescent="0.25"><c r="A133" s="1"><v>62416</v></c><c r="B133" s="1" t="s"><v>576</v></c><c r="C133" s="30"><v>1342</v></c><c r="D133" s="10"><v>7501539800</v></c><c r="E133" s="11"><v>5589821.0134128164</v></c><c r="F133" s="10"><v>0</v></c><c r="G133" s="30"><v>1044789000</v></c><c r="H133" s="1" t="s"><v>578</v></c></row><row r="134" spans="1:8" x14ac:dyDescent="0.25"><c r="A134" s="1"><v>62418</v></c><c r="B134" s="1" t="s"><v>579</v></c><c r="C134" s="30"><v>1342</v></c><c r="D134" s="10"><v>4736343982</v></c><c r="E134" s="11"><v>3529317.4232488824</v></c><c r="F134" s="10"><v>-93695767</v></c><c r="G134" s="30"><v>2448837136</v></c><c r="H134" s="1" t="s"><v>581</v></c></row><row r="135" spans="1:8" x14ac:dyDescent="0.25"><c r="A135" s="1"><v>62420</v></c><c r="B135" s="1" t="s"><v>582</v></c><c r="C135" s="30"><v>1342</v></c><c r="D135" s="10"><v>-4941334877</v></c><c r="E135" s="11"><v>-3682067.7175856931</v></c><c r="F135" s="10"><v>-384072000</v></c><c r="G135" s="30"><v>231104120</v></c><c r="H135" s="1" t="s"><v>584</v></c></row><row r="136" spans="1:8" x14ac:dyDescent="0.25"><c r="A136" s="1"><v>62422</v></c><c r="B136" s="1" t="s"><v>585</v></c><c r="C136" s="30"><v>1342</v></c><c r="D136" s="10"><v>-2146957599</v></c><c r="E136" s="11"><v>-1599819.3733233979</v></c><c r="F136" s="10"><v>-1770218438</v></c><c r="G136" s="30"><v>375855000</v></c><c r="H136" s="1" t="s"><v>587</v></c></row><row r="137" spans="1:8" x14ac:dyDescent="0.25"><c r="A137" s="1"><v>62426</v></c><c r="B137" s="1" t="s"><v>588</v></c><c r="C137" s="30"><v>1500</v></c><c r="D137" s="10"><v>4198345075</v></c><c r="E137" s="11"><v>2798896.7166666668</v></c><c r="F137" s="10"><v>-3729064000</v></c><c r="G137" s="30"><v>1742024102</v></c><c r="H137" s="1" t="s"><v>590</v></c></row><row r="138" spans="1:8" x14ac:dyDescent="0.25"><c r="A138" s="1"><v>62428</v></c><c r="B138" s="1" t="s"><v>591</v></c><c r="C138" s="30"><v>1500</v></c><c r="D138" s="10"><v>417779447178</v></c><c r="E138" s="11"><v>278519631.45200002</v></c><c r="F138" s="10"><v>0</v></c><c r="G138" s="30"><v>40695648000</v></c><c r="H138" s="1" t="s"><v>593</v></c></row><row r="139" spans="1:8" x14ac:dyDescent="0.25"><c r="A139" s="1"><v>62430</v></c><c r="B139" s="1" t="s"><v>594</v></c><c r="C139" s="30"><v>1500</v></c><c r="D139" s="10"><v>15654924018</v></c><c r="E139" s="11"><v>10436616.012</v></c><c r="F139" s="10"><v>-3445594000</v></c><c r="G139" s="30"><v>2187316795</v></c><c r="H139" s="1" t="s"><v>596</v></c></row><row r="140" spans="1:8" x14ac:dyDescent="0.25"><c r="A140" s="1"><v>62432</v></c><c r="B140" s="1" t="s"><v>597</v></c><c r="C140" s="30"><v>1500</v></c><c r="D140" s="10"><v>471426845591</v></c><c r="E140" s="11"><v>314284563.72733331</v></c><c r="F140" s="10"><v>-1577559427</v></c><c r="G140" s="30"><v>49440230422</v></c><c r="H140" s="1" t="s"><v>397</v></c></row><row r="141" spans="1:8" x14ac:dyDescent="0.25"><c r="A141" s="1"><v>62434</v></c><c r="B141" s="1" t="s"><v>599</v></c><c r="C141" s="30"><v>1500</v></c><c r="D141" s="1"><v>175085529767</v></c><c r="E141" s="35"><v>116723686.51133333</v></c><c r="F141" s="10"><v>-15805670000</v></c><c r="G141" s="30"><v>24050253660</v></c><c r="H141" s="1" t="s"><v>601</v></c></row><row r="142" spans="1:8" x14ac:dyDescent="0.25"><c r="A142" s="1"><v>62436</v></c><c r="B142" s="1" t="s"><v>602</v></c><c r="C142" s="30"><v>1500</v></c><c r="D142" s="1"><v>207844678507</v></c><c r="E142" s="35"><v>138563119.00466666</v></c><c r="F142" s="10"><v>0</v></c><c r="G142" s="30"><v>26652748000</v></c><c r="H142" s="1" t="s"><v>604</v></c></row><row r="143" spans="1:8" x14ac:dyDescent="0.25"><c r="A143" s="1"><v>62438</v></c><c r="B143" s="1" t="s"><v>605</v></c><c r="C143" s="30"><v>1500</v></c><c r="D143" s="1"><v>401593048263</v></c><c r="E143" s="35"><v>267728698.84200001</v></c><c r="F143" s="10"><v>0</v></c><c r="G143" s="30"><v>44424712000</v></c><c r="H143" s="1" t="s"><v>607</v></c></row><row r="144" spans="1:8" x14ac:dyDescent="0.25"><c r="D144" s="1"/></row><row r="145" spans="3:7" x14ac:dyDescent="0.25"><c r="C145" s="1"/><c r="D145" s="1"/><c r="E145" s="1"/><c r="F145" s="1"/><c r="G145" s="1"/></row><row r="146" spans="3:7" x14ac:dyDescent="0.25"><c r="C146" s="1"/><c r="D146" s="1"/><c r="E146" s="1"/><c r="F146" s="1"/><c r="G146" s="1"/></row><row r="147" spans="3:7" x14ac:dyDescent="0.25"><c r="C147" s="1"/><c r="D147" s="1"/><c r="E147" s="1"/><c r="F147" s="1"/><c r="G147" s="1"/></row><row r="148" spans="3:7" x14ac:dyDescent="0.25"><c r="C148" s="1"/><c r="D148" s="1"/><c r="E148" s="1"/><c r="F148" s="1"/><c r="G148" s="1"/></row><row r="149" spans="3:7" x14ac:dyDescent="0.25"><c r="C149" s="1"/><c r="D149" s="1"/><c r="E149" s="1"/><c r="F149" s="1"/><c r="G149" s="1"/></row><row r="150" spans="3:7" x14ac:dyDescent="0.25"><c r="C150" s="1"/><c r="D150" s="1"/><c r="E150" s="1"/><c r="F150" s="1"/><c r="G150" s="1"/></row><row r="151" spans="3:7" x14ac:dyDescent="0.25"><c r="C151" s="1"/><c r="D151" s="1"/><c r="E151" s="1"/><c r="F151" s="1"/><c r="G151" s="1"/></row><row r="152" spans="3:7" x14ac:dyDescent="0.25"><c r="C152" s="1"/><c r="D152" s="1"/><c r="E152" s="1"/><c r="F152" s="1"/><c r="G152" s="1"/></row><row r="153" spans="3:7" x14ac:dyDescent="0.25"><c r="C153" s="1"/><c r="D153" s="1"/><c r="E153" s="1"/><c r="F153" s="1"/><c r="G153" s="1"/></row><row r="154" spans="3:7" x14ac:dyDescent="0.25"><c r="C154" s="1"/><c r="D154" s="1"/><c r="E154" s="1"/><c r="F154" s="1"/><c r="G154" s="1"/></row><row r="155" spans="3:7" x14ac:dyDescent="0.25"><c r="C155" s="1"/><c r="D155" s="1"/><c r="E155" s="1"/><c r="F155" s="1"/><c r="G155" s="1"/></row><row r="156" spans="3:7" x14ac:dyDescent="0.25"><c r="C156" s="1"/><c r="D156" s="1"/><c r="E156" s="1"/><c r="F156" s="1"/><c r="G156" s="1"/></row><row r="157" spans="3:7" x14ac:dyDescent="0.25"><c r="C157" s="1"/><c r="D157" s="1"/><c r="E157" s="1"/><c r="F157" s="1"/><c r="G157" s="1"/></row><row r="158" spans="3:7" x14ac:dyDescent="0.25"><c r="C158" s="1"/><c r="D158" s="1"/><c r="E158" s="1"/><c r="F158" s="1"/><c r="G158" s="1"/></row><row r="159" spans="3:7" x14ac:dyDescent="0.25"><c r="C159" s="1"/><c r="D159" s="1"/><c r="E159" s="1"/><c r="F159" s="1"/><c r="G159" s="1"/></row><row r="160" spans="3:7" x14ac:dyDescent="0.25"><c r="C160" s="1"/><c r="D160" s="1"/><c r="E160" s="1"/><c r="F160" s="1"/><c r="G160" s="1"/></row><row r="161" spans="3:7" x14ac:dyDescent="0.25"><c r="C161" s="1"/><c r="D161" s="1"/><c r="E161" s="1"/><c r="F161" s="1"/><c r="G161" s="1"/></row><row r="162" spans="3:7" x14ac:dyDescent="0.25"><c r="C162" s="1"/><c r="D162" s="1"/><c r="E162" s="1"/><c r="F162" s="1"/><c r="G162" s="1"/></row><row r="163" spans="3:7" x14ac:dyDescent="0.25"><c r="C163" s="1"/><c r="D163" s="1"/><c r="E163" s="1"/><c r="F163" s="1"/><c r="G163" s="1"/></row><row r="164" spans="3:7" x14ac:dyDescent="0.25"><c r="C164" s="1"/><c r="D164" s="1"/><c r="E164" s="1"/><c r="F164" s="1"/><c r="G164" s="1"/></row><row r="165" spans="3:7" x14ac:dyDescent="0.25"><c r="C165" s="1"/><c r="D165" s="1"/><c r="E165" s="1"/><c r="F165" s="1"/><c r="G165" s="1"/></row><row r="166" spans="3:7" x14ac:dyDescent="0.25"><c r="C166" s="1"/><c r="D166" s="1"/><c r="E166" s="1"/><c r="F166" s="1"/><c r="G166" s="1"/></row><row r="167" spans="3:7" x14ac:dyDescent="0.25"><c r="C167" s="1"/><c r="D167" s="1"/><c r="E167" s="1"/><c r="F167" s="1"/><c r="G167" s="1"/></row><row r="168" spans="3:7" x14ac:dyDescent="0.25"><c r="C168" s="1"/><c r="D168" s="1"/><c r="E168" s="1"/><c r="F168" s="1"/><c r="G168" s="1"/></row><row r="169" spans="3:7" x14ac:dyDescent="0.25"><c r="C169" s="1"/><c r="D169" s="1"/><c r="E169" s="1"/><c r="F169" s="1"/><c r="G169" s="1"/></row><row r="170" spans="3:7" x14ac:dyDescent="0.25"><c r="C170" s="1"/><c r="D170" s="1"/><c r="E170" s="1"/><c r="F170" s="1"/><c r="G170" s="1"/></row><row r="171" spans="3:7" x14ac:dyDescent="0.25"><c r="C171" s="1"/><c r="D171" s="1"/><c r="E171" s="1"/><c r="F171" s="1"/><c r="G171" s="1"/></row><row r="172" spans="3:7" x14ac:dyDescent="0.25"><c r="C172" s="1"/><c r="D172" s="1"/><c r="E172" s="1"/><c r="F172" s="1"/><c r="G172" s="1"/></row><row r="173" spans="3:7" x14ac:dyDescent="0.25"><c r="C173" s="1"/><c r="D173" s="1"/><c r="E173" s="1"/><c r="F173" s="1"/><c r="G173" s="1"/></row><row r="174" spans="3:7" x14ac:dyDescent="0.25"><c r="C174" s="1"/><c r="D174" s="1"/><c r="E174" s="1"/><c r="F174" s="1"/><c r="G174" s="1"/></row><row r="175" spans="3:7" x14ac:dyDescent="0.25"><c r="C175" s="1"/><c r="D175" s="1"/><c r="E175" s="1"/><c r="F175" s="1"/><c r="G175" s="1"/></row><row r="176" spans="3:7" x14ac:dyDescent="0.25"><c r="C176" s="1"/><c r="D176" s="1"/><c r="E176" s="1"/><c r="F176" s="1"/><c r="G176" s="1"/></row><row r="177" spans="3:7" x14ac:dyDescent="0.25"><c r="C177" s="1"/><c r="D177" s="1"/><c r="E177" s="1"/><c r="F177" s="1"/><c r="G177" s="1"/></row><row r="178" spans="3:7" x14ac:dyDescent="0.25"><c r="C178" s="1"/><c r="D178" s="1"/><c r="E178" s="1"/><c r="F178" s="1"/><c r="G178" s="1"/></row><row r="179" spans="3:7" x14ac:dyDescent="0.25"><c r="C179" s="1"/><c r="D179" s="1"/><c r="E179" s="1"/><c r="F179" s="1"/><c r="G179" s="1"/></row><row r="180" spans="3:7" x14ac:dyDescent="0.25"><c r="C180" s="1"/><c r="D180" s="1"/><c r="E180" s="1"/><c r="F180" s="1"/><c r="G180" s="1"/></row><row r="181" spans="3:7" x14ac:dyDescent="0.25"><c r="C181" s="1"/><c r="D181" s="1"/><c r="E181" s="1"/><c r="F181" s="1"/><c r="G181" s="1"/></row><row r="182" spans="3:7" x14ac:dyDescent="0.25"><c r="C182" s="1"/><c r="D182" s="1"/><c r="E182" s="1"/><c r="F182" s="1"/><c r="G182" s="1"/></row><row r="183" spans="3:7" x14ac:dyDescent="0.25"><c r="C183" s="1"/><c r="D183" s="1"/><c r="E183" s="1"/><c r="F183" s="1"/><c r="G183" s="1"/></row><row r="184" spans="3:7" x14ac:dyDescent="0.25"><c r="C184" s="1"/><c r="D184" s="1"/><c r="E184" s="1"/><c r="F184" s="1"/><c r="G184" s="1"/></row><row r="185" spans="3:7" x14ac:dyDescent="0.25"><c r="C185" s="1"/><c r="D185" s="1"/><c r="E185" s="1"/><c r="F185" s="1"/><c r="G185" s="1"/></row><row r="186" spans="3:7" x14ac:dyDescent="0.25"><c r="C186" s="1"/><c r="D186" s="1"/><c r="E186" s="1"/><c r="F186" s="1"/><c r="G186" s="1"/></row><row r="187" spans="3:7" x14ac:dyDescent="0.25"><c r="C187" s="1"/><c r="D187" s="1"/><c r="E187" s="1"/><c r="F187" s="1"/><c r="G187" s="1"/></row><row r="188" spans="3:7" x14ac:dyDescent="0.25"><c r="C188" s="1"/><c r="D188" s="1"/><c r="E188" s="1"/><c r="F188" s="1"/><c r="G188" s="1"/></row><row r="189" spans="3:7" x14ac:dyDescent="0.25"><c r="C189" s="1"/><c r="D189" s="1"/><c r="E189" s="1"/><c r="F189" s="1"/><c r="G189" s="1"/></row><row r="190" spans="3:7" x14ac:dyDescent="0.25"><c r="C190" s="1"/><c r="D190" s="1"/><c r="E190" s="1"/><c r="F190" s="1"/><c r="G190" s="1"/></row><row r="191" spans="3:7" x14ac:dyDescent="0.25"><c r="C191" s="1"/><c r="D191" s="1"/><c r="E191" s="1"/><c r="F191" s="1"/><c r="G191" s="1"/></row><row r="192" spans="3:7" x14ac:dyDescent="0.25"><c r="C192" s="1"/><c r="D192" s="1"/><c r="E192" s="1"/><c r="F192" s="1"/><c r="G192" s="1"/></row><row r="193" spans="3:7" x14ac:dyDescent="0.25"><c r="C193" s="1"/><c r="D193" s="1"/><c r="E193" s="1"/><c r="F193" s="1"/><c r="G193" s="1"/></row><row r="194" spans="3:7" x14ac:dyDescent="0.25"><c r="C194" s="1"/><c r="D194" s="1"/><c r="E194" s="1"/><c r="F194" s="1"/><c r="G194" s="1"/></row><row r="195" spans="3:7" x14ac:dyDescent="0.25"><c r="C195" s="1"/><c r="D195" s="1"/><c r="E195" s="1"/><c r="F195" s="1"/><c r="G195" s="1"/></row><row r="196" spans="3:7" x14ac:dyDescent="0.25"><c r="C196" s="1"/><c r="D196" s="1"/><c r="E196" s="1"/><c r="F196" s="1"/><c r="G196" s="1"/></row><row r="197" spans="3:7" x14ac:dyDescent="0.25"><c r="C197" s="1"/><c r="D197" s="1"/><c r="E197" s="1"/><c r="F197" s="1"/><c r="G197" s="1"/></row><row r="198" spans="3:7" x14ac:dyDescent="0.25"><c r="C198" s="1"/><c r="D198" s="1"/><c r="E198" s="1"/><c r="F198" s="1"/><c r="G198" s="1"/></row><row r="199" spans="3:7" x14ac:dyDescent="0.25"><c r="C199" s="1"/><c r="D199" s="1"/><c r="E199" s="1"/><c r="F199" s="1"/><c r="G199" s="1"/></row><row r="200" spans="3:7" x14ac:dyDescent="0.25"><c r="C200" s="1"/><c r="D200" s="1"/><c r="E200" s="1"/><c r="F200" s="1"/><c r="G200" s="1"/></row><row r="201" spans="3:7" x14ac:dyDescent="0.25"><c r="C201" s="1"/><c r="D201" s="1"/><c r="E201" s="1"/><c r="F201" s="1"/><c r="G201" s="1"/></row><row r="202" spans="3:7" x14ac:dyDescent="0.25"><c r="C202" s="1"/><c r="D202" s="1"/><c r="E202" s="1"/><c r="F202" s="1"/><c r="G202" s="1"/></row><row r="203" spans="3:7" x14ac:dyDescent="0.25"><c r="C203" s="1"/><c r="D203" s="1"/><c r="E203" s="1"/><c r="F203" s="1"/><c r="G203" s="1"/></row><row r="204" spans="3:7" x14ac:dyDescent="0.25"><c r="C204" s="1"/><c r="D204" s="1"/><c r="E204" s="1"/><c r="F204" s="1"/><c r="G204" s="1"/></row><row r="205" spans="3:7" x14ac:dyDescent="0.25"><c r="C205" s="1"/><c r="D205" s="1"/><c r="E205" s="1"/><c r="F205" s="1"/><c r="G205" s="1"/></row><row r="206" spans="3:7" x14ac:dyDescent="0.25"><c r="C206" s="1"/><c r="D206" s="1"/><c r="E206" s="1"/><c r="F206" s="1"/><c r="G206" s="1"/></row><row r="207" spans="3:7" x14ac:dyDescent="0.25"><c r="C207" s="1"/><c r="D207" s="1"/><c r="E207" s="1"/><c r="F207" s="1"/><c r="G207" s="1"/></row><row r="208" spans="3:7" x14ac:dyDescent="0.25"><c r="C208" s="1"/><c r="D208" s="1"/><c r="E208" s="1"/><c r="F208" s="1"/><c r="G208" s="1"/></row><row r="209" spans="3:7" x14ac:dyDescent="0.25"><c r="C209" s="1"/><c r="D209" s="1"/><c r="E209" s="1"/><c r="F209" s="1"/><c r="G209" s="1"/></row><row r="210" spans="3:7" x14ac:dyDescent="0.25"><c r="C210" s="1"/><c r="D210" s="1"/><c r="E210" s="1"/><c r="F210" s="1"/><c r="G210" s="1"/></row><row r="211" spans="3:7" x14ac:dyDescent="0.25"><c r="C211" s="1"/><c r="D211" s="1"/><c r="E211" s="1"/><c r="F211" s="1"/><c r="G211" s="1"/></row><row r="212" spans="3:7" x14ac:dyDescent="0.25"><c r="C212" s="1"/><c r="D212" s="1"/><c r="E212" s="1"/><c r="F212" s="1"/><c r="G212" s="1"/></row><row r="213" spans="3:7" x14ac:dyDescent="0.25"><c r="C213" s="1"/><c r="D213" s="1"/><c r="E213" s="1"/><c r="F213" s="1"/><c r="G213" s="1"/></row><row r="214" spans="3:7" x14ac:dyDescent="0.25"><c r="C214" s="1"/><c r="D214" s="1"/><c r="E214" s="1"/><c r="F214" s="1"/><c r="G214" s="1"/></row><row r="215" spans="3:7" x14ac:dyDescent="0.25"><c r="C215" s="1"/><c r="D215" s="1"/><c r="E215" s="1"/><c r="F215" s="1"/><c r="G215" s="1"/></row><row r="216" spans="3:7" x14ac:dyDescent="0.25"><c r="C216" s="1"/><c r="D216" s="1"/><c r="E216" s="1"/><c r="F216" s="1"/><c r="G216" s="1"/></row><row r="217" spans="3:7" x14ac:dyDescent="0.25"><c r="C217" s="1"/><c r="D217" s="1"/><c r="E217" s="1"/><c r="F217" s="1"/><c r="G217" s="1"/></row><row r="218" spans="3:7" x14ac:dyDescent="0.25"><c r="C218" s="1"/><c r="D218" s="1"/><c r="E218" s="1"/><c r="F218" s="1"/><c r="G218" s="1"/></row><row r="219" spans="3:7" x14ac:dyDescent="0.25"><c r="C219" s="1"/><c r="D219" s="1"/><c r="E219" s="1"/><c r="F219" s="1"/><c r="G219" s="1"/></row><row r="220" spans="3:7" x14ac:dyDescent="0.25"><c r="C220" s="1"/><c r="D220" s="1"/><c r="E220" s="1"/><c r="F220" s="1"/><c r="G220" s="1"/></row><row r="221" spans="3:7" x14ac:dyDescent="0.25"><c r="C221" s="1"/><c r="D221" s="1"/><c r="E221" s="1"/><c r="F221" s="1"/><c r="G221" s="1"/></row><row r="222" spans="3:7" x14ac:dyDescent="0.25"><c r="C222" s="1"/><c r="D222" s="1"/><c r="E222" s="1"/><c r="F222" s="1"/><c r="G222" s="1"/></row><row r="223" spans="3:7" x14ac:dyDescent="0.25"><c r="C223" s="1"/><c r="D223" s="1"/><c r="E223" s="1"/><c r="F223" s="1"/><c r="G223" s="1"/></row><row r="224" spans="3:7" x14ac:dyDescent="0.25"><c r="C224" s="1"/><c r="D224" s="1"/><c r="E224" s="1"/><c r="F224" s="1"/><c r="G224" s="1"/></row><row r="225" spans="3:7" x14ac:dyDescent="0.25"><c r="C225" s="1"/><c r="D225" s="1"/><c r="E225" s="1"/><c r="F225" s="1"/><c r="G225" s="1"/></row><row r="226" spans="3:7" x14ac:dyDescent="0.25"><c r="C226" s="1"/><c r="D226" s="1"/><c r="E226" s="1"/><c r="F226" s="1"/><c r="G226" s="1"/></row><row r="227" spans="3:7" x14ac:dyDescent="0.25"><c r="C227" s="1"/><c r="D227" s="1"/><c r="E227" s="1"/><c r="F227" s="1"/><c r="G227" s="1"/></row><row r="228" spans="3:7" x14ac:dyDescent="0.25"><c r="C228" s="1"/><c r="D228" s="1"/><c r="E228" s="1"/><c r="F228" s="1"/><c r="G228" s="1"/></row><row r="229" spans="3:7" x14ac:dyDescent="0.25"><c r="C229" s="1"/><c r="D229" s="1"/><c r="E229" s="1"/><c r="F229" s="1"/><c r="G229" s="1"/></row><row r="230" spans="3:7" x14ac:dyDescent="0.25"><c r="C230" s="1"/><c r="D230" s="1"/><c r="E230" s="1"/><c r="F230" s="1"/><c r="G230" s="1"/></row><row r="231" spans="3:7" x14ac:dyDescent="0.25"><c r="C231" s="1"/><c r="D231" s="1"/><c r="E231" s="1"/><c r="F231" s="1"/><c r="G231" s="1"/></row><row r="232" spans="3:7" x14ac:dyDescent="0.25"><c r="C232" s="1"/><c r="D232" s="1"/><c r="E232" s="1"/><c r="F232" s="1"/><c r="G232" s="1"/></row><row r="233" spans="3:7" x14ac:dyDescent="0.25"><c r="C233" s="1"/><c r="D233" s="1"/><c r="E233" s="1"/><c r="F233" s="1"/><c r="G233" s="1"/></row><row r="234" spans="3:7" x14ac:dyDescent="0.25"><c r="C234" s="1"/><c r="D234" s="1"/><c r="E234" s="1"/><c r="F234" s="1"/><c r="G234" s="1"/></row><row r="235" spans="3:7" x14ac:dyDescent="0.25"><c r="C235" s="1"/><c r="D235" s="1"/><c r="E235" s="1"/><c r="F235" s="1"/><c r="G235" s="1"/></row><row r="236" spans="3:7" x14ac:dyDescent="0.25"><c r="C236" s="1"/><c r="D236" s="1"/><c r="E236" s="1"/><c r="F236" s="1"/><c r="G236" s="1"/></row><row r="237" spans="3:7" x14ac:dyDescent="0.25"><c r="C237" s="1"/><c r="D237" s="1"/><c r="E237" s="1"/><c r="F237" s="1"/><c r="G237" s="1"/></row><row r="238" spans="3:7" x14ac:dyDescent="0.25"><c r="C238" s="1"/><c r="D238" s="1"/><c r="E238" s="1"/><c r="F238" s="1"/><c r="G238" s="1"/></row><row r="239" spans="3:7" x14ac:dyDescent="0.25"><c r="C239" s="1"/><c r="D239" s="1"/><c r="E239" s="1"/><c r="F239" s="1"/><c r="G239" s="1"/></row><row r="240" spans="3:7" x14ac:dyDescent="0.25"><c r="C240" s="1"/><c r="D240" s="1"/><c r="E240" s="1"/><c r="F240" s="1"/><c r="G240" s="1"/></row><row r="241" spans="3:7" x14ac:dyDescent="0.25"><c r="C241" s="1"/><c r="D241" s="1"/><c r="E241" s="1"/><c r="F241" s="1"/><c r="G241" s="1"/></row><row r="242" spans="3:7" x14ac:dyDescent="0.25"><c r="C242" s="1"/><c r="D242" s="1"/><c r="E242" s="1"/><c r="F242" s="1"/><c r="G242" s="1"/></row><row r="243" spans="3:7" x14ac:dyDescent="0.25"><c r="C243" s="1"/><c r="D243" s="1"/><c r="E243" s="1"/><c r="F243" s="1"/><c r="G243" s="1"/></row><row r="244" spans="3:7" x14ac:dyDescent="0.25"><c r="C244" s="1"/><c r="D244" s="1"/><c r="E244" s="1"/><c r="F244" s="1"/><c r="G244" s="1"/></row><row r="245" spans="3:7" x14ac:dyDescent="0.25"><c r="C245" s="1"/><c r="D245" s="1"/><c r="E245" s="1"/><c r="F245" s="1"/><c r="G245" s="1"/></row><row r="246" spans="3:7" x14ac:dyDescent="0.25"><c r="C246" s="1"/><c r="D246" s="1"/><c r="E246" s="1"/><c r="F246" s="1"/><c r="G246" s="1"/></row><row r="247" spans="3:7" x14ac:dyDescent="0.25"><c r="C247" s="1"/><c r="D247" s="1"/><c r="E247" s="1"/><c r="F247" s="1"/><c r="G247" s="1"/></row><row r="248" spans="3:7" x14ac:dyDescent="0.25"><c r="C248" s="1"/><c r="D248" s="1"/><c r="E248" s="1"/><c r="F248" s="1"/><c r="G248" s="1"/></row><row r="249" spans="3:7" x14ac:dyDescent="0.25"><c r="C249" s="1"/><c r="D249" s="1"/><c r="E249" s="1"/><c r="F249" s="1"/><c r="G249" s="1"/></row><row r="250" spans="3:7" x14ac:dyDescent="0.25"><c r="C250" s="1"/><c r="D250" s="1"/><c r="E250" s="1"/><c r="F250" s="1"/><c r="G250" s="1"/></row><row r="251" spans="3:7" x14ac:dyDescent="0.25"><c r="C251" s="1"/><c r="D251" s="1"/><c r="E251" s="1"/><c r="F251" s="1"/><c r="G251" s="1"/></row><row r="252" spans="3:7" x14ac:dyDescent="0.25"><c r="C252" s="1"/><c r="D252" s="1"/><c r="E252" s="1"/><c r="F252" s="1"/><c r="G252" s="1"/></row><row r="253" spans="3:7" x14ac:dyDescent="0.25"><c r="C253" s="1"/><c r="D253" s="1"/><c r="E253" s="1"/><c r="F253" s="1"/><c r="G253" s="1"/></row><row r="254" spans="3:7" x14ac:dyDescent="0.25"><c r="C254" s="1"/><c r="D254" s="1"/><c r="E254" s="1"/><c r="F254" s="1"/><c r="G254" s="1"/></row><row r="255" spans="3:7" x14ac:dyDescent="0.25"><c r="C255" s="1"/><c r="D255" s="1"/><c r="E255" s="1"/><c r="F255" s="1"/><c r="G255" s="1"/></row><row r="256" spans="3:7" x14ac:dyDescent="0.25"><c r="C256" s="1"/><c r="D256" s="1"/><c r="E256" s="1"/><c r="F256" s="1"/><c r="G256" s="1"/></row><row r="257" spans="3:7" x14ac:dyDescent="0.25"><c r="C257" s="1"/><c r="D257" s="1"/><c r="E257" s="1"/><c r="F257" s="1"/><c r="G257" s="1"/></row><row r="258" spans="3:7" x14ac:dyDescent="0.25"><c r="C258" s="1"/><c r="D258" s="1"/><c r="E258" s="1"/><c r="F258" s="1"/><c r="G258" s="1"/></row><row r="259" spans="3:7" x14ac:dyDescent="0.25"><c r="C259" s="1"/><c r="D259" s="1"/><c r="E259" s="1"/><c r="F259" s="1"/><c r="G259" s="1"/></row><row r="260" spans="3:7" x14ac:dyDescent="0.25"><c r="C260" s="1"/><c r="D260" s="1"/><c r="E260" s="1"/><c r="F260" s="1"/><c r="G260" s="1"/></row><row r="261" spans="3:7" x14ac:dyDescent="0.25"><c r="C261" s="1"/><c r="D261" s="1"/><c r="E261" s="1"/><c r="F261" s="1"/><c r="G261" s="1"/></row><row r="262" spans="3:7" x14ac:dyDescent="0.25"><c r="C262" s="1"/><c r="D262" s="1"/><c r="E262" s="1"/><c r="F262" s="1"/><c r="G262" s="1"/></row><row r="263" spans="3:7" x14ac:dyDescent="0.25"><c r="C263" s="1"/><c r="D263" s="1"/><c r="E263" s="1"/><c r="F263" s="1"/><c r="G263" s="1"/></row><row r="264" spans="3:7" x14ac:dyDescent="0.25"><c r="C264" s="1"/><c r="D264" s="1"/><c r="E264" s="1"/><c r="F264" s="1"/><c r="G264" s="1"/></row><row r="265" spans="3:7" x14ac:dyDescent="0.25"><c r="C265" s="1"/><c r="D265" s="1"/><c r="E265" s="1"/><c r="F265" s="1"/><c r="G265" s="1"/></row><row r="266" spans="3:7" x14ac:dyDescent="0.25"><c r="C266" s="1"/><c r="D266" s="1"/><c r="E266" s="1"/><c r="F266" s="1"/><c r="G266" s="1"/></row><row r="267" spans="3:7" x14ac:dyDescent="0.25"><c r="C267" s="1"/><c r="D267" s="1"/><c r="E267" s="1"/><c r="F267" s="1"/><c r="G267" s="1"/></row><row r="268" spans="3:7" x14ac:dyDescent="0.25"><c r="C268" s="1"/><c r="D268" s="1"/><c r="E268" s="1"/><c r="F268" s="1"/><c r="G268" s="1"/></row><row r="269" spans="3:7" x14ac:dyDescent="0.25"><c r="C269" s="1"/><c r="D269" s="1"/><c r="E269" s="1"/><c r="F269" s="1"/><c r="G269" s="1"/></row><row r="270" spans="3:7" x14ac:dyDescent="0.25"><c r="C270" s="1"/><c r="D270" s="1"/><c r="E270" s="1"/><c r="F270" s="1"/><c r="G270" s="1"/></row><row r="271" spans="3:7" x14ac:dyDescent="0.25"><c r="C271" s="1"/><c r="D271" s="1"/><c r="E271" s="1"/><c r="F271" s="1"/><c r="G271" s="1"/></row><row r="272" spans="3:7" x14ac:dyDescent="0.25"><c r="C272" s="1"/><c r="D272" s="1"/><c r="E272" s="1"/><c r="F272" s="1"/><c r="G272" s="1"/></row><row r="273" spans="3:7" x14ac:dyDescent="0.25"><c r="C273" s="1"/><c r="D273" s="1"/><c r="E273" s="1"/><c r="F273" s="1"/><c r="G273" s="1"/></row><row r="274" spans="3:7" x14ac:dyDescent="0.25"><c r="C274" s="1"/><c r="D274" s="1"/><c r="E274" s="1"/><c r="F274" s="1"/><c r="G274" s="1"/></row><row r="275" spans="3:7" x14ac:dyDescent="0.25"><c r="C275" s="1"/><c r="D275" s="1"/><c r="E275" s="1"/><c r="F275" s="1"/><c r="G275" s="1"/></row><row r="276" spans="3:7" x14ac:dyDescent="0.25"><c r="C276" s="1"/><c r="D276" s="1"/><c r="E276" s="1"/><c r="F276" s="1"/><c r="G276" s="1"/></row><row r="277" spans="3:7" x14ac:dyDescent="0.25"><c r="C277" s="1"/><c r="D277" s="1"/><c r="E277" s="1"/><c r="F277" s="1"/><c r="G277" s="1"/></row><row r="278" spans="3:7" x14ac:dyDescent="0.25"><c r="C278" s="1"/><c r="D278" s="1"/><c r="E278" s="1"/><c r="F278" s="1"/><c r="G278" s="1"/></row><row r="279" spans="3:7" x14ac:dyDescent="0.25"><c r="C279" s="1"/><c r="D279" s="1"/><c r="E279" s="1"/><c r="F279" s="1"/><c r="G279" s="1"/></row><row r="280" spans="3:7" x14ac:dyDescent="0.25"><c r="C280" s="1"/><c r="D280" s="1"/><c r="E280" s="1"/><c r="F280" s="1"/><c r="G280" s="1"/></row><row r="281" spans="3:7" x14ac:dyDescent="0.25"><c r="C281" s="1"/><c r="D281" s="1"/><c r="E281" s="1"/><c r="F281" s="1"/><c r="G281" s="1"/></row><row r="282" spans="3:7" x14ac:dyDescent="0.25"><c r="C282" s="1"/><c r="D282" s="1"/><c r="E282" s="1"/><c r="F282" s="1"/><c r="G282" s="1"/></row><row r="283" spans="3:7" x14ac:dyDescent="0.25"><c r="C283" s="1"/><c r="D283" s="1"/><c r="E283" s="1"/><c r="F283" s="1"/><c r="G283" s="1"/></row><row r="284" spans="3:7" x14ac:dyDescent="0.25"><c r="C284" s="1"/><c r="D284" s="1"/><c r="E284" s="1"/><c r="F284" s="1"/><c r="G284" s="1"/></row><row r="285" spans="3:7" x14ac:dyDescent="0.25"><c r="C285" s="1"/><c r="D285" s="1"/><c r="E285" s="1"/><c r="F285" s="1"/><c r="G285" s="1"/></row><row r="286" spans="3:7" x14ac:dyDescent="0.25"><c r="C286" s="1"/><c r="D286" s="1"/><c r="E286" s="1"/><c r="F286" s="1"/><c r="G286" s="1"/></row><row r="287" spans="3:7" x14ac:dyDescent="0.25"><c r="C287" s="1"/><c r="D287" s="1"/><c r="E287" s="1"/><c r="F287" s="1"/><c r="G287" s="1"/></row><row r="288" spans="3:7" x14ac:dyDescent="0.25"><c r="C288" s="1"/><c r="D288" s="1"/><c r="E288" s="1"/><c r="F288" s="1"/><c r="G288" s="1"/></row><row r="289" spans="3:7" x14ac:dyDescent="0.25"><c r="C289" s="1"/><c r="D289" s="1"/><c r="E289" s="1"/><c r="F289" s="1"/><c r="G289" s="1"/></row><row r="290" spans="3:7" x14ac:dyDescent="0.25"><c r="C290" s="1"/><c r="D290" s="1"/><c r="E290" s="1"/><c r="F290" s="1"/><c r="G290" s="1"/></row><row r="291" spans="3:7" x14ac:dyDescent="0.25"><c r="C291" s="1"/><c r="D291" s="1"/><c r="E291" s="1"/><c r="F291" s="1"/><c r="G291" s="1"/></row><row r="292" spans="3:7" x14ac:dyDescent="0.25"><c r="C292" s="1"/><c r="D292" s="1"/><c r="E292" s="1"/><c r="F292" s="1"/><c r="G292" s="1"/></row><row r="293" spans="3:7" x14ac:dyDescent="0.25"><c r="C293" s="1"/><c r="D293" s="1"/><c r="E293" s="1"/><c r="F293" s="1"/><c r="G293" s="1"/></row><row r="294" spans="3:7" x14ac:dyDescent="0.25"><c r="C294" s="1"/><c r="D294" s="1"/><c r="E294" s="1"/><c r="F294" s="1"/><c r="G294" s="1"/></row><row r="295" spans="3:7" x14ac:dyDescent="0.25"><c r="C295" s="1"/><c r="D295" s="1"/><c r="E295" s="1"/><c r="F295" s="1"/><c r="G295" s="1"/></row><row r="296" spans="3:7" x14ac:dyDescent="0.25"><c r="C296" s="1"/><c r="D296" s="1"/><c r="E296" s="1"/><c r="F296" s="1"/><c r="G296" s="1"/></row><row r="297" spans="3:7" x14ac:dyDescent="0.25"><c r="C297" s="1"/><c r="D297" s="1"/><c r="E297" s="1"/><c r="F297" s="1"/><c r="G297" s="1"/></row><row r="298" spans="3:7" x14ac:dyDescent="0.25"><c r="C298" s="1"/><c r="D298" s="1"/><c r="E298" s="1"/><c r="F298" s="1"/><c r="G298" s="1"/></row><row r="299" spans="3:7" x14ac:dyDescent="0.25"><c r="C299" s="1"/><c r="D299" s="1"/><c r="E299" s="1"/><c r="F299" s="1"/><c r="G299" s="1"/></row><row r="300" spans="3:7" x14ac:dyDescent="0.25"><c r="C300" s="1"/><c r="D300" s="1"/><c r="E300" s="1"/><c r="F300" s="1"/><c r="G300" s="1"/></row><row r="301" spans="3:7" x14ac:dyDescent="0.25"><c r="C301" s="1"/><c r="D301" s="1"/><c r="E301" s="1"/><c r="F301" s="1"/><c r="G301" s="1"/></row><row r="302" spans="3:7" x14ac:dyDescent="0.25"><c r="C302" s="1"/><c r="D302" s="1"/><c r="E302" s="1"/><c r="F302" s="1"/><c r="G302" s="1"/></row><row r="303" spans="3:7" x14ac:dyDescent="0.25"><c r="C303" s="1"/><c r="D303" s="1"/><c r="E303" s="1"/><c r="F303" s="1"/><c r="G303" s="1"/></row><row r="304" spans="3:7" x14ac:dyDescent="0.25"><c r="C304" s="1"/><c r="D304" s="1"/><c r="E304" s="1"/><c r="F304" s="1"/><c r="G304" s="1"/></row><row r="305" spans="3:7" x14ac:dyDescent="0.25"><c r="C305" s="1"/><c r="D305" s="1"/><c r="E305" s="1"/><c r="F305" s="1"/><c r="G305" s="1"/></row><row r="306" spans="3:7" x14ac:dyDescent="0.25"><c r="C306" s="1"/><c r="D306" s="1"/><c r="E306" s="1"/><c r="F306" s="1"/><c r="G306" s="1"/></row><row r="307" spans="3:7" x14ac:dyDescent="0.25"><c r="C307" s="1"/><c r="D307" s="1"/><c r="E307" s="1"/><c r="F307" s="1"/><c r="G307" s="1"/></row><row r="308" spans="3:7" x14ac:dyDescent="0.25"><c r="C308" s="1"/><c r="D308" s="1"/><c r="E308" s="1"/><c r="F308" s="1"/><c r="G308" s="1"/></row><row r="309" spans="3:7" x14ac:dyDescent="0.25"><c r="C309" s="1"/><c r="D309" s="1"/><c r="E309" s="1"/><c r="F309" s="1"/><c r="G309" s="1"/></row><row r="310" spans="3:7" x14ac:dyDescent="0.25"><c r="C310" s="1"/><c r="D310" s="1"/><c r="E310" s="1"/><c r="F310" s="1"/><c r="G310" s="1"/></row><row r="311" spans="3:7" x14ac:dyDescent="0.25"><c r="C311" s="1"/><c r="D311" s="1"/><c r="E311" s="1"/><c r="F311" s="1"/><c r="G311" s="1"/></row><row r="312" spans="3:7" x14ac:dyDescent="0.25"><c r="C312" s="1"/><c r="D312" s="1"/><c r="E312" s="1"/><c r="F312" s="1"/><c r="G312" s="1"/></row><row r="313" spans="3:7" x14ac:dyDescent="0.25"><c r="C313" s="1"/><c r="D313" s="1"/><c r="E313" s="1"/><c r="F313" s="1"/><c r="G313" s="1"/></row><row r="314" spans="3:7" x14ac:dyDescent="0.25"><c r="C314" s="1"/><c r="D314" s="1"/><c r="E314" s="1"/><c r="F314" s="1"/><c r="G314" s="1"/></row><row r="315" spans="3:7" x14ac:dyDescent="0.25"><c r="C315" s="1"/><c r="D315" s="1"/><c r="E315" s="1"/><c r="F315" s="1"/><c r="G315" s="1"/></row><row r="316" spans="3:7" x14ac:dyDescent="0.25"><c r="C316" s="1"/><c r="D316" s="1"/><c r="E316" s="1"/><c r="F316" s="1"/><c r="G316" s="1"/></row><row r="317" spans="3:7" x14ac:dyDescent="0.25"><c r="C317" s="1"/><c r="D317" s="1"/><c r="E317" s="1"/><c r="F317" s="1"/><c r="G317" s="1"/></row><row r="318" spans="3:7" x14ac:dyDescent="0.25"><c r="C318" s="1"/><c r="D318" s="1"/><c r="E318" s="1"/><c r="F318" s="1"/><c r="G318" s="1"/></row><row r="319" spans="3:7" x14ac:dyDescent="0.25"><c r="C319" s="1"/><c r="D319" s="1"/><c r="E319" s="1"/><c r="F319" s="1"/><c r="G319" s="1"/></row><row r="320" spans="3:7" x14ac:dyDescent="0.25"><c r="C320" s="1"/><c r="D320" s="1"/><c r="E320" s="1"/><c r="F320" s="1"/><c r="G320" s="1"/></row><row r="321" spans="3:7" x14ac:dyDescent="0.25"><c r="C321" s="1"/><c r="D321" s="1"/><c r="E321" s="1"/><c r="F321" s="1"/><c r="G321" s="1"/></row><row r="322" spans="3:7" x14ac:dyDescent="0.25"><c r="C322" s="1"/><c r="D322" s="1"/><c r="E322" s="1"/><c r="F322" s="1"/><c r="G322" s="1"/></row><row r="323" spans="3:7" x14ac:dyDescent="0.25"><c r="C323" s="1"/><c r="D323" s="1"/><c r="E323" s="1"/><c r="F323" s="1"/><c r="G323" s="1"/></row><row r="324" spans="3:7" x14ac:dyDescent="0.25"><c r="C324" s="1"/><c r="D324" s="1"/><c r="E324" s="1"/><c r="F324" s="1"/><c r="G324" s="1"/></row></sheetData><pageMargins left="0.75" right="0.75" top="1" bottom="1" header="0.5" footer="0.5"/><pageSetup paperSize="0" orientation="portrait" horizontalDpi="0" verticalDpi="0" copies="0"/><headerFooter alignWithMargins="0"/></worksheet>